Workbook

Sheet 合计
A1: 2026年各平台边界利润汇总 (单位: CNY)
D2: 全年 | R2: 1月 | AG2: 2月 | AV2: 3月 | BK2: 4月 | BZ2: 5月 | CO2: 6月 | DD2: 7月 | DS2: 8月 | EH2: 9月 | EW2: 10月 | FL2: 11月 | GA2: 12月
D3: AMAZON | F3: TEMU | H3: SHEIN | J3: TK | L3: 综合部 | N3: 技术部 | P3: 合计 | R3: AMAZON | T3: TEMU | V3: SHEIN | X3: TK | Z3: 综合部 | AB3: 技术部 | AD3: 合计 | AF3: 环比 | AG3: AMAZON | AI3: TEMU | AK3: SHEIN | AM3: TK | AO3: 综合部 | AQ3: 技术部 | AS3: 合计 | AU3: 环比 | AV3: AMAZON | AX3: TEMU | AZ3: SHEIN | BB3: TK | BD3: 综合部 | BF3: 技术部 | BH3: 合计 | BJ3: 环比 | BK3: AMAZON | BM3: TEMU | BO3: SHEIN | BQ3: TK | BS3: 综合部 | BU3: 技术部 | BW3: 合计 | BY3: 环比 | BZ3: AMAZON | CB3: TEMU | CD3: SHEIN | CF3: TK | CH3: 综合部 | CJ3: 技术部 | CL3: 合计 | CN3: 环比 | CO3: AMAZON | CQ3: TEMU | CS3: SHEIN | CU3: TK | CW3: 综合部 | CY3: 技术部 | DA3: 合计 | DC3: 环比 | DD3: AMAZON | DF3: TEMU | DH3: SHEIN | DJ3: TK | DL3: 综合部 | DN3: 技术部 | DP3: 合计 | DR3: 环比 | DS3: AMAZON | DU3: TEMU | DW3: SHEIN | DY3: TK | EA3: 综合部 | EC3: 技术部 | EE3: 合计 | EG3: 环比 | EH3: AMAZON | EJ3: TEMU | EL3: SHEIN | EN3: TK | EP3: 综合部 | ER3: 技术部 | ET3: 合计 | EV3: 环比 | EW3: AMAZON | EY3: TEMU | FA3: SHEIN | FC3: TK | FE3: 综合部 | FG3: 技术部 | FI3: 合计 | FK3: 环比 | FL3: AMAZON | FN3: TEMU | FP3: SHEIN | FR3: TK | FT3: 综合部 | FV3: 技术部 | FX3: 合计 | FZ3: 环比 | GA3: AMAZON | GC3: TEMU | GE3: SHEIN | GG3: TK | GI3: 综合部 | GK3: 技术部 | GM3: 合计 | GO3: 环比
A4: 科目大类 | B4: 科目明细 | C4: 单位 | D4: 金额 | E4: 占比 | F4: 金额 | G4: 占比 | H4: 金额 | I4: 占比 | J4: 金额 | K4: 占比 | L4: 金额 | M4: 比例 | N4: 金额 | O4: 比例 | P4: 金额 | Q4: 比例 | R4: 合计 | S4: 占比 | T4: 合计 | U4: 占比 | V4: 合计 | W4: 占比 | X4: 合计 | Y4: 占比 | Z4: 金额 | AA4: 比例 | AB4: 金额 | AC4: 比例 | AD4: 金额 | AE4: 比例 | AF4: 环比 | AG4: 合计 | AH4: 占比 | AI4: 合计 | AJ4: 占比 | AK4: 合计 | AL4: 占比 | AM4: 合计 | AN4: 占比 | AO4: 金额 | AP4: 比例 | AQ4: 金额 | AR4: 比例 | AS4: 金额 | AT4: 比例 | AU4: 环比 | AV4: 合计 | AW4: 占比 | AX4: 合计 | AY4: 占比 | AZ4: 合计 | BA4: 占比 | BB4: 合计 | BC4: 占比 | BD4: 金额 | BE4: 比例 | BF4: 金额 | BG4: 比例 | BH4: 金额 | BI4: 比例 | BJ4: 环比 | BK4: 合计 | BL4: 占比 | BM4: 合计 | BN4: 占比 | BO4: 合计 | BP4: 占比 | BQ4: 合计 | BR4: 占比 | BS4: 金额 | BT4: 比例 | BU4: 金额 | BV4: 比例 | BW4: 金额 | BX4: 比例 | BY4: 环比 | BZ4: 合计 | CA4: 占比 | CB4: 合计 | CC4: 占比 | CD4: 合计 | CE4: 占比 | CF4: 合计 | CG4: 占比 | CH4: 金额 | CI4: 比例 | CJ4: 金额 | CK4: 比例 | CL4: 金额 | CM4: 比例 | CN4: 环比 | CO4: 合计 | CP4: 占比 | CQ4: 合计 | CR4: 占比 | CS4: 合计 | CT4: 占比 | CU4: 合计 | CV4: 占比 | CW4: 金额 | CX4: 比例 | CY4: 金额 | CZ4: 比例 | DA4: 金额 | DB4: 比例 | DC4: 环比 | DD4: 合计 | DE4: 占比 | DF4: 合计 | DG4: 占比 | DH4: 合计 | DI4: 占比 | DJ4: 合计 | DK4: 占比 | DL4: 金额 | DM4: 比例 | DN4: 金额 | DO4: 比例 | DP4: 金额 | DQ4: 比例 | DR4: 环比 | DS4: 合计 | DT4: 占比 | DU4: 合计 | DV4: 占比 | DW4: 合计 | DX4: 占比 | DY4: 合计 | DZ4: 占比 | EA4: 金额 | EB4: 比例 | EC4: 金额 | ED4: 比例 | EE4: 金额 | EF4: 比例 | EG4: 环比 | EH4: 合计 | EI4: 占比 | EJ4: 合计 | EK4: 占比 | EL4: 合计 | EM4: 占比 | EN4: 合计 | EO4: 占比 | EP4: 金额 | EQ4: 比例 | ER4: 金额 | ES4: 比例 | ET4: 金额 | EU4: 比例 | EV4: 环比 | EW4: 合计 | EX4: 占比 | EY4: 合计 | EZ4: 占比 | FA4: 合计 | FB4: 占比 | FC4: 合计 | FD4: 占比 | FE4: 金额 | FF4: 比例 | FG4: 金额 | FH4: 比例 | FI4: 金额 | FJ4: 比例 | FK4: 环比 | FL4: 合计 | FM4: 占比 | FN4: 合计 | FO4: 占比 | FP4: 合计 | FQ4: 占比 | FR4: 合计 | FS4: 占比 | FT4: 金额 | FU4: 比例 | FV4: 金额 | FW4: 比例 | FX4: 金额 | FY4: 比例 | FZ4: 环比 | GA4: 合计 | GB4: 占比 | GC4: 合计 | GD4: 占比 | GE4: 合计 | GF4: 占比 | GG4: 合计 | GH4: 占比 | GI4: 金额 | GJ4: 比例 | GK4: 金额 | GL4: 比例 | GM4: 金额 | GN4: 比例 | GO4: 环比
A5: 净销售量 | C5: 件 | D5: =AMAZON!F4 -> 0 | F5: =TEMU!F4 -> 0 | H5: =SHEIN!F4 -> 0 | J5: =TK!F4 -> 0 | P5: =D5+F5+H5+J5+L5+N5 -> 0 | Q5: =IFERROR(P5/(D11+F11+H11+J11),0) -> 0 | R5: =AMAZON!H4 -> 0 | T5: =TEMU!H4 -> 0 | V5: =SHEIN!H4 -> 0 | X5: =TK!H4 -> 0 | AD5: =R5+T5+V5+X5+Z5+AB5 -> 0 | AE5: =IFERROR(AD5/(R11+T11+V11+X11),0) -> 0 | AG5: =AMAZON!J4 -> 0 | AI5: =TEMU!J4 -> 0 | AK5: =SHEIN!J4 -> 0 | AM5: =TK!J4 -> 0 | AS5: =AG5+AI5+AK5+AM5+AO5+AQ5 -> 0 | AT5: =IFERROR(AS5/(AG11+AI11+AK11+AM11),0) -> 0 | AU5: =IFERROR((AS5-AD5)/AD5,0) -> 0 | AV5: =AMAZON!L4 -> 0 | AX5: =TEMU!L4 -> 0 | AZ5: =SHEIN!L4 -> 0 | BB5: =TK!L4 -> 0 | BH5: =AV5+AX5+AZ5+BB5+BD5+BF5 -> 0 | BI5: =IFERROR(BH5/(AV11+AX11+AZ11+BB11),0) -> 0 | BJ5: =IFERROR((BH5-AS5)/AS5,0) -> 0 | BK5: =AMAZON!N4 -> 0 | BM5: =TEMU!N4 -> 0 | BO5: =SHEIN!N4 -> 0 | BQ5: =TK!N4 -> 0 | BW5: =BK5+BM5+BO5+BQ5+BS5+BU5 -> 0 | BX5: =IFERROR(BW5/(BK11+BM11+BO11+BQ11),0) -> 0 | BY5: =IFERROR((BW5-BH5)/BH5,0) -> 0 | BZ5: =AMAZON!P4 -> 0 | CB5: =TEMU!P4 -> 0 | CD5: =SHEIN!P4 -> 0 | CF5: =TK!P4 -> 0 | CL5: =BZ5+CB5+CD5+CF5+CH5+CJ5 -> 0 | CM5: =IFERROR(CL5/(BZ11+CB11+CD11+CF11),0) -> 0 | CN5: =IFERROR((CL5-BW5)/BW5,0) -> 0 | CO5: =AMAZON!R4 -> 0 | CQ5: =TEMU!R4 -> 0 | CS5: =SHEIN!R4 -> 0 | CU5: =TK!R4 -> 0 | DA5: =CO5+CQ5+CS5+CU5+CW5+CY5 -> 0 | DB5: =IFERROR(DA5/(CO11+CQ11+CS11+CU11),0) -> 0 | DC5: =IFERROR((DA5-CL5)/CL5,0) -> 0 | DD5: =AMAZON!T4 -> 0 | DF5: =TEMU!T4 -> 0 | DH5: =SHEIN!T4 -> 0 | DJ5: =TK!T4 -> 0 | DP5: =DD5+DF5+DH5+DJ5+DL5+DN5 -> 0 | DQ5: =IFERROR(DP5/(DD11+DF11+DH11+DJ11),0) -> 0 | DR5: =IFERROR((DP5-DA5)/DA5,0) -> 0 | DS5: =AMAZON!V4 -> 0 | DU5: =TEMU!V4 -> 0 | DW5: =SHEIN!V4 -> 0 | DY5: =TK!V4 -> 0 | EE5: =DS5+DU5+DW5+DY5+EA5+EC5 -> 0 | EF5: =IFERROR(EE5/(DS11+DU11+DW11+DY11),0) -> 0 | EG5: =IFERROR((EE5-DP5)/DP5,0) -> 0 | EH5: =AMAZON!X4 -> 0 | EJ5: =TEMU!X4 -> 0 | EL5: =SHEIN!X4 -> 0 | EN5: =TK!X4 -> 0 | ET5: =EH5+EJ5+EL5+EN5+EP5+ER5 -> 0 | EU5: =IFERROR(ET5/(EH11+EJ11+EL11+EN11),0) -> 0 | EV5: =IFERROR((ET5-EE5)/EE5,0) -> 0 | EW5: =AMAZON!Z4 -> 0 | EY5: =TEMU!Z4 -> 0 | FA5: =SHEIN!Z4 -> 0 | FC5: =TK!Z4 -> 0 | FI5: =EW5+EY5+FA5+FC5+FE5+FG5 -> 0 | FJ5: =IFERROR(FI5/(EW11+EY11+FA11+FC11),0) -> 0 | FK5: =IFERROR((FI5-ET5)/ET5,0) -> 0 | FL5: =AMAZON!AB4 -> 0 | FN5: =TEMU!AB4 -> 0 | FP5: =SHEIN!AB4 -> 0 | FR5: =TK!AB4 -> 0 | FX5: =FL5+FN5+FP5+FR5+FT5+FV5 -> 0 | FY5: =IFERROR(FX5/(FL11+FN11+FP11+FR11),0) -> 0 | FZ5: =IFERROR((FX5-FI5)/FI5,0) -> 0 | GA5: =AMAZON!AD4 -> 0 | GC5: =TEMU!AD4 -> 0 | GE5: =SHEIN!AD4 -> 0 | GG5: =TK!AD4 -> 0 | GM5: =GA5+GC5+GE5+GG5+GI5+GK5 -> 0 | GN5: =IFERROR(GM5/(GA11+GC11+GE11+GG11),0) -> 0 | GO5: =IFERROR((GM5-FX5)/FX5,0) -> 0
A6: 净销售量 | B6: 销售量 | C6: 件 | D6: =AMAZON!F13 -> 0 | F6: =TEMU!F8 -> 0 | H6: =SHEIN!F7 -> 0 | J6: =TK!F8 -> 0 | P6: =D6+F6+H6+J6+L6+N6 -> 0 | Q6: =IFERROR(P6/(D11+F11+H11+J11),0) -> 0 | R6: =AMAZON!H13 -> 0 | T6: =TEMU!H8 -> 0 | V6: =SHEIN!H7 -> 0 | X6: =TK!H8 -> 0 | AD6: =R6+T6+V6+X6+Z6+AB6 -> 0 | AE6: =IFERROR(AD6/(R11+T11+V11+X11),0) -> 0 | AG6: =AMAZON!J13 -> 0 | AI6: =TEMU!J8 -> 0 | AK6: =SHEIN!J7 -> 0 | AM6: =TK!J8 -> 0 | AS6: =AG6+AI6+AK6+AM6+AO6+AQ6 -> 0 | AT6: =IFERROR(AS6/(AG11+AI11+AK11+AM11),0) -> 0 | AU6: =IFERROR((AS6-AD6)/AD6,0) -> 0 | AV6: =AMAZON!L13 -> 0 | AX6: =TEMU!L8 -> 0 | AZ6: =SHEIN!L7 -> 0 | BB6: =TK!L8 -> 0 | BH6: =AV6+AX6+AZ6+BB6+BD6+BF6 -> 0 | BI6: =IFERROR(BH6/(AV11+AX11+AZ11+BB11),0) -> 0 | BJ6: =IFERROR((BH6-AS6)/AS6,0) -> 0 | BK6: =AMAZON!N13 -> 0 | BM6: =TEMU!N8 -> 0 | BO6: =SHEIN!N7 -> 0 | BQ6: =TK!N8 -> 0 | BW6: =BK6+BM6+BO6+BQ6+BS6+BU6 -> 0 | BX6: =IFERROR(BW6/(BK11+BM11+BO11+BQ11),0) -> 0 | BY6: =IFERROR((BW6-BH6)/BH6,0) -> 0 | BZ6: =AMAZON!P13 -> 0 | CB6: =TEMU!P8 -> 0 | CD6: =SHEIN!P7 -> 0 | CF6: =TK!P8 -> 0 | CL6: =BZ6+CB6+CD6+CF6+CH6+CJ6 -> 0 | CM6: =IFERROR(CL6/(BZ11+CB11+CD11+CF11),0) -> 0 | CN6: =IFERROR((CL6-BW6)/BW6,0) -> 0 | CO6: =AMAZON!R13 -> 0 | CQ6: =TEMU!R8 -> 0 | CS6: =SHEIN!R7 -> 0 | CU6: =TK!R8 -> 0 | DA6: =CO6+CQ6+CS6+CU6+CW6+CY6 -> 0 | DB6: =IFERROR(DA6/(CO11+CQ11+CS11+CU11),0) -> 0 | DC6: =IFERROR((DA6-CL6)/CL6,0) -> 0 | DD6: =AMAZON!T13 -> 0 | DF6: =TEMU!T8 -> 0 | DH6: =SHEIN!T7 -> 0 | DJ6: =TK!T8 -> 0 | DP6: =DD6+DF6+DH6+DJ6+DL6+DN6 -> 0 | DQ6: =IFERROR(DP6/(DD11+DF11+DH11+DJ11),0) -> 0 | DR6: =IFERROR((DP6-DA6)/DA6,0) -> 0 | DS6: =AMAZON!V13 -> 0 | DU6: =TEMU!V8 -> 0 | DW6: =SHEIN!V7 -> 0 | DY6: =TK!V8 -> 0 | EE6: =DS6+DU6+DW6+DY6+EA6+EC6 -> 0 | EF6: =IFERROR(EE6/(DS11+DU11+DW11+DY11),0) -> 0 | EG6: =IFERROR((EE6-DP6)/DP6,0) -> 0 | EH6: =AMAZON!X13 -> 0 | EJ6: =TEMU!X8 -> 0 | EL6: =SHEIN!X7 -> 0 | EN6: =TK!X8 -> 0 | ET6: =EH6+EJ6+EL6+EN6+EP6+ER6 -> 0 | EU6: =IFERROR(ET6/(EH11+EJ11+EL11+EN11),0) -> 0 | EV6: =IFERROR((ET6-EE6)/EE6,0) -> 0 | EW6: =AMAZON!Z13 -> 0 | EY6: =TEMU!Z8 -> 0 | FA6: =SHEIN!Z7 -> 0 | FC6: =TK!Z8 -> 0 | FI6: =EW6+EY6+FA6+FC6+FE6+FG6 -> 0 | FJ6: =IFERROR(FI6/(EW11+EY11+FA11+FC11),0) -> 0 | FK6: =IFERROR((FI6-ET6)/ET6,0) -> 0 | FL6: =AMAZON!AB13 -> 0 | FN6: =TEMU!AB8 -> 0 | FP6: =SHEIN!AB7 -> 0 | FR6: =TK!AB8 -> 0 | FX6: =FL6+FN6+FP6+FR6+FT6+FV6 -> 0 | FY6: =IFERROR(FX6/(FL11+FN11+FP11+FR11),0) -> 0 | FZ6: =IFERROR((FX6-FI6)/FI6,0) -> 0 | GA6: =AMAZON!AD13 -> 0 | GC6: =TEMU!AD8 -> 0 | GE6: =SHEIN!AD7 -> 0 | GG6: =TK!AD8 -> 0 | GM6: =GA6+GC6+GE6+GG6+GI6+GK6 -> 0 | GN6: =IFERROR(GM6/(GA11+GC11+GE11+GG11),0) -> 0 | GO6: =IFERROR((GM6-FX6)/FX6,0) -> 0
A7: 净销售量 | B7: 退款量 | C7: 件 | D7: =AMAZON!F22 -> 0 | F7: =TEMU!F12 -> 0 | H7: =SHEIN!F10 -> 0 | J7: =TK!F12 -> 0 | P7: =D7+F7+H7+J7+L7+N7 -> 0 | Q7: =IFERROR(P7/(D11+F11+H11+J11),0) -> 0 | R7: =AMAZON!H22 -> 0 | T7: =TEMU!H12 -> 0 | V7: =SHEIN!H10 -> 0 | X7: =TK!H12 -> 0 | AD7: =R7+T7+V7+X7+Z7+AB7 -> 0 | AE7: =IFERROR(AD7/(R11+T11+V11+X11),0) -> 0 | AG7: =AMAZON!J22 -> 0 | AI7: =TEMU!J12 -> 0 | AK7: =SHEIN!J10 -> 0 | AM7: =TK!J12 -> 0 | AS7: =AG7+AI7+AK7+AM7+AO7+AQ7 -> 0 | AT7: =IFERROR(AS7/(AG11+AI11+AK11+AM11),0) -> 0 | AU7: =IFERROR((AS7-AD7)/AD7,0) -> 0 | AV7: =AMAZON!L22 -> 0 | AX7: =TEMU!L12 -> 0 | AZ7: =SHEIN!L10 -> 0 | BB7: =TK!L12 -> 0 | BH7: =AV7+AX7+AZ7+BB7+BD7+BF7 -> 0 | BI7: =IFERROR(BH7/(AV11+AX11+AZ11+BB11),0) -> 0 | BJ7: =IFERROR((BH7-AS7)/AS7,0) -> 0 | BK7: =AMAZON!N22 -> 0 | BM7: =TEMU!N12 -> 0 | BO7: =SHEIN!N10 -> 0 | BQ7: =TK!N12 -> 0 | BW7: =BK7+BM7+BO7+BQ7+BS7+BU7 -> 0 | BX7: =IFERROR(BW7/(BK11+BM11+BO11+BQ11),0) -> 0 | BY7: =IFERROR((BW7-BH7)/BH7,0) -> 0 | BZ7: =AMAZON!P22 -> 0 | CB7: =TEMU!P12 -> 0 | CD7: =SHEIN!P10 -> 0 | CF7: =TK!P12 -> 0 | CL7: =BZ7+CB7+CD7+CF7+CH7+CJ7 -> 0 | CM7: =IFERROR(CL7/(BZ11+CB11+CD11+CF11),0) -> 0 | CN7: =IFERROR((CL7-BW7)/BW7,0) -> 0 | CO7: =AMAZON!R22 -> 0 | CQ7: =TEMU!R12 -> 0 | CS7: =SHEIN!R10 -> 0 | CU7: =TK!R12 -> 0 | DA7: =CO7+CQ7+CS7+CU7+CW7+CY7 -> 0 | DB7: =IFERROR(DA7/(CO11+CQ11+CS11+CU11),0) -> 0 | DC7: =IFERROR((DA7-CL7)/CL7,0) -> 0 | DD7: =AMAZON!T22 -> 0 | DF7: =TEMU!T12 -> 0 | DH7: =SHEIN!T10 -> 0 | DJ7: =TK!T12 -> 0 | DP7: =DD7+DF7+DH7+DJ7+DL7+DN7 -> 0 | DQ7: =IFERROR(DP7/(DD11+DF11+DH11+DJ11),0) -> 0 | DR7: =IFERROR((DP7-DA7)/DA7,0) -> 0 | DS7: =AMAZON!V22 -> 0 | DU7: =TEMU!V12 -> 0 | DW7: =SHEIN!V10 -> 0 | DY7: =TK!V12 -> 0 | EE7: =DS7+DU7+DW7+DY7+EA7+EC7 -> 0 | EF7: =IFERROR(EE7/(DS11+DU11+DW11+DY11),0) -> 0 | EG7: =IFERROR((EE7-DP7)/DP7,0) -> 0 | EH7: =AMAZON!X22 -> 0 | EJ7: =TEMU!X12 -> 0 | EL7: =SHEIN!X10 -> 0 | EN7: =TK!X12 -> 0 | ET7: =EH7+EJ7+EL7+EN7+EP7+ER7 -> 0 | EU7: =IFERROR(ET7/(EH11+EJ11+EL11+EN11),0) -> 0 | EV7: =IFERROR((ET7-EE7)/EE7,0) -> 0 | EW7: =AMAZON!Z22 -> 0 | EY7: =TEMU!Z12 -> 0 | FA7: =SHEIN!Z10 -> 0 | FC7: =TK!Z12 -> 0 | FI7: =EW7+EY7+FA7+FC7+FE7+FG7 -> 0 | FJ7: =IFERROR(FI7/(EW11+EY11+FA11+FC11),0) -> 0 | FK7: =IFERROR((FI7-ET7)/ET7,0) -> 0 | FL7: =AMAZON!AB22 -> 0 | FN7: =TEMU!AB12 -> 0 | FP7: =SHEIN!AB10 -> 0 | FR7: =TK!AB12 -> 0 | FX7: =FL7+FN7+FP7+FR7+FT7+FV7 -> 0 | FY7: =IFERROR(FX7/(FL11+FN11+FP11+FR11),0) -> 0 | FZ7: =IFERROR((FX7-FI7)/FI7,0) -> 0 | GA7: =AMAZON!AD22 -> 0 | GC7: =TEMU!AD12 -> 0 | GE7: =SHEIN!AD10 -> 0 | GG7: =TK!AD12 -> 0 | GM7: =GA7+GC7+GE7+GG7+GI7+GK7 -> 0 | GN7: =IFERROR(GM7/(GA11+GC11+GE11+GG11),0) -> 0 | GO7: =IFERROR((GM7-FX7)/FX7,0) -> 0
A8: 毛利率 | C8: % | D8: =IFERROR(AMAZON!F31,"") -> 0 | F8: =IFERROR(TEMU!F16,"") -> 0 | H8: =IFERROR(SHEIN!F13,"") -> 0 | J8: =IFERROR(TK!F16,"") -> 0 | P8: =D8+F8+H8+J8+L8+N8 -> 0 | Q8: =IFERROR(P8/(D11+F11+H11+J11),0) -> 0 | R8: =IFERROR(AMAZON!H31,"") | T8: =IFERROR(TEMU!H16,"") | V8: =IFERROR(SHEIN!H13,"") | X8: =IFERROR(TK!H16,"") | AD8: =R8+T8+V8+X8+Z8+AB8 -> #VALUE! | AE8: =IFERROR(AD8/(R11+T11+V11+X11),0) -> 0 | AG8: =IFERROR(AMAZON!J31,"") | AI8: =IFERROR(TEMU!J16,"") | AK8: =IFERROR(SHEIN!J13,"") | AM8: =IFERROR(TK!J16,"") | AS8: =AG8+AI8+AK8+AM8+AO8+AQ8 -> #VALUE! | AT8: =IFERROR(AS8/(AG11+AI11+AK11+AM11),0) -> 0 | AU8: =IFERROR((AS8-AD8)/AD8,0) -> 0 | AV8: =IFERROR(AMAZON!L31,"") | AX8: =IFERROR(TEMU!L16,"") | AZ8: =IFERROR(SHEIN!L13,"") | BB8: =IFERROR(TK!L16,"") | BH8: =AV8+AX8+AZ8+BB8+BD8+BF8 -> #VALUE! | BI8: =IFERROR(BH8/(AV11+AX11+AZ11+BB11),0) -> 0 | BJ8: =IFERROR((BH8-AS8)/AS8,0) -> 0 | BK8: =IFERROR(AMAZON!N31,"") | BM8: =IFERROR(TEMU!N16,"") | BO8: =IFERROR(SHEIN!N13,"") | BQ8: =IFERROR(TK!N16,"") | BW8: =BK8+BM8+BO8+BQ8+BS8+BU8 -> #VALUE! | BX8: =IFERROR(BW8/(BK11+BM11+BO11+BQ11),0) -> 0 | BY8: =IFERROR((BW8-BH8)/BH8,0) -> 0 | BZ8: =IFERROR(AMAZON!P31,"") | CB8: =IFERROR(TEMU!P16,"") | CD8: =IFERROR(SHEIN!P13,"") | CF8: =IFERROR(TK!P16,"") | CL8: =BZ8+CB8+CD8+CF8+CH8+CJ8 -> #VALUE! | CM8: =IFERROR(CL8/(BZ11+CB11+CD11+CF11),0) -> 0 | CN8: =IFERROR((CL8-BW8)/BW8,0) -> 0 | CO8: =IFERROR(AMAZON!R31,"") | CQ8: =IFERROR(TEMU!R16,"") | CS8: =IFERROR(SHEIN!R13,"") | CU8: =IFERROR(TK!R16,"") | DA8: =CO8+CQ8+CS8+CU8+CW8+CY8 -> #VALUE! | DB8: =IFERROR(DA8/(CO11+CQ11+CS11+CU11),0) -> 0 | DC8: =IFERROR((DA8-CL8)/CL8,0) -> 0 | DD8: =IFERROR(AMAZON!T31,"") | DF8: =IFERROR(TEMU!T16,"") | DH8: =IFERROR(SHEIN!T13,"") | DJ8: =IFERROR(TK!T16,"") | DP8: =DD8+DF8+DH8+DJ8+DL8+DN8 -> #VALUE! | DQ8: =IFERROR(DP8/(DD11+DF11+DH11+DJ11),0) -> 0 | DR8: =IFERROR((DP8-DA8)/DA8,0) -> 0 | DS8: =IFERROR(AMAZON!V31,"") | DU8: =IFERROR(TEMU!V16,"") | DW8: =IFERROR(SHEIN!V13,"") | DY8: =IFERROR(TK!V16,"") | EE8: =DS8+DU8+DW8+DY8+EA8+EC8 -> #VALUE! | EF8: =IFERROR(EE8/(DS11+DU11+DW11+DY11),0) -> 0 | EG8: =IFERROR((EE8-DP8)/DP8,0) -> 0 | EH8: =IFERROR(AMAZON!X31,"") | EJ8: =IFERROR(TEMU!X16,"") | EL8: =IFERROR(SHEIN!X13,"") | EN8: =IFERROR(TK!X16,"") | ET8: =EH8+EJ8+EL8+EN8+EP8+ER8 -> #VALUE! | EU8: =IFERROR(ET8/(EH11+EJ11+EL11+EN11),0) -> 0 | EV8: =IFERROR((ET8-EE8)/EE8,0) -> 0 | EW8: =IFERROR(AMAZON!Z31,"") | EY8: =IFERROR(TEMU!Z16,"") | FA8: =IFERROR(SHEIN!Z13,"") | FC8: =IFERROR(TK!Z16,"") | FI8: =EW8+EY8+FA8+FC8+FE8+FG8 -> #VALUE! | FJ8: =IFERROR(FI8/(EW11+EY11+FA11+FC11),0) -> 0 | FK8: =IFERROR((FI8-ET8)/ET8,0) -> 0 | FL8: =IFERROR(AMAZON!AB31,"") | FN8: =IFERROR(TEMU!AB16,"") | FP8: =IFERROR(SHEIN!AB13,"") | FR8: =IFERROR(TK!AB16,"") | FX8: =FL8+FN8+FP8+FR8+FT8+FV8 -> #VALUE! | FY8: =IFERROR(FX8/(FL11+FN11+FP11+FR11),0) -> 0 | FZ8: =IFERROR((FX8-FI8)/FI8,0) -> 0 | GA8: =IFERROR(AMAZON!AD31,"") | GC8: =IFERROR(TEMU!AD16,"") | GE8: =IFERROR(SHEIN!AD13,"") | GG8: =IFERROR(TK!AD16,"") | GM8: =GA8+GC8+GE8+GG8+GI8+GK8 -> #VALUE! | GN8: =IFERROR(GM8/(GA11+GC11+GE11+GG11),0) -> 0 | GO8: =IFERROR((GM8-FX8)/FX8,0) -> 0
A9: 经营收入 | C9: 元 | D9: =AMAZON!F40 -> 0 | E9: =IFERROR(D9/AMAZON!F50,0) -> 0 | F9: =TEMU!F20 -> 0 | G9: =IFERROR(F9/TEMU!F25,0) -> 0 | H9: =SHEIN!F16 -> 0 | I9: =IFERROR(H9/SHEIN!F20,0) -> 0 | J9: =TK!F20 -> 0 | K9: =IFERROR(J9/TK!F25,0) -> 0 | P9: =D9+F9+H9+J9+L9+N9 -> 0 | Q9: =IFERROR(P9/(D11+F11+H11+J11),0) -> 0 | R9: =AMAZON!H40 -> 0 | S9: =IFERROR(R9/AMAZON!H50,0) -> 0 | T9: =TEMU!H20 -> 0 | U9: =IFERROR(T9/TEMU!H25,0) -> 0 | V9: =SHEIN!H16 -> 0 | W9: =IFERROR(V9/SHEIN!H20,0) -> 0 | X9: =TK!H20 -> 0 | Y9: =IFERROR(X9/TK!H25,0) -> 0 | AD9: =R9+T9+V9+X9+Z9+AB9 -> 0 | AE9: =IFERROR(AD9/(R11+T11+V11+X11),0) -> 0 | AG9: =AMAZON!J40 -> 0 | AH9: =IFERROR(AG9/AMAZON!J50,0) -> 0 | AI9: =TEMU!J20 -> 0 | AJ9: =IFERROR(AI9/TEMU!J25,0) -> 0 | AK9: =SHEIN!J16 -> 0 | AL9: =IFERROR(AK9/SHEIN!J20,0) -> 0 | AM9: =TK!J20 -> 0 | AN9: =IFERROR(AM9/TK!J25,0) -> 0 | AS9: =AG9+AI9+AK9+AM9+AO9+AQ9 -> 0 | AT9: =IFERROR(AS9/(AG11+AI11+AK11+AM11),0) -> 0 | AU9: =IFERROR((AS9-AD9)/AD9,0) -> 0 | AV9: =AMAZON!L40 -> 0 | AW9: =IFERROR(AV9/AMAZON!L50,0) -> 0 | AX9: =TEMU!L20 -> 0 | AY9: =IFERROR(AX9/TEMU!L25,0) -> 0 | AZ9: =SHEIN!L16 -> 0 | BA9: =IFERROR(AZ9/SHEIN!L20,0) -> 0 | BB9: =TK!L20 -> 0 | BC9: =IFERROR(BB9/TK!L25,0) -> 0 | BH9: =AV9+AX9+AZ9+BB9+BD9+BF9 -> 0 | BI9: =IFERROR(BH9/(AV11+AX11+AZ11+BB11),0) -> 0 | BJ9: =IFERROR((BH9-AS9)/AS9,0) -> 0 | BK9: =AMAZON!N40 -> 0 | BL9: =IFERROR(BK9/AMAZON!N50,0) -> 0 | BM9: =TEMU!N20 -> 0 | BN9: =IFERROR(BM9/TEMU!N25,0) -> 0 | BO9: =SHEIN!N16 -> 0 | BP9: =IFERROR(BO9/SHEIN!N20,0) -> 0 | BQ9: =TK!N20 -> 0 | BR9: =IFERROR(BQ9/TK!N25,0) -> 0 | BW9: =BK9+BM9+BO9+BQ9+BS9+BU9 -> 0 | BX9: =IFERROR(BW9/(BK11+BM11+BO11+BQ11),0) -> 0 | BY9: =IFERROR((BW9-BH9)/BH9,0) -> 0 | BZ9: =AMAZON!P40 -> 0 | CA9: =IFERROR(BZ9/AMAZON!P50,0) -> 0 | CB9: =TEMU!P20 -> 0 | CC9: =IFERROR(CB9/TEMU!P25,0) -> 0 | CD9: =SHEIN!P16 -> 0 | CE9: =IFERROR(CD9/SHEIN!P20,0) -> 0 | CF9: =TK!P20 -> 0 | CG9: =IFERROR(CF9/TK!P25,0) -> 0 | CL9: =BZ9+CB9+CD9+CF9+CH9+CJ9 -> 0 | CM9: =IFERROR(CL9/(BZ11+CB11+CD11+CF11),0) -> 0 | CN9: =IFERROR((CL9-BW9)/BW9,0) -> 0 | CO9: =AMAZON!R40 -> 0 | CP9: =IFERROR(CO9/AMAZON!R50,0) -> 0 | CQ9: =TEMU!R20 -> 0 | CR9: =IFERROR(CQ9/TEMU!R25,0) -> 0 | CS9: =SHEIN!R16 -> 0 | CT9: =IFERROR(CS9/SHEIN!R20,0) -> 0 | CU9: =TK!R20 -> 0 | CV9: =IFERROR(CU9/TK!R25,0) -> 0 | DA9: =CO9+CQ9+CS9+CU9+CW9+CY9 -> 0 | DB9: =IFERROR(DA9/(CO11+CQ11+CS11+CU11),0) -> 0 | DC9: =IFERROR((DA9-CL9)/CL9,0) -> 0 | DD9: =AMAZON!T40 -> 0 | DE9: =IFERROR(DD9/AMAZON!T50,0) -> 0 | DF9: =TEMU!T20 -> 0 | DG9: =IFERROR(DF9/TEMU!T25,0) -> 0 | DH9: =SHEIN!T16 -> 0 | DI9: =IFERROR(DH9/SHEIN!T20,0) -> 0 | DJ9: =TK!T20 -> 0 | DK9: =IFERROR(DJ9/TK!T25,0) -> 0 | DP9: =DD9+DF9+DH9+DJ9+DL9+DN9 -> 0 | DQ9: =IFERROR(DP9/(DD11+DF11+DH11+DJ11),0) -> 0 | DR9: =IFERROR((DP9-DA9)/DA9,0) -> 0 | DS9: =AMAZON!V40 -> 0 | DT9: =IFERROR(DS9/AMAZON!V50,0) -> 0 | DU9: =TEMU!V20 -> 0 | DV9: =IFERROR(DU9/TEMU!V25,0) -> 0 | DW9: =SHEIN!V16 -> 0 | DX9: =IFERROR(DW9/SHEIN!V20,0) -> 0 | DY9: =TK!V20 -> 0 | DZ9: =IFERROR(DY9/TK!V25,0) -> 0 | EE9: =DS9+DU9+DW9+DY9+EA9+EC9 -> 0 | EF9: =IFERROR(EE9/(DS11+DU11+DW11+DY11),0) -> 0 | EG9: =IFERROR((EE9-DP9)/DP9,0) -> 0 | EH9: =AMAZON!X40 -> 0 | EI9: =IFERROR(EH9/AMAZON!X50,0) -> 0 | EJ9: =TEMU!X20 -> 0 | EK9: =IFERROR(EJ9/TEMU!X25,0) -> 0 | EL9: =SHEIN!X16 -> 0 | EM9: =IFERROR(EL9/SHEIN!X20,0) -> 0 | EN9: =TK!X20 -> 0 | EO9: =IFERROR(EN9/TK!X25,0) -> 0 | ET9: =EH9+EJ9+EL9+EN9+EP9+ER9 -> 0 | EU9: =IFERROR(ET9/(EH11+EJ11+EL11+EN11),0) -> 0 | EV9: =IFERROR((ET9-EE9)/EE9,0) -> 0 | EW9: =AMAZON!Z40 -> 0 | EX9: =IFERROR(EW9/AMAZON!Z50,0) -> 0 | EY9: =TEMU!Z20 -> 0 | EZ9: =IFERROR(EY9/TEMU!Z25,0) -> 0 | FA9: =SHEIN!Z16 -> 0 | FB9: =IFERROR(FA9/SHEIN!Z20,0) -> 0 | FC9: =TK!Z20 -> 0 | FD9: =IFERROR(FC9/TK!Z25,0) -> 0 | FI9: =EW9+EY9+FA9+FC9+FE9+FG9 -> 0 | FJ9: =IFERROR(FI9/(EW11+EY11+FA11+FC11),0) -> 0 | FK9: =IFERROR((FI9-ET9)/ET9,0) -> 0 | FL9: =AMAZON!AB40 -> 0 | FM9: =IFERROR(FL9/AMAZON!AB50,0) -> 0 | FN9: =TEMU!AB20 -> 0 | FO9: =IFERROR(FN9/TEMU!AB25,0) -> 0 | FP9: =SHEIN!AB16 -> 0 | FQ9: =IFERROR(FP9/SHEIN!AB20,0) -> 0 | FR9: =TK!AB20 -> 0 | FS9: =IFERROR(FR9/TK!AB25,0) -> 0 | FX9: =FL9+FN9+FP9+FR9+FT9+FV9 -> 0 | FY9: =IFERROR(FX9/(FL11+FN11+FP11+FR11),0) -> 0 | FZ9: =IFERROR((FX9-FI9)/FI9,0) -> 0 | GA9: =AMAZON!AD40 -> 0 | GB9: =IFERROR(GA9/AMAZON!AD50,0) -> 0 | GC9: =TEMU!AD20 -> 0 | GD9: =IFERROR(GC9/TEMU!AD25,0) -> 0 | GE9: =SHEIN!AD16 -> 0 | GF9: =IFERROR(GE9/SHEIN!AD20,0) -> 0 | GG9: =TK!AD20 -> 0 | GH9: =IFERROR(GG9/TK!AD25,0) -> 0 | GM9: =GA9+GC9+GE9+GG9+GI9+GK9 -> 0 | GN9: =IFERROR(GM9/(GA11+GC11+GE11+GG11),0) -> 0 | GO9: =IFERROR((GM9-FX9)/FX9,0) -> 0
A10: 经营销售 | C10: 元 | D10: =AMAZON!F41 -> 0 | E10: =IFERROR(D10/AMAZON!F50,0) -> 0 | F10: =TEMU!F21 -> 0 | G10: =IFERROR(F10/TEMU!F25,0) -> 0 | H10: =SHEIN!F17 -> 0 | I10: =IFERROR(H10/SHEIN!F20,0) -> 0 | J10: =TK!F21 -> 0 | K10: =IFERROR(J10/TK!F25,0) -> 0 | P10: =D10+F10+H10+J10+L10+N10 -> 0 | Q10: =IFERROR(P10/(D11+F11+H11+J11),0) -> 0 | R10: =AMAZON!H41 -> 0 | S10: =IFERROR(R10/AMAZON!H50,0) -> 0 | T10: =TEMU!H21 -> 0 | U10: =IFERROR(T10/TEMU!H25,0) -> 0 | V10: =SHEIN!H17 -> 0 | W10: =IFERROR(V10/SHEIN!H20,0) -> 0 | X10: =TK!H21 -> 0 | Y10: =IFERROR(X10/TK!H25,0) -> 0 | AD10: =R10+T10+V10+X10+Z10+AB10 -> 0 | AE10: =IFERROR(AD10/(R11+T11+V11+X11),0) -> 0 | AG10: =AMAZON!J41 -> 0 | AH10: =IFERROR(AG10/AMAZON!J50,0) -> 0 | AI10: =TEMU!J21 -> 0 | AJ10: =IFERROR(AI10/TEMU!J25,0) -> 0 | AK10: =SHEIN!J17 -> 0 | AL10: =IFERROR(AK10/SHEIN!J20,0) -> 0 | AM10: =TK!J21 -> 0 | AN10: =IFERROR(AM10/TK!J25,0) -> 0 | AS10: =AG10+AI10+AK10+AM10+AO10+AQ10 -> 0 | AT10: =IFERROR(AS10/(AG11+AI11+AK11+AM11),0) -> 0 | AU10: =IFERROR((AS10-AD10)/AD10,0) -> 0 | AV10: =AMAZON!L41 -> 0 | AW10: =IFERROR(AV10/AMAZON!L50,0) -> 0 | AX10: =TEMU!L21 -> 0 | AY10: =IFERROR(AX10/TEMU!L25,0) -> 0 | AZ10: =SHEIN!L17 -> 0 | BA10: =IFERROR(AZ10/SHEIN!L20,0) -> 0 | BB10: =TK!L21 -> 0 | BC10: =IFERROR(BB10/TK!L25,0) -> 0 | BH10: =AV10+AX10+AZ10+BB10+BD10+BF10 -> 0 | BI10: =IFERROR(BH10/(AV11+AX11+AZ11+BB11),0) -> 0 | BJ10: =IFERROR((BH10-AS10)/AS10,0) -> 0 | BK10: =AMAZON!N41 -> 0 | BL10: =IFERROR(BK10/AMAZON!N50,0) -> 0 | BM10: =TEMU!N21 -> 0 | BN10: =IFERROR(BM10/TEMU!N25,0) -> 0 | BO10: =SHEIN!N17 -> 0 | BP10: =IFERROR(BO10/SHEIN!N20,0) -> 0 | BQ10: =TK!N21 -> 0 | BR10: =IFERROR(BQ10/TK!N25,0) -> 0 | BW10: =BK10+BM10+BO10+BQ10+BS10+BU10 -> 0 | BX10: =IFERROR(BW10/(BK11+BM11+BO11+BQ11),0) -> 0 | BY10: =IFERROR((BW10-BH10)/BH10,0) -> 0 | BZ10: =AMAZON!P41 -> 0 | CA10: =IFERROR(BZ10/AMAZON!P50,0) -> 0 | CB10: =TEMU!P21 -> 0 | CC10: =IFERROR(CB10/TEMU!P25,0) -> 0 | CD10: =SHEIN!P17 -> 0 | CE10: =IFERROR(CD10/SHEIN!P20,0) -> 0 | CF10: =TK!P21 -> 0 | CG10: =IFERROR(CF10/TK!P25,0) -> 0 | CL10: =BZ10+CB10+CD10+CF10+CH10+CJ10 -> 0 | CM10: =IFERROR(CL10/(BZ11+CB11+CD11+CF11),0) -> 0 | CN10: =IFERROR((CL10-BW10)/BW10,0) -> 0 | CO10: =AMAZON!R41 -> 0 | CP10: =IFERROR(CO10/AMAZON!R50,0) -> 0 | CQ10: =TEMU!R21 -> 0 | CR10: =IFERROR(CQ10/TEMU!R25,0) -> 0 | CS10: =SHEIN!R17 -> 0 | CT10: =IFERROR(CS10/SHEIN!R20,0) -> 0 | CU10: =TK!R21 -> 0 | CV10: =IFERROR(CU10/TK!R25,0) -> 0 | DA10: =CO10+CQ10+CS10+CU10+CW10+CY10 -> 0 | DB10: =IFERROR(DA10/(CO11+CQ11+CS11+CU11),0) -> 0 | DC10: =IFERROR((DA10-CL10)/CL10,0) -> 0 | DD10: =AMAZON!T41 -> 0 | DE10: =IFERROR(DD10/AMAZON!T50,0) -> 0 | DF10: =TEMU!T21 -> 0 | DG10: =IFERROR(DF10/TEMU!T25,0) -> 0 | DH10: =SHEIN!T17 -> 0 | DI10: =IFERROR(DH10/SHEIN!T20,0) -> 0 | DJ10: =TK!T21 -> 0 | DK10: =IFERROR(DJ10/TK!T25,0) -> 0 | DP10: =DD10+DF10+DH10+DJ10+DL10+DN10 -> 0 | DQ10: =IFERROR(DP10/(DD11+DF11+DH11+DJ11),0) -> 0 | DR10: =IFERROR((DP10-DA10)/DA10,0) -> 0 | DS10: =AMAZON!V41 -> 0 | DT10: =IFERROR(DS10/AMAZON!V50,0) -> 0 | DU10: =TEMU!V21 -> 0 | DV10: =IFERROR(DU10/TEMU!V25,0) -> 0 | DW10: =SHEIN!V17 -> 0 | DX10: =IFERROR(DW10/SHEIN!V20,0) -> 0 | DY10: =TK!V21 -> 0 | DZ10: =IFERROR(DY10/TK!V25,0) -> 0 | EE10: =DS10+DU10+DW10+DY10+EA10+EC10 -> 0 | EF10: =IFERROR(EE10/(DS11+DU11+DW11+DY11),0) -> 0 | EG10: =IFERROR((EE10-DP10)/DP10,0) -> 0 | EH10: =AMAZON!X41 -> 0 | EI10: =IFERROR(EH10/AMAZON!X50,0) -> 0 | EJ10: =TEMU!X21 -> 0 | EK10: =IFERROR(EJ10/TEMU!X25,0) -> 0 | EL10: =SHEIN!X17 -> 0 | EM10: =IFERROR(EL10/SHEIN!X20,0) -> 0 | EN10: =TK!X21 -> 0 | EO10: =IFERROR(EN10/TK!X25,0) -> 0 | ET10: =EH10+EJ10+EL10+EN10+EP10+ER10 -> 0 | EU10: =IFERROR(ET10/(EH11+EJ11+EL11+EN11),0) -> 0 | EV10: =IFERROR((ET10-EE10)/EE10,0) -> 0 | EW10: =AMAZON!Z41 -> 0 | EX10: =IFERROR(EW10/AMAZON!Z50,0) -> 0 | EY10: =TEMU!Z21 -> 0 | EZ10: =IFERROR(EY10/TEMU!Z25,0) -> 0 | FA10: =SHEIN!Z17 -> 0 | FB10: =IFERROR(FA10/SHEIN!Z20,0) -> 0 | FC10: =TK!Z21 -> 0 | FD10: =IFERROR(FC10/TK!Z25,0) -> 0 | FI10: =EW10+EY10+FA10+FC10+FE10+FG10 -> 0 | FJ10: =IFERROR(FI10/(EW11+EY11+FA11+FC11),0) -> 0 | FK10: =IFERROR((FI10-ET10)/ET10,0) -> 0 | FL10: =AMAZON!AB41 -> 0 | FM10: =IFERROR(FL10/AMAZON!AB50,0) -> 0 | FN10: =TEMU!AB21 -> 0 | FO10: =IFERROR(FN10/TEMU!AB25,0) -> 0 | FP10: =SHEIN!AB17 -> 0 | FQ10: =IFERROR(FP10/SHEIN!AB20,0) -> 0 | FR10: =TK!AB21 -> 0 | FS10: =IFERROR(FR10/TK!AB25,0) -> 0 | FX10: =FL10+FN10+FP10+FR10+FT10+FV10 -> 0 | FY10: =IFERROR(FX10/(FL11+FN11+FP11+FR11),0) -> 0 | FZ10: =IFERROR((FX10-FI10)/FI10,0) -> 0 | GA10: =AMAZON!AD41 -> 0 | GB10: =IFERROR(GA10/AMAZON!AD50,0) -> 0 | GC10: =TEMU!AD21 -> 0 | GD10: =IFERROR(GC10/TEMU!AD25,0) -> 0 | GE10: =SHEIN!AD17 -> 0 | GF10: =IFERROR(GE10/SHEIN!AD20,0) -> 0 | GG10: =TK!AD21 -> 0 | GH10: =IFERROR(GG10/TK!AD25,0) -> 0 | GM10: =GA10+GC10+GE10+GG10+GI10+GK10 -> 0 | GN10: =IFERROR(GM10/(GA11+GC11+GE11+GG11),0) -> 0 | GO10: =IFERROR((GM10-FX10)/FX10,0) -> 0
A11: 经营销售 | B11: 销售额 | C11: 元 | D11: =AMAZON!F50 -> 0 | E11: =IFERROR(D11/AMAZON!F50,0) -> 0 | F11: =TEMU!F25 -> 0 | G11: =IFERROR(F11/TEMU!F25,0) -> 0 | H11: =SHEIN!F20 -> 0 | I11: =IFERROR(H11/SHEIN!F20,0) -> 0 | J11: =TK!F25 -> 0 | K11: =IFERROR(J11/TK!F25,0) -> 0 | P11: =D11+F11+H11+J11+L11+N11 -> 0 | Q11: =IFERROR(P11/(D11+F11+H11+J11),0) -> 0 | R11: =AMAZON!H50 -> 0 | S11: =IFERROR(R11/AMAZON!H50,0) -> 0 | T11: =TEMU!H25 -> 0 | U11: =IFERROR(T11/TEMU!H25,0) -> 0 | V11: =SHEIN!H20 -> 0 | W11: =IFERROR(V11/SHEIN!H20,0) -> 0 | X11: =TK!H25 -> 0 | Y11: =IFERROR(X11/TK!H25,0) -> 0 | AD11: =R11+T11+V11+X11+Z11+AB11 -> 0 | AE11: =IFERROR(AD11/(R11+T11+V11+X11),0) -> 0 | AG11: =AMAZON!J50 -> 0 | AH11: =IFERROR(AG11/AMAZON!J50,0) -> 0 | AI11: =TEMU!J25 -> 0 | AJ11: =IFERROR(AI11/TEMU!J25,0) -> 0 | AK11: =SHEIN!J20 -> 0 | AL11: =IFERROR(AK11/SHEIN!J20,0) -> 0 | AM11: =TK!J25 -> 0 | AN11: =IFERROR(AM11/TK!J25,0) -> 0 | AS11: =AG11+AI11+AK11+AM11+AO11+AQ11 -> 0 | AT11: =IFERROR(AS11/(AG11+AI11+AK11+AM11),0) -> 0 | AU11: =IFERROR((AS11-AD11)/AD11,0) -> 0 | AV11: =AMAZON!L50 -> 0 | AW11: =IFERROR(AV11/AMAZON!L50,0) -> 0 | AX11: =TEMU!L25 -> 0 | AY11: =IFERROR(AX11/TEMU!L25,0) -> 0 | AZ11: =SHEIN!L20 -> 0 | BA11: =IFERROR(AZ11/SHEIN!L20,0) -> 0 | BB11: =TK!L25 -> 0 | BC11: =IFERROR(BB11/TK!L25,0) -> 0 | BH11: =AV11+AX11+AZ11+BB11+BD11+BF11 -> 0 | BI11: =IFERROR(BH11/(AV11+AX11+AZ11+BB11),0) -> 0 | BJ11: =IFERROR((BH11-AS11)/AS11,0) -> 0 | BK11: =AMAZON!N50 -> 0 | BL11: =IFERROR(BK11/AMAZON!N50,0) -> 0 | BM11: =TEMU!N25 -> 0 | BN11: =IFERROR(BM11/TEMU!N25,0) -> 0 | BO11: =SHEIN!N20 -> 0 | BP11: =IFERROR(BO11/SHEIN!N20,0) -> 0 | BQ11: =TK!N25 -> 0 | BR11: =IFERROR(BQ11/TK!N25,0) -> 0 | BW11: =BK11+BM11+BO11+BQ11+BS11+BU11 -> 0 | BX11: =IFERROR(BW11/(BK11+BM11+BO11+BQ11),0) -> 0 | BY11: =IFERROR((BW11-BH11)/BH11,0) -> 0 | BZ11: =AMAZON!P50 -> 0 | CA11: =IFERROR(BZ11/AMAZON!P50,0) -> 0 | CB11: =TEMU!P25 -> 0 | CC11: =IFERROR(CB11/TEMU!P25,0) -> 0 | CD11: =SHEIN!P20 -> 0 | CE11: =IFERROR(CD11/SHEIN!P20,0) -> 0 | CF11: =TK!P25 -> 0 | CG11: =IFERROR(CF11/TK!P25,0) -> 0 | CL11: =BZ11+CB11+CD11+CF11+CH11+CJ11 -> 0 | CM11: =IFERROR(CL11/(BZ11+CB11+CD11+CF11),0) -> 0 | CN11: =IFERROR((CL11-BW11)/BW11,0) -> 0 | CO11: =AMAZON!R50 -> 0 | CP11: =IFERROR(CO11/AMAZON!R50,0) -> 0 | CQ11: =TEMU!R25 -> 0 | CR11: =IFERROR(CQ11/TEMU!R25,0) -> 0 | CS11: =SHEIN!R20 -> 0 | CT11: =IFERROR(CS11/SHEIN!R20,0) -> 0 | CU11: =TK!R25 -> 0 | CV11: =IFERROR(CU11/TK!R25,0) -> 0 | DA11: =CO11+CQ11+CS11+CU11+CW11+CY11 -> 0 | DB11: =IFERROR(DA11/(CO11+CQ11+CS11+CU11),0) -> 0 | DC11: =IFERROR((DA11-CL11)/CL11,0) -> 0 | DD11: =AMAZON!T50 -> 0 | DE11: =IFERROR(DD11/AMAZON!T50,0) -> 0 | DF11: =TEMU!T25 -> 0 | DG11: =IFERROR(DF11/TEMU!T25,0) -> 0 | DH11: =SHEIN!T20 -> 0 | DI11: =IFERROR(DH11/SHEIN!T20,0) -> 0 | DJ11: =TK!T25 -> 0 | DK11: =IFERROR(DJ11/TK!T25,0) -> 0 | DP11: =DD11+DF11+DH11+DJ11+DL11+DN11 -> 0 | DQ11: =IFERROR(DP11/(DD11+DF11+DH11+DJ11),0) -> 0 | DR11: =IFERROR((DP11-DA11)/DA11,0) -> 0 | DS11: =AMAZON!V50 -> 0 | DT11: =IFERROR(DS11/AMAZON!V50,0) -> 0 | DU11: =TEMU!V25 -> 0 | DV11: =IFERROR(DU11/TEMU!V25,0) -> 0 | DW11: =SHEIN!V20 -> 0 | DX11: =IFERROR(DW11/SHEIN!V20,0) -> 0 | DY11: =TK!V25 -> 0 | DZ11: =IFERROR(DY11/TK!V25,0) -> 0 | EE11: =DS11+DU11+DW11+DY11+EA11+EC11 -> 0 | EF11: =IFERROR(EE11/(DS11+DU11+DW11+DY11),0) -> 0 | EG11: =IFERROR((EE11-DP11)/DP11,0) -> 0 | EH11: =AMAZON!X50 -> 0 | EI11: =IFERROR(EH11/AMAZON!X50,0) -> 0 | EJ11: =TEMU!X25 -> 0 | EK11: =IFERROR(EJ11/TEMU!X25,0) -> 0 | EL11: =SHEIN!X20 -> 0 | EM11: =IFERROR(EL11/SHEIN!X20,0) -> 0 | EN11: =TK!X25 -> 0 | EO11: =IFERROR(EN11/TK!X25,0) -> 0 | ET11: =EH11+EJ11+EL11+EN11+EP11+ER11 -> 0 | EU11: =IFERROR(ET11/(EH11+EJ11+EL11+EN11),0) -> 0 | EV11: =IFERROR((ET11-EE11)/EE11,0) -> 0 | EW11: =AMAZON!Z50 -> 0 | EX11: =IFERROR(EW11/AMAZON!Z50,0) -> 0 | EY11: =TEMU!Z25 -> 0 | EZ11: =IFERROR(EY11/TEMU!Z25,0) -> 0 | FA11: =SHEIN!Z20 -> 0 | FB11: =IFERROR(FA11/SHEIN!Z20,0) -> 0 | FC11: =TK!Z25 -> 0 | FD11: =IFERROR(FC11/TK!Z25,0) -> 0 | FI11: =EW11+EY11+FA11+FC11+FE11+FG11 -> 0 | FJ11: =IFERROR(FI11/(EW11+EY11+FA11+FC11),0) -> 0 | FK11: =IFERROR((FI11-ET11)/ET11,0) -> 0 | FL11: =AMAZON!AB50 -> 0 | FM11: =IFERROR(FL11/AMAZON!AB50,0) -> 0 | FN11: =TEMU!AB25 -> 0 | FO11: =IFERROR(FN11/TEMU!AB25,0) -> 0 | FP11: =SHEIN!AB20 -> 0 | FQ11: =IFERROR(FP11/SHEIN!AB20,0) -> 0 | FR11: =TK!AB25 -> 0 | FS11: =IFERROR(FR11/TK!AB25,0) -> 0 | FX11: =FL11+FN11+FP11+FR11+FT11+FV11 -> 0 | FY11: =IFERROR(FX11/(FL11+FN11+FP11+FR11),0) -> 0 | FZ11: =IFERROR((FX11-FI11)/FI11,0) -> 0 | GA11: =AMAZON!AD50 -> 0 | GB11: =IFERROR(GA11/AMAZON!AD50,0) -> 0 | GC11: =TEMU!AD25 -> 0 | GD11: =IFERROR(GC11/TEMU!AD25,0) -> 0 | GE11: =SHEIN!AD20 -> 0 | GF11: =IFERROR(GE11/SHEIN!AD20,0) -> 0 | GG11: =TK!AD25 -> 0 | GH11: =IFERROR(GG11/TK!AD25,0) -> 0 | GM11: =GA11+GC11+GE11+GG11+GI11+GK11 -> 0 | GN11: =IFERROR(GM11/(GA11+GC11+GE11+GG11),0) -> 0 | GO11: =IFERROR((GM11-FX11)/FX11,0) -> 0
A12: 经营销售 | B12: 促销折扣 | C12: 元 | D12: =AMAZON!F59 -> 0 | E12: =IFERROR(D12/AMAZON!F50,0) -> 0 | F12: =TEMU!F29 -> 0 | G12: =IFERROR(F12/TEMU!F25,0) -> 0 | H12: =SHEIN!F23 -> 0 | I12: =IFERROR(H12/SHEIN!F20,0) -> 0 | J12: =TK!F29 -> 0 | K12: =IFERROR(J12/TK!F25,0) -> 0 | P12: =D12+F12+H12+J12+L12+N12 -> 0 | Q12: =IFERROR(P12/(D11+F11+H11+J11),0) -> 0 | R12: =AMAZON!H59 -> 0 | S12: =IFERROR(R12/AMAZON!H50,0) -> 0 | T12: =TEMU!H29 -> 0 | U12: =IFERROR(T12/TEMU!H25,0) -> 0 | V12: =SHEIN!H23 -> 0 | W12: =IFERROR(V12/SHEIN!H20,0) -> 0 | X12: =TK!H29 -> 0 | Y12: =IFERROR(X12/TK!H25,0) -> 0 | AD12: =R12+T12+V12+X12+Z12+AB12 -> 0 | AE12: =IFERROR(AD12/(R11+T11+V11+X11),0) -> 0 | AG12: =AMAZON!J59 -> 0 | AH12: =IFERROR(AG12/AMAZON!J50,0) -> 0 | AI12: =TEMU!J29 -> 0 | AJ12: =IFERROR(AI12/TEMU!J25,0) -> 0 | AK12: =SHEIN!J23 -> 0 | AL12: =IFERROR(AK12/SHEIN!J20,0) -> 0 | AM12: =TK!J29 -> 0 | AN12: =IFERROR(AM12/TK!J25,0) -> 0 | AS12: =AG12+AI12+AK12+AM12+AO12+AQ12 -> 0 | AT12: =IFERROR(AS12/(AG11+AI11+AK11+AM11),0) -> 0 | AU12: =IFERROR((AS12-AD12)/AD12,0) -> 0 | AV12: =AMAZON!L59 -> 0 | AW12: =IFERROR(AV12/AMAZON!L50,0) -> 0 | AX12: =TEMU!L29 -> 0 | AY12: =IFERROR(AX12/TEMU!L25,0) -> 0 | AZ12: =SHEIN!L23 -> 0 | BA12: =IFERROR(AZ12/SHEIN!L20,0) -> 0 | BB12: =TK!L29 -> 0 | BC12: =IFERROR(BB12/TK!L25,0) -> 0 | BH12: =AV12+AX12+AZ12+BB12+BD12+BF12 -> 0 | BI12: =IFERROR(BH12/(AV11+AX11+AZ11+BB11),0) -> 0 | BJ12: =IFERROR((BH12-AS12)/AS12,0) -> 0 | BK12: =AMAZON!N59 -> 0 | BL12: =IFERROR(BK12/AMAZON!N50,0) -> 0 | BM12: =TEMU!N29 -> 0 | BN12: =IFERROR(BM12/TEMU!N25,0) -> 0 | BO12: =SHEIN!N23 -> 0 | BP12: =IFERROR(BO12/SHEIN!N20,0) -> 0 | BQ12: =TK!N29 -> 0 | BR12: =IFERROR(BQ12/TK!N25,0) -> 0 | BW12: =BK12+BM12+BO12+BQ12+BS12+BU12 -> 0 | BX12: =IFERROR(BW12/(BK11+BM11+BO11+BQ11),0) -> 0 | BY12: =IFERROR((BW12-BH12)/BH12,0) -> 0 | BZ12: =AMAZON!P59 -> 0 | CA12: =IFERROR(BZ12/AMAZON!P50,0) -> 0 | CB12: =TEMU!P29 -> 0 | CC12: =IFERROR(CB12/TEMU!P25,0) -> 0 | CD12: =SHEIN!P23 -> 0 | CE12: =IFERROR(CD12/SHEIN!P20,0) -> 0 | CF12: =TK!P29 -> 0 | CG12: =IFERROR(CF12/TK!P25,0) -> 0 | CL12: =BZ12+CB12+CD12+CF12+CH12+CJ12 -> 0 | CM12: =IFERROR(CL12/(BZ11+CB11+CD11+CF11),0) -> 0 | CN12: =IFERROR((CL12-BW12)/BW12,0) -> 0 | CO12: =AMAZON!R59 -> 0 | CP12: =IFERROR(CO12/AMAZON!R50,0) -> 0 | CQ12: =TEMU!R29 -> 0 | CR12: =IFERROR(CQ12/TEMU!R25,0) -> 0 | CS12: =SHEIN!R23 -> 0 | CT12: =IFERROR(CS12/SHEIN!R20,0) -> 0 | CU12: =TK!R29 -> 0 | CV12: =IFERROR(CU12/TK!R25,0) -> 0 | DA12: =CO12+CQ12+CS12+CU12+CW12+CY12 -> 0 | DB12: =IFERROR(DA12/(CO11+CQ11+CS11+CU11),0) -> 0 | DC12: =IFERROR((DA12-CL12)/CL12,0) -> 0 | DD12: =AMAZON!T59 -> 0 | DE12: =IFERROR(DD12/AMAZON!T50,0) -> 0 | DF12: =TEMU!T29 -> 0 | DG12: =IFERROR(DF12/TEMU!T25,0) -> 0 | DH12: =SHEIN!T23 -> 0 | DI12: =IFERROR(DH12/SHEIN!T20,0) -> 0 | DJ12: =TK!T29 -> 0 | DK12: =IFERROR(DJ12/TK!T25,0) -> 0 | DP12: =DD12+DF12+DH12+DJ12+DL12+DN12 -> 0 | DQ12: =IFERROR(DP12/(DD11+DF11+DH11+DJ11),0) -> 0 | DR12: =IFERROR((DP12-DA12)/DA12,0) -> 0 | DS12: =AMAZON!V59 -> 0 | DT12: =IFERROR(DS12/AMAZON!V50,0) -> 0 | DU12: =TEMU!V29 -> 0 | DV12: =IFERROR(DU12/TEMU!V25,0) -> 0 | DW12: =SHEIN!V23 -> 0 | DX12: =IFERROR(DW12/SHEIN!V20,0) -> 0 | DY12: =TK!V29 -> 0 | DZ12: =IFERROR(DY12/TK!V25,0) -> 0 | EE12: =DS12+DU12+DW12+DY12+EA12+EC12 -> 0 | EF12: =IFERROR(EE12/(DS11+DU11+DW11+DY11),0) -> 0 | EG12: =IFERROR((EE12-DP12)/DP12,0) -> 0 | EH12: =AMAZON!X59 -> 0 | EI12: =IFERROR(EH12/AMAZON!X50,0) -> 0 | EJ12: =TEMU!X29 -> 0 | EK12: =IFERROR(EJ12/TEMU!X25,0) -> 0 | EL12: =SHEIN!X23 -> 0 | EM12: =IFERROR(EL12/SHEIN!X20,0) -> 0 | EN12: =TK!X29 -> 0 | EO12: =IFERROR(EN12/TK!X25,0) -> 0 | ET12: =EH12+EJ12+EL12+EN12+EP12+ER12 -> 0 | EU12: =IFERROR(ET12/(EH11+EJ11+EL11+EN11),0) -> 0 | EV12: =IFERROR((ET12-EE12)/EE12,0) -> 0 | EW12: =AMAZON!Z59 -> 0 | EX12: =IFERROR(EW12/AMAZON!Z50,0) -> 0 | EY12: =TEMU!Z29 -> 0 | EZ12: =IFERROR(EY12/TEMU!Z25,0) -> 0 | FA12: =SHEIN!Z23 -> 0 | FB12: =IFERROR(FA12/SHEIN!Z20,0) -> 0 | FC12: =TK!Z29 -> 0 | FD12: =IFERROR(FC12/TK!Z25,0) -> 0 | FI12: =EW12+EY12+FA12+FC12+FE12+FG12 -> 0 | FJ12: =IFERROR(FI12/(EW11+EY11+FA11+FC11),0) -> 0 | FK12: =IFERROR((FI12-ET12)/ET12,0) -> 0 | FL12: =AMAZON!AB59 -> 0 | FM12: =IFERROR(FL12/AMAZON!AB50,0) -> 0 | FN12: =TEMU!AB29 -> 0 | FO12: =IFERROR(FN12/TEMU!AB25,0) -> 0 | FP12: =SHEIN!AB23 -> 0 | FQ12: =IFERROR(FP12/SHEIN!AB20,0) -> 0 | FR12: =TK!AB29 -> 0 | FS12: =IFERROR(FR12/TK!AB25,0) -> 0 | FX12: =FL12+FN12+FP12+FR12+FT12+FV12 -> 0 | FY12: =IFERROR(FX12/(FL11+FN11+FP11+FR11),0) -> 0 | FZ12: =IFERROR((FX12-FI12)/FI12,0) -> 0 | GA12: =AMAZON!AD59 -> 0 | GB12: =IFERROR(GA12/AMAZON!AD50,0) -> 0 | GC12: =TEMU!AD29 -> 0 | GD12: =IFERROR(GC12/TEMU!AD25,0) -> 0 | GE12: =SHEIN!AD23 -> 0 | GF12: =IFERROR(GE12/SHEIN!AD20,0) -> 0 | GG12: =TK!AD29 -> 0 | GH12: =IFERROR(GG12/TK!AD25,0) -> 0 | GM12: =GA12+GC12+GE12+GG12+GI12+GK12 -> 0 | GN12: =IFERROR(GM12/(GA11+GC11+GE11+GG11),0) -> 0 | GO12: =IFERROR((GM12-FX12)/FX12,0) -> 0
A13: 经营退款 | C13: 元 | D13: =AMAZON!F68 -> 0 | E13: =IFERROR(D13/AMAZON!F50,0) -> 0 | F13: =TEMU!F33 -> 0 | G13: =IFERROR(F13/TEMU!F25,0) -> 0 | H13: =SHEIN!F26 -> 0 | I13: =IFERROR(H13/SHEIN!F20,0) -> 0 | J13: =TK!F33 -> 0 | K13: =IFERROR(J13/TK!F25,0) -> 0 | P13: =D13+F13+H13+J13+L13+N13 -> 0 | Q13: =IFERROR(P13/(D11+F11+H11+J11),0) -> 0 | R13: =AMAZON!H68 -> 0 | S13: =IFERROR(R13/AMAZON!H50,0) -> 0 | T13: =TEMU!H33 -> 0 | U13: =IFERROR(T13/TEMU!H25,0) -> 0 | V13: =SHEIN!H26 -> 0 | W13: =IFERROR(V13/SHEIN!H20,0) -> 0 | X13: =TK!H33 -> 0 | Y13: =IFERROR(X13/TK!H25,0) -> 0 | AD13: =R13+T13+V13+X13+Z13+AB13 -> 0 | AE13: =IFERROR(AD13/(R11+T11+V11+X11),0) -> 0 | AG13: =AMAZON!J68 -> 0 | AH13: =IFERROR(AG13/AMAZON!J50,0) -> 0 | AI13: =TEMU!J33 -> 0 | AJ13: =IFERROR(AI13/TEMU!J25,0) -> 0 | AK13: =SHEIN!J26 -> 0 | AL13: =IFERROR(AK13/SHEIN!J20,0) -> 0 | AM13: =TK!J33 -> 0 | AN13: =IFERROR(AM13/TK!J25,0) -> 0 | AS13: =AG13+AI13+AK13+AM13+AO13+AQ13 -> 0 | AT13: =IFERROR(AS13/(AG11+AI11+AK11+AM11),0) -> 0 | AU13: =IFERROR((AS13-AD13)/AD13,0) -> 0 | AV13: =AMAZON!L68 -> 0 | AW13: =IFERROR(AV13/AMAZON!L50,0) -> 0 | AX13: =TEMU!L33 -> 0 | AY13: =IFERROR(AX13/TEMU!L25,0) -> 0 | AZ13: =SHEIN!L26 -> 0 | BA13: =IFERROR(AZ13/SHEIN!L20,0) -> 0 | BB13: =TK!L33 -> 0 | BC13: =IFERROR(BB13/TK!L25,0) -> 0 | BH13: =AV13+AX13+AZ13+BB13+BD13+BF13 -> 0 | BI13: =IFERROR(BH13/(AV11+AX11+AZ11+BB11),0) -> 0 | BJ13: =IFERROR((BH13-AS13)/AS13,0) -> 0 | BK13: =AMAZON!N68 -> 0 | BL13: =IFERROR(BK13/AMAZON!N50,0) -> 0 | BM13: =TEMU!N33 -> 0 | BN13: =IFERROR(BM13/TEMU!N25,0) -> 0 | BO13: =SHEIN!N26 -> 0 | BP13: =IFERROR(BO13/SHEIN!N20,0) -> 0 | BQ13: =TK!N33 -> 0 | BR13: =IFERROR(BQ13/TK!N25,0) -> 0 | BW13: =BK13+BM13+BO13+BQ13+BS13+BU13 -> 0 | BX13: =IFERROR(BW13/(BK11+BM11+BO11+BQ11),0) -> 0 | BY13: =IFERROR((BW13-BH13)/BH13,0) -> 0 | BZ13: =AMAZON!P68 -> 0 | CA13: =IFERROR(BZ13/AMAZON!P50,0) -> 0 | CB13: =TEMU!P33 -> 0 | CC13: =IFERROR(CB13/TEMU!P25,0) -> 0 | CD13: =SHEIN!P26 -> 0 | CE13: =IFERROR(CD13/SHEIN!P20,0) -> 0 | CF13: =TK!P33 -> 0 | CG13: =IFERROR(CF13/TK!P25,0) -> 0 | CL13: =BZ13+CB13+CD13+CF13+CH13+CJ13 -> 0 | CM13: =IFERROR(CL13/(BZ11+CB11+CD11+CF11),0) -> 0 | CN13: =IFERROR((CL13-BW13)/BW13,0) -> 0 | CO13: =AMAZON!R68 -> 0 | CP13: =IFERROR(CO13/AMAZON!R50,0) -> 0 | CQ13: =TEMU!R33 -> 0 | CR13: =IFERROR(CQ13/TEMU!R25,0) -> 0 | CS13: =SHEIN!R26 -> 0 | CT13: =IFERROR(CS13/SHEIN!R20,0) -> 0 | CU13: =TK!R33 -> 0 | CV13: =IFERROR(CU13/TK!R25,0) -> 0 | DA13: =CO13+CQ13+CS13+CU13+CW13+CY13 -> 0 | DB13: =IFERROR(DA13/(CO11+CQ11+CS11+CU11),0) -> 0 | DC13: =IFERROR((DA13-CL13)/CL13,0) -> 0 | DD13: =AMAZON!T68 -> 0 | DE13: =IFERROR(DD13/AMAZON!T50,0) -> 0 | DF13: =TEMU!T33 -> 0 | DG13: =IFERROR(DF13/TEMU!T25,0) -> 0 | DH13: =SHEIN!T26 -> 0 | DI13: =IFERROR(DH13/SHEIN!T20,0) -> 0 | DJ13: =TK!T33 -> 0 | DK13: =IFERROR(DJ13/TK!T25,0) -> 0 | DP13: =DD13+DF13+DH13+DJ13+DL13+DN13 -> 0 | DQ13: =IFERROR(DP13/(DD11+DF11+DH11+DJ11),0) -> 0 | DR13: =IFERROR((DP13-DA13)/DA13,0) -> 0 | DS13: =AMAZON!V68 -> 0 | DT13: =IFERROR(DS13/AMAZON!V50,0) -> 0 | DU13: =TEMU!V33 -> 0 | DV13: =IFERROR(DU13/TEMU!V25,0) -> 0 | DW13: =SHEIN!V26 -> 0 | DX13: =IFERROR(DW13/SHEIN!V20,0) -> 0 | DY13: =TK!V33 -> 0 | DZ13: =IFERROR(DY13/TK!V25,0) -> 0 | EE13: =DS13+DU13+DW13+DY13+EA13+EC13 -> 0 | EF13: =IFERROR(EE13/(DS11+DU11+DW11+DY11),0) -> 0 | EG13: =IFERROR((EE13-DP13)/DP13,0) -> 0 | EH13: =AMAZON!X68 -> 0 | EI13: =IFERROR(EH13/AMAZON!X50,0) -> 0 | EJ13: =TEMU!X33 -> 0 | EK13: =IFERROR(EJ13/TEMU!X25,0) -> 0 | EL13: =SHEIN!X26 -> 0 | EM13: =IFERROR(EL13/SHEIN!X20,0) -> 0 | EN13: =TK!X33 -> 0 | EO13: =IFERROR(EN13/TK!X25,0) -> 0 | ET13: =EH13+EJ13+EL13+EN13+EP13+ER13 -> 0 | EU13: =IFERROR(ET13/(EH11+EJ11+EL11+EN11),0) -> 0 | EV13: =IFERROR((ET13-EE13)/EE13,0) -> 0 | EW13: =AMAZON!Z68 -> 0 | EX13: =IFERROR(EW13/AMAZON!Z50,0) -> 0 | EY13: =TEMU!Z33 -> 0 | EZ13: =IFERROR(EY13/TEMU!Z25,0) -> 0 | FA13: =SHEIN!Z26 -> 0 | FB13: =IFERROR(FA13/SHEIN!Z20,0) -> 0 | FC13: =TK!Z33 -> 0 | FD13: =IFERROR(FC13/TK!Z25,0) -> 0 | FI13: =EW13+EY13+FA13+FC13+FE13+FG13 -> 0 | FJ13: =IFERROR(FI13/(EW11+EY11+FA11+FC11),0) -> 0 | FK13: =IFERROR((FI13-ET13)/ET13,0) -> 0 | FL13: =AMAZON!AB68 -> 0 | FM13: =IFERROR(FL13/AMAZON!AB50,0) -> 0 | FN13: =TEMU!AB33 -> 0 | FO13: =IFERROR(FN13/TEMU!AB25,0) -> 0 | FP13: =SHEIN!AB26 -> 0 | FQ13: =IFERROR(FP13/SHEIN!AB20,0) -> 0 | FR13: =TK!AB33 -> 0 | FS13: =IFERROR(FR13/TK!AB25,0) -> 0 | FX13: =FL13+FN13+FP13+FR13+FT13+FV13 -> 0 | FY13: =IFERROR(FX13/(FL11+FN11+FP11+FR11),0) -> 0 | FZ13: =IFERROR((FX13-FI13)/FI13,0) -> 0 | GA13: =AMAZON!AD68 -> 0 | GB13: =IFERROR(GA13/AMAZON!AD50,0) -> 0 | GC13: =TEMU!AD33 -> 0 | GD13: =IFERROR(GC13/TEMU!AD25,0) -> 0 | GE13: =SHEIN!AD26 -> 0 | GF13: =IFERROR(GE13/SHEIN!AD20,0) -> 0 | GG13: =TK!AD33 -> 0 | GH13: =IFERROR(GG13/TK!AD25,0) -> 0 | GM13: =GA13+GC13+GE13+GG13+GI13+GK13 -> 0 | GN13: =IFERROR(GM13/(GA11+GC11+GE11+GG11),0) -> 0 | GO13: =IFERROR((GM13-FX13)/FX13,0) -> 0
A14: 经营退款 | B14: 销售退款 | C14: 元 | D14: =AMAZON!F69 -> 0 | E14: =IFERROR(D14/AMAZON!F50,0) -> 0 | F14: =TEMU!F34 -> 0 | G14: =IFERROR(F14/TEMU!F25,0) -> 0 | H14: =SHEIN!F27 -> 0 | I14: =IFERROR(H14/SHEIN!F20,0) -> 0 | J14: =TK!F34 -> 0 | K14: =IFERROR(J14/TK!F25,0) -> 0 | P14: =D14+F14+H14+J14+L14+N14 -> 0 | Q14: =IFERROR(P14/(D11+F11+H11+J11),0) -> 0 | R14: =AMAZON!H69 -> 0 | S14: =IFERROR(R14/AMAZON!H50,0) -> 0 | T14: =TEMU!H34 -> 0 | U14: =IFERROR(T14/TEMU!H25,0) -> 0 | V14: =SHEIN!H27 -> 0 | W14: =IFERROR(V14/SHEIN!H20,0) -> 0 | X14: =TK!H34 -> 0 | Y14: =IFERROR(X14/TK!H25,0) -> 0 | AD14: =R14+T14+V14+X14+Z14+AB14 -> 0 | AE14: =IFERROR(AD14/(R11+T11+V11+X11),0) -> 0 | AG14: =AMAZON!J69 -> 0 | AH14: =IFERROR(AG14/AMAZON!J50,0) -> 0 | AI14: =TEMU!J34 -> 0 | AJ14: =IFERROR(AI14/TEMU!J25,0) -> 0 | AK14: =SHEIN!J27 -> 0 | AL14: =IFERROR(AK14/SHEIN!J20,0) -> 0 | AM14: =TK!J34 -> 0 | AN14: =IFERROR(AM14/TK!J25,0) -> 0 | AS14: =AG14+AI14+AK14+AM14+AO14+AQ14 -> 0 | AT14: =IFERROR(AS14/(AG11+AI11+AK11+AM11),0) -> 0 | AU14: =IFERROR((AS14-AD14)/AD14,0) -> 0 | AV14: =AMAZON!L69 -> 0 | AW14: =IFERROR(AV14/AMAZON!L50,0) -> 0 | AX14: =TEMU!L34 -> 0 | AY14: =IFERROR(AX14/TEMU!L25,0) -> 0 | AZ14: =SHEIN!L27 -> 0 | BA14: =IFERROR(AZ14/SHEIN!L20,0) -> 0 | BB14: =TK!L34 -> 0 | BC14: =IFERROR(BB14/TK!L25,0) -> 0 | BH14: =AV14+AX14+AZ14+BB14+BD14+BF14 -> 0 | BI14: =IFERROR(BH14/(AV11+AX11+AZ11+BB11),0) -> 0 | BJ14: =IFERROR((BH14-AS14)/AS14,0) -> 0 | BK14: =AMAZON!N69 -> 0 | BL14: =IFERROR(BK14/AMAZON!N50,0) -> 0 | BM14: =TEMU!N34 -> 0 | BN14: =IFERROR(BM14/TEMU!N25,0) -> 0 | BO14: =SHEIN!N27 -> 0 | BP14: =IFERROR(BO14/SHEIN!N20,0) -> 0 | BQ14: =TK!N34 -> 0 | BR14: =IFERROR(BQ14/TK!N25,0) -> 0 | BW14: =BK14+BM14+BO14+BQ14+BS14+BU14 -> 0 | BX14: =IFERROR(BW14/(BK11+BM11+BO11+BQ11),0) -> 0 | BY14: =IFERROR((BW14-BH14)/BH14,0) -> 0 | BZ14: =AMAZON!P69 -> 0 | CA14: =IFERROR(BZ14/AMAZON!P50,0) -> 0 | CB14: =TEMU!P34 -> 0 | CC14: =IFERROR(CB14/TEMU!P25,0) -> 0 | CD14: =SHEIN!P27 -> 0 | CE14: =IFERROR(CD14/SHEIN!P20,0) -> 0 | CF14: =TK!P34 -> 0 | CG14: =IFERROR(CF14/TK!P25,0) -> 0 | CL14: =BZ14+CB14+CD14+CF14+CH14+CJ14 -> 0 | CM14: =IFERROR(CL14/(BZ11+CB11+CD11+CF11),0) -> 0 | CN14: =IFERROR((CL14-BW14)/BW14,0) -> 0 | CO14: =AMAZON!R69 -> 0 | CP14: =IFERROR(CO14/AMAZON!R50,0) -> 0 | CQ14: =TEMU!R34 -> 0 | CR14: =IFERROR(CQ14/TEMU!R25,0) -> 0 | CS14: =SHEIN!R27 -> 0 | CT14: =IFERROR(CS14/SHEIN!R20,0) -> 0 | CU14: =TK!R34 -> 0 | CV14: =IFERROR(CU14/TK!R25,0) -> 0 | DA14: =CO14+CQ14+CS14+CU14+CW14+CY14 -> 0 | DB14: =IFERROR(DA14/(CO11+CQ11+CS11+CU11),0) -> 0 | DC14: =IFERROR((DA14-CL14)/CL14,0) -> 0 | DD14: =AMAZON!T69 -> 0 | DE14: =IFERROR(DD14/AMAZON!T50,0) -> 0 | DF14: =TEMU!T34 -> 0 | DG14: =IFERROR(DF14/TEMU!T25,0) -> 0 | DH14: =SHEIN!T27 -> 0 | DI14: =IFERROR(DH14/SHEIN!T20,0) -> 0 | DJ14: =TK!T34 -> 0 | DK14: =IFERROR(DJ14/TK!T25,0) -> 0 | DP14: =DD14+DF14+DH14+DJ14+DL14+DN14 -> 0 | DQ14: =IFERROR(DP14/(DD11+DF11+DH11+DJ11),0) -> 0 | DR14: =IFERROR((DP14-DA14)/DA14,0) -> 0 | DS14: =AMAZON!V69 -> 0 | DT14: =IFERROR(DS14/AMAZON!V50,0) -> 0 | DU14: =TEMU!V34 -> 0 | DV14: =IFERROR(DU14/TEMU!V25,0) -> 0 | DW14: =SHEIN!V27 -> 0 | DX14: =IFERROR(DW14/SHEIN!V20,0) -> 0 | DY14: =TK!V34 -> 0 | DZ14: =IFERROR(DY14/TK!V25,0) -> 0 | EE14: =DS14+DU14+DW14+DY14+EA14+EC14 -> 0 | EF14: =IFERROR(EE14/(DS11+DU11+DW11+DY11),0) -> 0 | EG14: =IFERROR((EE14-DP14)/DP14,0) -> 0 | EH14: =AMAZON!X69 -> 0 | EI14: =IFERROR(EH14/AMAZON!X50,0) -> 0 | EJ14: =TEMU!X34 -> 0 | EK14: =IFERROR(EJ14/TEMU!X25,0) -> 0 | EL14: =SHEIN!X27 -> 0 | EM14: =IFERROR(EL14/SHEIN!X20,0) -> 0 | EN14: =TK!X34 -> 0 | EO14: =IFERROR(EN14/TK!X25,0) -> 0 | ET14: =EH14+EJ14+EL14+EN14+EP14+ER14 -> 0 | EU14: =IFERROR(ET14/(EH11+EJ11+EL11+EN11),0) -> 0 | EV14: =IFERROR((ET14-EE14)/EE14,0) -> 0 | EW14: =AMAZON!Z69 -> 0 | EX14: =IFERROR(EW14/AMAZON!Z50,0) -> 0 | EY14: =TEMU!Z34 -> 0 | EZ14: =IFERROR(EY14/TEMU!Z25,0) -> 0 | FA14: =SHEIN!Z27 -> 0 | FB14: =IFERROR(FA14/SHEIN!Z20,0) -> 0 | FC14: =TK!Z34 -> 0 | FD14: =IFERROR(FC14/TK!Z25,0) -> 0 | FI14: =EW14+EY14+FA14+FC14+FE14+FG14 -> 0 | FJ14: =IFERROR(FI14/(EW11+EY11+FA11+FC11),0) -> 0 | FK14: =IFERROR((FI14-ET14)/ET14,0) -> 0 | FL14: =AMAZON!AB69 -> 0 | FM14: =IFERROR(FL14/AMAZON!AB50,0) -> 0 | FN14: =TEMU!AB34 -> 0 | FO14: =IFERROR(FN14/TEMU!AB25,0) -> 0 | FP14: =SHEIN!AB27 -> 0 | FQ14: =IFERROR(FP14/SHEIN!AB20,0) -> 0 | FR14: =TK!AB34 -> 0 | FS14: =IFERROR(FR14/TK!AB25,0) -> 0 | FX14: =FL14+FN14+FP14+FR14+FT14+FV14 -> 0 | FY14: =IFERROR(FX14/(FL11+FN11+FP11+FR11),0) -> 0 | FZ14: =IFERROR((FX14-FI14)/FI14,0) -> 0 | GA14: =AMAZON!AD69 -> 0 | GB14: =IFERROR(GA14/AMAZON!AD50,0) -> 0 | GC14: =TEMU!AD34 -> 0 | GD14: =IFERROR(GC14/TEMU!AD25,0) -> 0 | GE14: =SHEIN!AD27 -> 0 | GF14: =IFERROR(GE14/SHEIN!AD20,0) -> 0 | GG14: =TK!AD34 -> 0 | GH14: =IFERROR(GG14/TK!AD25,0) -> 0 | GM14: =GA14+GC14+GE14+GG14+GI14+GK14 -> 0 | GN14: =IFERROR(GM14/(GA11+GC11+GE11+GG11),0) -> 0 | GO14: =IFERROR((GM14-FX14)/FX14,0) -> 0
A15: 经营退款 | B15: 退款损失 | C15: 元 | D15: =AMAZON!F78 -> 0 | E15: =IFERROR(D15/AMAZON!F50,0) -> 0 | F15: =TEMU!F38 -> 0 | G15: =IFERROR(F15/TEMU!F25,0) -> 0 | H15: =SHEIN!F30 -> 0 | I15: =IFERROR(H15/SHEIN!F20,0) -> 0 | J15: =TK!F38 -> 0 | K15: =IFERROR(J15/TK!F25,0) -> 0 | P15: =D15+F15+H15+J15+L15+N15 -> 0 | Q15: =IFERROR(P15/(D11+F11+H11+J11),0) -> 0 | R15: =AMAZON!H78 -> 0 | S15: =IFERROR(R15/AMAZON!H50,0) -> 0 | T15: =TEMU!H38 -> 0 | U15: =IFERROR(T15/TEMU!H25,0) -> 0 | V15: =SHEIN!H30 -> 0 | W15: =IFERROR(V15/SHEIN!H20,0) -> 0 | X15: =TK!H38 -> 0 | Y15: =IFERROR(X15/TK!H25,0) -> 0 | AD15: =R15+T15+V15+X15+Z15+AB15 -> 0 | AE15: =IFERROR(AD15/(R11+T11+V11+X11),0) -> 0 | AG15: =AMAZON!J78 -> 0 | AH15: =IFERROR(AG15/AMAZON!J50,0) -> 0 | AI15: =TEMU!J38 -> 0 | AJ15: =IFERROR(AI15/TEMU!J25,0) -> 0 | AK15: =SHEIN!J30 -> 0 | AL15: =IFERROR(AK15/SHEIN!J20,0) -> 0 | AM15: =TK!J38 -> 0 | AN15: =IFERROR(AM15/TK!J25,0) -> 0 | AS15: =AG15+AI15+AK15+AM15+AO15+AQ15 -> 0 | AT15: =IFERROR(AS15/(AG11+AI11+AK11+AM11),0) -> 0 | AU15: =IFERROR((AS15-AD15)/AD15,0) -> 0 | AV15: =AMAZON!L78 -> 0 | AW15: =IFERROR(AV15/AMAZON!L50,0) -> 0 | AX15: =TEMU!L38 -> 0 | AY15: =IFERROR(AX15/TEMU!L25,0) -> 0 | AZ15: =SHEIN!L30 -> 0 | BA15: =IFERROR(AZ15/SHEIN!L20,0) -> 0 | BB15: =TK!L38 -> 0 | BC15: =IFERROR(BB15/TK!L25,0) -> 0 | BH15: =AV15+AX15+AZ15+BB15+BD15+BF15 -> 0 | BI15: =IFERROR(BH15/(AV11+AX11+AZ11+BB11),0) -> 0 | BJ15: =IFERROR((BH15-AS15)/AS15,0) -> 0 | BK15: =AMAZON!N78 -> 0 | BL15: =IFERROR(BK15/AMAZON!N50,0) -> 0 | BM15: =TEMU!N38 -> 0 | BN15: =IFERROR(BM15/TEMU!N25,0) -> 0 | BO15: =SHEIN!N30 -> 0 | BP15: =IFERROR(BO15/SHEIN!N20,0) -> 0 | BQ15: =TK!N38 -> 0 | BR15: =IFERROR(BQ15/TK!N25,0) -> 0 | BW15: =BK15+BM15+BO15+BQ15+BS15+BU15 -> 0 | BX15: =IFERROR(BW15/(BK11+BM11+BO11+BQ11),0) -> 0 | BY15: =IFERROR((BW15-BH15)/BH15,0) -> 0 | BZ15: =AMAZON!P78 -> 0 | CA15: =IFERROR(BZ15/AMAZON!P50,0) -> 0 | CB15: =TEMU!P38 -> 0 | CC15: =IFERROR(CB15/TEMU!P25,0) -> 0 | CD15: =SHEIN!P30 -> 0 | CE15: =IFERROR(CD15/SHEIN!P20,0) -> 0 | CF15: =TK!P38 -> 0 | CG15: =IFERROR(CF15/TK!P25,0) -> 0 | CL15: =BZ15+CB15+CD15+CF15+CH15+CJ15 -> 0 | CM15: =IFERROR(CL15/(BZ11+CB11+CD11+CF11),0) -> 0 | CN15: =IFERROR((CL15-BW15)/BW15,0) -> 0 | CO15: =AMAZON!R78 -> 0 | CP15: =IFERROR(CO15/AMAZON!R50,0) -> 0 | CQ15: =TEMU!R38 -> 0 | CR15: =IFERROR(CQ15/TEMU!R25,0) -> 0 | CS15: =SHEIN!R30 -> 0 | CT15: =IFERROR(CS15/SHEIN!R20,0) -> 0 | CU15: =TK!R38 -> 0 | CV15: =IFERROR(CU15/TK!R25,0) -> 0 | DA15: =CO15+CQ15+CS15+CU15+CW15+CY15 -> 0 | DB15: =IFERROR(DA15/(CO11+CQ11+CS11+CU11),0) -> 0 | DC15: =IFERROR((DA15-CL15)/CL15,0) -> 0 | DD15: =AMAZON!T78 -> 0 | DE15: =IFERROR(DD15/AMAZON!T50,0) -> 0 | DF15: =TEMU!T38 -> 0 | DG15: =IFERROR(DF15/TEMU!T25,0) -> 0 | DH15: =SHEIN!T30 -> 0 | DI15: =IFERROR(DH15/SHEIN!T20,0) -> 0 | DJ15: =TK!T38 -> 0 | DK15: =IFERROR(DJ15/TK!T25,0) -> 0 | DP15: =DD15+DF15+DH15+DJ15+DL15+DN15 -> 0 | DQ15: =IFERROR(DP15/(DD11+DF11+DH11+DJ11),0) -> 0 | DR15: =IFERROR((DP15-DA15)/DA15,0) -> 0 | DS15: =AMAZON!V78 -> 0 | DT15: =IFERROR(DS15/AMAZON!V50,0) -> 0 | DU15: =TEMU!V38 -> 0 | DV15: =IFERROR(DU15/TEMU!V25,0) -> 0 | DW15: =SHEIN!V30 -> 0 | DX15: =IFERROR(DW15/SHEIN!V20,0) -> 0 | DY15: =TK!V38 -> 0 | DZ15: =IFERROR(DY15/TK!V25,0) -> 0 | EE15: =DS15+DU15+DW15+DY15+EA15+EC15 -> 0 | EF15: =IFERROR(EE15/(DS11+DU11+DW11+DY11),0) -> 0 | EG15: =IFERROR((EE15-DP15)/DP15,0) -> 0 | EH15: =AMAZON!X78 -> 0 | EI15: =IFERROR(EH15/AMAZON!X50,0) -> 0 | EJ15: =TEMU!X38 -> 0 | EK15: =IFERROR(EJ15/TEMU!X25,0) -> 0 | EL15: =SHEIN!X30 -> 0 | EM15: =IFERROR(EL15/SHEIN!X20,0) -> 0 | EN15: =TK!X38 -> 0 | EO15: =IFERROR(EN15/TK!X25,0) -> 0 | ET15: =EH15+EJ15+EL15+EN15+EP15+ER15 -> 0 | EU15: =IFERROR(ET15/(EH11+EJ11+EL11+EN11),0) -> 0 | EV15: =IFERROR((ET15-EE15)/EE15,0) -> 0 | EW15: =AMAZON!Z78 -> 0 | EX15: =IFERROR(EW15/AMAZON!Z50,0) -> 0 | EY15: =TEMU!Z38 -> 0 | EZ15: =IFERROR(EY15/TEMU!Z25,0) -> 0 | FA15: =SHEIN!Z30 -> 0 | FB15: =IFERROR(FA15/SHEIN!Z20,0) -> 0 | FC15: =TK!Z38 -> 0 | FD15: =IFERROR(FC15/TK!Z25,0) -> 0 | FI15: =EW15+EY15+FA15+FC15+FE15+FG15 -> 0 | FJ15: =IFERROR(FI15/(EW11+EY11+FA11+FC11),0) -> 0 | FK15: =IFERROR((FI15-ET15)/ET15,0) -> 0 | FL15: =AMAZON!AB78 -> 0 | FM15: =IFERROR(FL15/AMAZON!AB50,0) -> 0 | FN15: =TEMU!AB38 -> 0 | FO15: =IFERROR(FN15/TEMU!AB25,0) -> 0 | FP15: =SHEIN!AB30 -> 0 | FQ15: =IFERROR(FP15/SHEIN!AB20,0) -> 0 | FR15: =TK!AB38 -> 0 | FS15: =IFERROR(FR15/TK!AB25,0) -> 0 | FX15: =FL15+FN15+FP15+FR15+FT15+FV15 -> 0 | FY15: =IFERROR(FX15/(FL11+FN11+FP11+FR11),0) -> 0 | FZ15: =IFERROR((FX15-FI15)/FI15,0) -> 0 | GA15: =AMAZON!AD78 -> 0 | GB15: =IFERROR(GA15/AMAZON!AD50,0) -> 0 | GC15: =TEMU!AD38 -> 0 | GD15: =IFERROR(GC15/TEMU!AD25,0) -> 0 | GE15: =SHEIN!AD30 -> 0 | GF15: =IFERROR(GE15/SHEIN!AD20,0) -> 0 | GG15: =TK!AD38 -> 0 | GH15: =IFERROR(GG15/TK!AD25,0) -> 0 | GM15: =GA15+GC15+GE15+GG15+GI15+GK15 -> 0 | GN15: =IFERROR(GM15/(GA11+GC11+GE11+GG11),0) -> 0 | GO15: =IFERROR((GM15-FX15)/FX15,0) -> 0
A16: 税费 | C16: 元 | D16: =AMAZON!F87 -> 0 | E16: =IFERROR(D16/AMAZON!F50,0) -> 0 | F16: =TEMU!F42 -> 0 | G16: =IFERROR(F16/TEMU!F25,0) -> 0 | H16: =SHEIN!F33 -> 0 | I16: =IFERROR(H16/SHEIN!F20,0) -> 0 | J16: =TK!F42 -> 0 | K16: =IFERROR(J16/TK!F25,0) -> 0 | P16: =D16+F16+H16+J16+L16+N16 -> 0 | Q16: =IFERROR(P16/(D11+F11+H11+J11),0) -> 0 | R16: =AMAZON!H87 -> 0 | S16: =IFERROR(R16/AMAZON!H50,0) -> 0 | T16: =TEMU!H42 -> 0 | U16: =IFERROR(T16/TEMU!H25,0) -> 0 | V16: =SHEIN!H33 -> 0 | W16: =IFERROR(V16/SHEIN!H20,0) -> 0 | X16: =TK!H42 -> 0 | Y16: =IFERROR(X16/TK!H25,0) -> 0 | AD16: =R16+T16+V16+X16+Z16+AB16 -> 0 | AE16: =IFERROR(AD16/(R11+T11+V11+X11),0) -> 0 | AG16: =AMAZON!J87 -> 0 | AH16: =IFERROR(AG16/AMAZON!J50,0) -> 0 | AI16: =TEMU!J42 -> 0 | AJ16: =IFERROR(AI16/TEMU!J25,0) -> 0 | AK16: =SHEIN!J33 -> 0 | AL16: =IFERROR(AK16/SHEIN!J20,0) -> 0 | AM16: =TK!J42 -> 0 | AN16: =IFERROR(AM16/TK!J25,0) -> 0 | AS16: =AG16+AI16+AK16+AM16+AO16+AQ16 -> 0 | AT16: =IFERROR(AS16/(AG11+AI11+AK11+AM11),0) -> 0 | AU16: =IFERROR((AS16-AD16)/AD16,0) -> 0 | AV16: =AMAZON!L87 -> 0 | AW16: =IFERROR(AV16/AMAZON!L50,0) -> 0 | AX16: =TEMU!L42 -> 0 | AY16: =IFERROR(AX16/TEMU!L25,0) -> 0 | AZ16: =SHEIN!L33 -> 0 | BA16: =IFERROR(AZ16/SHEIN!L20,0) -> 0 | BB16: =TK!L42 -> 0 | BC16: =IFERROR(BB16/TK!L25,0) -> 0 | BH16: =AV16+AX16+AZ16+BB16+BD16+BF16 -> 0 | BI16: =IFERROR(BH16/(AV11+AX11+AZ11+BB11),0) -> 0 | BJ16: =IFERROR((BH16-AS16)/AS16,0) -> 0 | BK16: =AMAZON!N87 -> 0 | BL16: =IFERROR(BK16/AMAZON!N50,0) -> 0 | BM16: =TEMU!N42 -> 0 | BN16: =IFERROR(BM16/TEMU!N25,0) -> 0 | BO16: =SHEIN!N33 -> 0 | BP16: =IFERROR(BO16/SHEIN!N20,0) -> 0 | BQ16: =TK!N42 -> 0 | BR16: =IFERROR(BQ16/TK!N25,0) -> 0 | BW16: =BK16+BM16+BO16+BQ16+BS16+BU16 -> 0 | BX16: =IFERROR(BW16/(BK11+BM11+BO11+BQ11),0) -> 0 | BY16: =IFERROR((BW16-BH16)/BH16,0) -> 0 | BZ16: =AMAZON!P87 -> 0 | CA16: =IFERROR(BZ16/AMAZON!P50,0) -> 0 | CB16: =TEMU!P42 -> 0 | CC16: =IFERROR(CB16/TEMU!P25,0) -> 0 | CD16: =SHEIN!P33 -> 0 | CE16: =IFERROR(CD16/SHEIN!P20,0) -> 0 | CF16: =TK!P42 -> 0 | CG16: =IFERROR(CF16/TK!P25,0) -> 0 | CL16: =BZ16+CB16+CD16+CF16+CH16+CJ16 -> 0 | CM16: =IFERROR(CL16/(BZ11+CB11+CD11+CF11),0) -> 0 | CN16: =IFERROR((CL16-BW16)/BW16,0) -> 0 | CO16: =AMAZON!R87 -> 0 | CP16: =IFERROR(CO16/AMAZON!R50,0) -> 0 | CQ16: =TEMU!R42 -> 0 | CR16: =IFERROR(CQ16/TEMU!R25,0) -> 0 | CS16: =SHEIN!R33 -> 0 | CT16: =IFERROR(CS16/SHEIN!R20,0) -> 0 | CU16: =TK!R42 -> 0 | CV16: =IFERROR(CU16/TK!R25,0) -> 0 | DA16: =CO16+CQ16+CS16+CU16+CW16+CY16 -> 0 | DB16: =IFERROR(DA16/(CO11+CQ11+CS11+CU11),0) -> 0 | DC16: =IFERROR((DA16-CL16)/CL16,0) -> 0 | DD16: =AMAZON!T87 -> 0 | DE16: =IFERROR(DD16/AMAZON!T50,0) -> 0 | DF16: =TEMU!T42 -> 0 | DG16: =IFERROR(DF16/TEMU!T25,0) -> 0 | DH16: =SHEIN!T33 -> 0 | DI16: =IFERROR(DH16/SHEIN!T20,0) -> 0 | DJ16: =TK!T42 -> 0 | DK16: =IFERROR(DJ16/TK!T25,0) -> 0 | DP16: =DD16+DF16+DH16+DJ16+DL16+DN16 -> 0 | DQ16: =IFERROR(DP16/(DD11+DF11+DH11+DJ11),0) -> 0 | DR16: =IFERROR((DP16-DA16)/DA16,0) -> 0 | DS16: =AMAZON!V87 -> 0 | DT16: =IFERROR(DS16/AMAZON!V50,0) -> 0 | DU16: =TEMU!V42 -> 0 | DV16: =IFERROR(DU16/TEMU!V25,0) -> 0 | DW16: =SHEIN!V33 -> 0 | DX16: =IFERROR(DW16/SHEIN!V20,0) -> 0 | DY16: =TK!V42 -> 0 | DZ16: =IFERROR(DY16/TK!V25,0) -> 0 | EE16: =DS16+DU16+DW16+DY16+EA16+EC16 -> 0 | EF16: =IFERROR(EE16/(DS11+DU11+DW11+DY11),0) -> 0 | EG16: =IFERROR((EE16-DP16)/DP16,0) -> 0 | EH16: =AMAZON!X87 -> 0 | EI16: =IFERROR(EH16/AMAZON!X50,0) -> 0 | EJ16: =TEMU!X42 -> 0 | EK16: =IFERROR(EJ16/TEMU!X25,0) -> 0 | EL16: =SHEIN!X33 -> 0 | EM16: =IFERROR(EL16/SHEIN!X20,0) -> 0 | EN16: =TK!X42 -> 0 | EO16: =IFERROR(EN16/TK!X25,0) -> 0 | ET16: =EH16+EJ16+EL16+EN16+EP16+ER16 -> 0 | EU16: =IFERROR(ET16/(EH11+EJ11+EL11+EN11),0) -> 0 | EV16: =IFERROR((ET16-EE16)/EE16,0) -> 0 | EW16: =AMAZON!Z87 -> 0 | EX16: =IFERROR(EW16/AMAZON!Z50,0) -> 0 | EY16: =TEMU!Z42 -> 0 | EZ16: =IFERROR(EY16/TEMU!Z25,0) -> 0 | FA16: =SHEIN!Z33 -> 0 | FB16: =IFERROR(FA16/SHEIN!Z20,0) -> 0 | FC16: =TK!Z42 -> 0 | FD16: =IFERROR(FC16/TK!Z25,0) -> 0 | FI16: =EW16+EY16+FA16+FC16+FE16+FG16 -> 0 | FJ16: =IFERROR(FI16/(EW11+EY11+FA11+FC11),0) -> 0 | FK16: =IFERROR((FI16-ET16)/ET16,0) -> 0 | FL16: =AMAZON!AB87 -> 0 | FM16: =IFERROR(FL16/AMAZON!AB50,0) -> 0 | FN16: =TEMU!AB42 -> 0 | FO16: =IFERROR(FN16/TEMU!AB25,0) -> 0 | FP16: =SHEIN!AB33 -> 0 | FQ16: =IFERROR(FP16/SHEIN!AB20,0) -> 0 | FR16: =TK!AB42 -> 0 | FS16: =IFERROR(FR16/TK!AB25,0) -> 0 | FX16: =FL16+FN16+FP16+FR16+FT16+FV16 -> 0 | FY16: =IFERROR(FX16/(FL11+FN11+FP11+FR11),0) -> 0 | FZ16: =IFERROR((FX16-FI16)/FI16,0) -> 0 | GA16: =AMAZON!AD87 -> 0 | GB16: =IFERROR(GA16/AMAZON!AD50,0) -> 0 | GC16: =TEMU!AD42 -> 0 | GD16: =IFERROR(GC16/TEMU!AD25,0) -> 0 | GE16: =SHEIN!AD33 -> 0 | GF16: =IFERROR(GE16/SHEIN!AD20,0) -> 0 | GG16: =TK!AD42 -> 0 | GH16: =IFERROR(GG16/TK!AD25,0) -> 0 | GM16: =GA16+GC16+GE16+GG16+GI16+GK16 -> 0 | GN16: =IFERROR(GM16/(GA11+GC11+GE11+GG11),0) -> 0 | GO16: =IFERROR((GM16-FX16)/FX16,0) -> 0
A17: 平台费用 | C17: 元 | D17: =AMAZON!F96 -> 0 | E17: =IFERROR(D17/AMAZON!F50,0) -> 0 | F17: =TEMU!F46 -> 0 | G17: =IFERROR(F17/TEMU!F25,0) -> 0 | H17: =SHEIN!F36 -> 0 | I17: =IFERROR(H17/SHEIN!F20,0) -> 0 | J17: =TK!F46 -> 0 | K17: =IFERROR(J17/TK!F25,0) -> 0 | P17: =D17+F17+H17+J17+L17+N17 -> 0 | Q17: =IFERROR(P17/(D11+F11+H11+J11),0) -> 0 | R17: =AMAZON!H96 -> 0 | S17: =IFERROR(R17/AMAZON!H50,0) -> 0 | T17: =TEMU!H46 -> 0 | U17: =IFERROR(T17/TEMU!H25,0) -> 0 | V17: =SHEIN!H36 -> 0 | W17: =IFERROR(V17/SHEIN!H20,0) -> 0 | X17: =TK!H46 -> 0 | Y17: =IFERROR(X17/TK!H25,0) -> 0 | AD17: =R17+T17+V17+X17+Z17+AB17 -> 0 | AE17: =IFERROR(AD17/(R11+T11+V11+X11),0) -> 0 | AG17: =AMAZON!J96 -> 0 | AH17: =IFERROR(AG17/AMAZON!J50,0) -> 0 | AI17: =TEMU!J46 -> 0 | AJ17: =IFERROR(AI17/TEMU!J25,0) -> 0 | AK17: =SHEIN!J36 -> 0 | AL17: =IFERROR(AK17/SHEIN!J20,0) -> 0 | AM17: =TK!J46 -> 0 | AN17: =IFERROR(AM17/TK!J25,0) -> 0 | AS17: =AG17+AI17+AK17+AM17+AO17+AQ17 -> 0 | AT17: =IFERROR(AS17/(AG11+AI11+AK11+AM11),0) -> 0 | AU17: =IFERROR((AS17-AD17)/AD17,0) -> 0 | AV17: =AMAZON!L96 -> 0 | AW17: =IFERROR(AV17/AMAZON!L50,0) -> 0 | AX17: =TEMU!L46 -> 0 | AY17: =IFERROR(AX17/TEMU!L25,0) -> 0 | AZ17: =SHEIN!L36 -> 0 | BA17: =IFERROR(AZ17/SHEIN!L20,0) -> 0 | BB17: =TK!L46 -> 0 | BC17: =IFERROR(BB17/TK!L25,0) -> 0 | BH17: =AV17+AX17+AZ17+BB17+BD17+BF17 -> 0 | BI17: =IFERROR(BH17/(AV11+AX11+AZ11+BB11),0) -> 0 | BJ17: =IFERROR((BH17-AS17)/AS17,0) -> 0 | BK17: =AMAZON!N96 -> 0 | BL17: =IFERROR(BK17/AMAZON!N50,0) -> 0 | BM17: =TEMU!N46 -> 0 | BN17: =IFERROR(BM17/TEMU!N25,0) -> 0 | BO17: =SHEIN!N36 -> 0 | BP17: =IFERROR(BO17/SHEIN!N20,0) -> 0 | BQ17: =TK!N46 -> 0 | BR17: =IFERROR(BQ17/TK!N25,0) -> 0 | BW17: =BK17+BM17+BO17+BQ17+BS17+BU17 -> 0 | BX17: =IFERROR(BW17/(BK11+BM11+BO11+BQ11),0) -> 0 | BY17: =IFERROR((BW17-BH17)/BH17,0) -> 0 | BZ17: =AMAZON!P96 -> 0 | CA17: =IFERROR(BZ17/AMAZON!P50,0) -> 0 | CB17: =TEMU!P46 -> 0 | CC17: =IFERROR(CB17/TEMU!P25,0) -> 0 | CD17: =SHEIN!P36 -> 0 | CE17: =IFERROR(CD17/SHEIN!P20,0) -> 0 | CF17: =TK!P46 -> 0 | CG17: =IFERROR(CF17/TK!P25,0) -> 0 | CL17: =BZ17+CB17+CD17+CF17+CH17+CJ17 -> 0 | CM17: =IFERROR(CL17/(BZ11+CB11+CD11+CF11),0) -> 0 | CN17: =IFERROR((CL17-BW17)/BW17,0) -> 0 | CO17: =AMAZON!R96 -> 0 | CP17: =IFERROR(CO17/AMAZON!R50,0) -> 0 | CQ17: =TEMU!R46 -> 0 | CR17: =IFERROR(CQ17/TEMU!R25,0) -> 0 | CS17: =SHEIN!R36 -> 0 | CT17: =IFERROR(CS17/SHEIN!R20,0) -> 0 | CU17: =TK!R46 -> 0 | CV17: =IFERROR(CU17/TK!R25,0) -> 0 | DA17: =CO17+CQ17+CS17+CU17+CW17+CY17 -> 0 | DB17: =IFERROR(DA17/(CO11+CQ11+CS11+CU11),0) -> 0 | DC17: =IFERROR((DA17-CL17)/CL17,0) -> 0 | DD17: =AMAZON!T96 -> 0 | DE17: =IFERROR(DD17/AMAZON!T50,0) -> 0 | DF17: =TEMU!T46 -> 0 | DG17: =IFERROR(DF17/TEMU!T25,0) -> 0 | DH17: =SHEIN!T36 -> 0 | DI17: =IFERROR(DH17/SHEIN!T20,0) -> 0 | DJ17: =TK!T46 -> 0 | DK17: =IFERROR(DJ17/TK!T25,0) -> 0 | DP17: =DD17+DF17+DH17+DJ17+DL17+DN17 -> 0 | DQ17: =IFERROR(DP17/(DD11+DF11+DH11+DJ11),0) -> 0 | DR17: =IFERROR((DP17-DA17)/DA17,0) -> 0 | DS17: =AMAZON!V96 -> 0 | DT17: =IFERROR(DS17/AMAZON!V50,0) -> 0 | DU17: =TEMU!V46 -> 0 | DV17: =IFERROR(DU17/TEMU!V25,0) -> 0 | DW17: =SHEIN!V36 -> 0 | DX17: =IFERROR(DW17/SHEIN!V20,0) -> 0 | DY17: =TK!V46 -> 0 | DZ17: =IFERROR(DY17/TK!V25,0) -> 0 | EE17: =DS17+DU17+DW17+DY17+EA17+EC17 -> 0 | EF17: =IFERROR(EE17/(DS11+DU11+DW11+DY11),0) -> 0 | EG17: =IFERROR((EE17-DP17)/DP17,0) -> 0 | EH17: =AMAZON!X96 -> 0 | EI17: =IFERROR(EH17/AMAZON!X50,0) -> 0 | EJ17: =TEMU!X46 -> 0 | EK17: =IFERROR(EJ17/TEMU!X25,0) -> 0 | EL17: =SHEIN!X36 -> 0 | EM17: =IFERROR(EL17/SHEIN!X20,0) -> 0 | EN17: =TK!X46 -> 0 | EO17: =IFERROR(EN17/TK!X25,0) -> 0 | ET17: =EH17+EJ17+EL17+EN17+EP17+ER17 -> 0 | EU17: =IFERROR(ET17/(EH11+EJ11+EL11+EN11),0) -> 0 | EV17: =IFERROR((ET17-EE17)/EE17,0) -> 0 | EW17: =AMAZON!Z96 -> 0 | EX17: =IFERROR(EW17/AMAZON!Z50,0) -> 0 | EY17: =TEMU!Z46 -> 0 | EZ17: =IFERROR(EY17/TEMU!Z25,0) -> 0 | FA17: =SHEIN!Z36 -> 0 | FB17: =IFERROR(FA17/SHEIN!Z20,0) -> 0 | FC17: =TK!Z46 -> 0 | FD17: =IFERROR(FC17/TK!Z25,0) -> 0 | FI17: =EW17+EY17+FA17+FC17+FE17+FG17 -> 0 | FJ17: =IFERROR(FI17/(EW11+EY11+FA11+FC11),0) -> 0 | FK17: =IFERROR((FI17-ET17)/ET17,0) -> 0 | FL17: =AMAZON!AB96 -> 0 | FM17: =IFERROR(FL17/AMAZON!AB50,0) -> 0 | FN17: =TEMU!AB46 -> 0 | FO17: =IFERROR(FN17/TEMU!AB25,0) -> 0 | FP17: =SHEIN!AB36 -> 0 | FQ17: =IFERROR(FP17/SHEIN!AB20,0) -> 0 | FR17: =TK!AB46 -> 0 | FS17: =IFERROR(FR17/TK!AB25,0) -> 0 | FX17: =FL17+FN17+FP17+FR17+FT17+FV17 -> 0 | FY17: =IFERROR(FX17/(FL11+FN11+FP11+FR11),0) -> 0 | FZ17: =IFERROR((FX17-FI17)/FI17,0) -> 0 | GA17: =AMAZON!AD96 -> 0 | GB17: =IFERROR(GA17/AMAZON!AD50,0) -> 0 | GC17: =TEMU!AD46 -> 0 | GD17: =IFERROR(GC17/TEMU!AD25,0) -> 0 | GE17: =SHEIN!AD36 -> 0 | GF17: =IFERROR(GE17/SHEIN!AD20,0) -> 0 | GG17: =TK!AD46 -> 0 | GH17: =IFERROR(GG17/TK!AD25,0) -> 0 | GM17: =GA17+GC17+GE17+GG17+GI17+GK17 -> 0 | GN17: =IFERROR(GM17/(GA11+GC11+GE11+GG11),0) -> 0 | GO17: =IFERROR((GM17-FX17)/FX17,0) -> 0
A18: 平台费用 | B18: 佣金 | C18: 元 | D18: =AMAZON!F97 -> 0 | E18: =IFERROR(D18/AMAZON!F50,0) -> 0 | F18: =TEMU!F47 -> 0 | G18: =IFERROR(F18/TEMU!F25,0) -> 0 | H18: =SHEIN!F37 -> 0 | I18: =IFERROR(H18/SHEIN!F20,0) -> 0 | J18: =TK!F47 -> 0 | K18: =IFERROR(J18/TK!F25,0) -> 0 | P18: =D18+F18+H18+J18+L18+N18 -> 0 | Q18: =IFERROR(P18/(D11+F11+H11+J11),0) -> 0 | R18: =AMAZON!H97 -> 0 | S18: =IFERROR(R18/AMAZON!H50,0) -> 0 | T18: =TEMU!H47 -> 0 | U18: =IFERROR(T18/TEMU!H25,0) -> 0 | V18: =SHEIN!H37 -> 0 | W18: =IFERROR(V18/SHEIN!H20,0) -> 0 | X18: =TK!H47 -> 0 | Y18: =IFERROR(X18/TK!H25,0) -> 0 | AD18: =R18+T18+V18+X18+Z18+AB18 -> 0 | AE18: =IFERROR(AD18/(R11+T11+V11+X11),0) -> 0 | AG18: =AMAZON!J97 -> 0 | AH18: =IFERROR(AG18/AMAZON!J50,0) -> 0 | AI18: =TEMU!J47 -> 0 | AJ18: =IFERROR(AI18/TEMU!J25,0) -> 0 | AK18: =SHEIN!J37 -> 0 | AL18: =IFERROR(AK18/SHEIN!J20,0) -> 0 | AM18: =TK!J47 -> 0 | AN18: =IFERROR(AM18/TK!J25,0) -> 0 | AS18: =AG18+AI18+AK18+AM18+AO18+AQ18 -> 0 | AT18: =IFERROR(AS18/(AG11+AI11+AK11+AM11),0) -> 0 | AU18: =IFERROR((AS18-AD18)/AD18,0) -> 0 | AV18: =AMAZON!L97 -> 0 | AW18: =IFERROR(AV18/AMAZON!L50,0) -> 0 | AX18: =TEMU!L47 -> 0 | AY18: =IFERROR(AX18/TEMU!L25,0) -> 0 | AZ18: =SHEIN!L37 -> 0 | BA18: =IFERROR(AZ18/SHEIN!L20,0) -> 0 | BB18: =TK!L47 -> 0 | BC18: =IFERROR(BB18/TK!L25,0) -> 0 | BH18: =AV18+AX18+AZ18+BB18+BD18+BF18 -> 0 | BI18: =IFERROR(BH18/(AV11+AX11+AZ11+BB11),0) -> 0 | BJ18: =IFERROR((BH18-AS18)/AS18,0) -> 0 | BK18: =AMAZON!N97 -> 0 | BL18: =IFERROR(BK18/AMAZON!N50,0) -> 0 | BM18: =TEMU!N47 -> 0 | BN18: =IFERROR(BM18/TEMU!N25,0) -> 0 | BO18: =SHEIN!N37 -> 0 | BP18: =IFERROR(BO18/SHEIN!N20,0) -> 0 | BQ18: =TK!N47 -> 0 | BR18: =IFERROR(BQ18/TK!N25,0) -> 0 | BW18: =BK18+BM18+BO18+BQ18+BS18+BU18 -> 0 | BX18: =IFERROR(BW18/(BK11+BM11+BO11+BQ11),0) -> 0 | BY18: =IFERROR((BW18-BH18)/BH18,0) -> 0 | BZ18: =AMAZON!P97 -> 0 | CA18: =IFERROR(BZ18/AMAZON!P50,0) -> 0 | CB18: =TEMU!P47 -> 0 | CC18: =IFERROR(CB18/TEMU!P25,0) -> 0 | CD18: =SHEIN!P37 -> 0 | CE18: =IFERROR(CD18/SHEIN!P20,0) -> 0 | CF18: =TK!P47 -> 0 | CG18: =IFERROR(CF18/TK!P25,0) -> 0 | CL18: =BZ18+CB18+CD18+CF18+CH18+CJ18 -> 0 | CM18: =IFERROR(CL18/(BZ11+CB11+CD11+CF11),0) -> 0 | CN18: =IFERROR((CL18-BW18)/BW18,0) -> 0 | CO18: =AMAZON!R97 -> 0 | CP18: =IFERROR(CO18/AMAZON!R50,0) -> 0 | CQ18: =TEMU!R47 -> 0 | CR18: =IFERROR(CQ18/TEMU!R25,0) -> 0 | CS18: =SHEIN!R37 -> 0 | CT18: =IFERROR(CS18/SHEIN!R20,0) -> 0 | CU18: =TK!R47 -> 0 | CV18: =IFERROR(CU18/TK!R25,0) -> 0 | DA18: =CO18+CQ18+CS18+CU18+CW18+CY18 -> 0 | DB18: =IFERROR(DA18/(CO11+CQ11+CS11+CU11),0) -> 0 | DC18: =IFERROR((DA18-CL18)/CL18,0) -> 0 | DD18: =AMAZON!T97 -> 0 | DE18: =IFERROR(DD18/AMAZON!T50,0) -> 0 | DF18: =TEMU!T47 -> 0 | DG18: =IFERROR(DF18/TEMU!T25,0) -> 0 | DH18: =SHEIN!T37 -> 0 | DI18: =IFERROR(DH18/SHEIN!T20,0) -> 0 | DJ18: =TK!T47 -> 0 | DK18: =IFERROR(DJ18/TK!T25,0) -> 0 | DP18: =DD18+DF18+DH18+DJ18+DL18+DN18 -> 0 | DQ18: =IFERROR(DP18/(DD11+DF11+DH11+DJ11),0) -> 0 | DR18: =IFERROR((DP18-DA18)/DA18,0) -> 0 | DS18: =AMAZON!V97 -> 0 | DT18: =IFERROR(DS18/AMAZON!V50,0) -> 0 | DU18: =TEMU!V47 -> 0 | DV18: =IFERROR(DU18/TEMU!V25,0) -> 0 | DW18: =SHEIN!V37 -> 0 | DX18: =IFERROR(DW18/SHEIN!V20,0) -> 0 | DY18: =TK!V47 -> 0 | DZ18: =IFERROR(DY18/TK!V25,0) -> 0 | EE18: =DS18+DU18+DW18+DY18+EA18+EC18 -> 0 | EF18: =IFERROR(EE18/(DS11+DU11+DW11+DY11),0) -> 0 | EG18: =IFERROR((EE18-DP18)/DP18,0) -> 0 | EH18: =AMAZON!X97 -> 0 | EI18: =IFERROR(EH18/AMAZON!X50,0) -> 0 | EJ18: =TEMU!X47 -> 0 | EK18: =IFERROR(EJ18/TEMU!X25,0) -> 0 | EL18: =SHEIN!X37 -> 0 | EM18: =IFERROR(EL18/SHEIN!X20,0) -> 0 | EN18: =TK!X47 -> 0 | EO18: =IFERROR(EN18/TK!X25,0) -> 0 | ET18: =EH18+EJ18+EL18+EN18+EP18+ER18 -> 0 | EU18: =IFERROR(ET18/(EH11+EJ11+EL11+EN11),0) -> 0 | EV18: =IFERROR((ET18-EE18)/EE18,0) -> 0 | EW18: =AMAZON!Z97 -> 0 | EX18: =IFERROR(EW18/AMAZON!Z50,0) -> 0 | EY18: =TEMU!Z47 -> 0 | EZ18: =IFERROR(EY18/TEMU!Z25,0) -> 0 | FA18: =SHEIN!Z37 -> 0 | FB18: =IFERROR(FA18/SHEIN!Z20,0) -> 0 | FC18: =TK!Z47 -> 0 | FD18: =IFERROR(FC18/TK!Z25,0) -> 0 | FI18: =EW18+EY18+FA18+FC18+FE18+FG18 -> 0 | FJ18: =IFERROR(FI18/(EW11+EY11+FA11+FC11),0) -> 0 | FK18: =IFERROR((FI18-ET18)/ET18,0) -> 0 | FL18: =AMAZON!AB97 -> 0 | FM18: =IFERROR(FL18/AMAZON!AB50,0) -> 0 | FN18: =TEMU!AB47 -> 0 | FO18: =IFERROR(FN18/TEMU!AB25,0) -> 0 | FP18: =SHEIN!AB37 -> 0 | FQ18: =IFERROR(FP18/SHEIN!AB20,0) -> 0 | FR18: =TK!AB47 -> 0 | FS18: =IFERROR(FR18/TK!AB25,0) -> 0 | FX18: =FL18+FN18+FP18+FR18+FT18+FV18 -> 0 | FY18: =IFERROR(FX18/(FL11+FN11+FP11+FR11),0) -> 0 | FZ18: =IFERROR((FX18-FI18)/FI18,0) -> 0 | GA18: =AMAZON!AD97 -> 0 | GB18: =IFERROR(GA18/AMAZON!AD50,0) -> 0 | GC18: =TEMU!AD47 -> 0 | GD18: =IFERROR(GC18/TEMU!AD25,0) -> 0 | GE18: =SHEIN!AD37 -> 0 | GF18: =IFERROR(GE18/SHEIN!AD20,0) -> 0 | GG18: =TK!AD47 -> 0 | GH18: =IFERROR(GG18/TK!AD25,0) -> 0 | GM18: =GA18+GC18+GE18+GG18+GI18+GK18 -> 0 | GN18: =IFERROR(GM18/(GA11+GC11+GE11+GG11),0) -> 0 | GO18: =IFERROR((GM18-FX18)/FX18,0) -> 0
A19: 平台费用 | B19: 广告 | C19: 元 | D19: =AMAZON!F106 -> 0 | E19: =IFERROR(D19/AMAZON!F50,0) -> 0 | F19: =TEMU!F51 -> 0 | G19: =IFERROR(F19/TEMU!F25,0) -> 0 | H19: =SHEIN!F40 -> 0 | I19: =IFERROR(H19/SHEIN!F20,0) -> 0 | J19: =TK!F51 -> 0 | K19: =IFERROR(J19/TK!F25,0) -> 0 | P19: =D19+F19+H19+J19+L19+N19 -> 0 | Q19: =IFERROR(P19/(D11+F11+H11+J11),0) -> 0 | R19: =AMAZON!H106 -> 0 | S19: =IFERROR(R19/AMAZON!H50,0) -> 0 | T19: =TEMU!H51 -> 0 | U19: =IFERROR(T19/TEMU!H25,0) -> 0 | V19: =SHEIN!H40 -> 0 | W19: =IFERROR(V19/SHEIN!H20,0) -> 0 | X19: =TK!H51 -> 0 | Y19: =IFERROR(X19/TK!H25,0) -> 0 | AD19: =R19+T19+V19+X19+Z19+AB19 -> 0 | AE19: =IFERROR(AD19/(R11+T11+V11+X11),0) -> 0 | AG19: =AMAZON!J106 -> 0 | AH19: =IFERROR(AG19/AMAZON!J50,0) -> 0 | AI19: =TEMU!J51 -> 0 | AJ19: =IFERROR(AI19/TEMU!J25,0) -> 0 | AK19: =SHEIN!J40 -> 0 | AL19: =IFERROR(AK19/SHEIN!J20,0) -> 0 | AM19: =TK!J51 -> 0 | AN19: =IFERROR(AM19/TK!J25,0) -> 0 | AS19: =AG19+AI19+AK19+AM19+AO19+AQ19 -> 0 | AT19: =IFERROR(AS19/(AG11+AI11+AK11+AM11),0) -> 0 | AU19: =IFERROR((AS19-AD19)/AD19,0) -> 0 | AV19: =AMAZON!L106 -> 0 | AW19: =IFERROR(AV19/AMAZON!L50,0) -> 0 | AX19: =TEMU!L51 -> 0 | AY19: =IFERROR(AX19/TEMU!L25,0) -> 0 | AZ19: =SHEIN!L40 -> 0 | BA19: =IFERROR(AZ19/SHEIN!L20,0) -> 0 | BB19: =TK!L51 -> 0 | BC19: =IFERROR(BB19/TK!L25,0) -> 0 | BH19: =AV19+AX19+AZ19+BB19+BD19+BF19 -> 0 | BI19: =IFERROR(BH19/(AV11+AX11+AZ11+BB11),0) -> 0 | BJ19: =IFERROR((BH19-AS19)/AS19,0) -> 0 | BK19: =AMAZON!N106 -> 0 | BL19: =IFERROR(BK19/AMAZON!N50,0) -> 0 | BM19: =TEMU!N51 -> 0 | BN19: =IFERROR(BM19/TEMU!N25,0) -> 0 | BO19: =SHEIN!N40 -> 0 | BP19: =IFERROR(BO19/SHEIN!N20,0) -> 0 | BQ19: =TK!N51 -> 0 | BR19: =IFERROR(BQ19/TK!N25,0) -> 0 | BW19: =BK19+BM19+BO19+BQ19+BS19+BU19 -> 0 | BX19: =IFERROR(BW19/(BK11+BM11+BO11+BQ11),0) -> 0 | BY19: =IFERROR((BW19-BH19)/BH19,0) -> 0 | BZ19: =AMAZON!P106 -> 0 | CA19: =IFERROR(BZ19/AMAZON!P50,0) -> 0 | CB19: =TEMU!P51 -> 0 | CC19: =IFERROR(CB19/TEMU!P25,0) -> 0 | CD19: =SHEIN!P40 -> 0 | CE19: =IFERROR(CD19/SHEIN!P20,0) -> 0 | CF19: =TK!P51 -> 0 | CG19: =IFERROR(CF19/TK!P25,0) -> 0 | CL19: =BZ19+CB19+CD19+CF19+CH19+CJ19 -> 0 | CM19: =IFERROR(CL19/(BZ11+CB11+CD11+CF11),0) -> 0 | CN19: =IFERROR((CL19-BW19)/BW19,0) -> 0 | CO19: =AMAZON!R106 -> 0 | CP19: =IFERROR(CO19/AMAZON!R50,0) -> 0 | CQ19: =TEMU!R51 -> 0 | CR19: =IFERROR(CQ19/TEMU!R25,0) -> 0 | CS19: =SHEIN!R40 -> 0 | CT19: =IFERROR(CS19/SHEIN!R20,0) -> 0 | CU19: =TK!R51 -> 0 | CV19: =IFERROR(CU19/TK!R25,0) -> 0 | DA19: =CO19+CQ19+CS19+CU19+CW19+CY19 -> 0 | DB19: =IFERROR(DA19/(CO11+CQ11+CS11+CU11),0) -> 0 | DC19: =IFERROR((DA19-CL19)/CL19,0) -> 0 | DD19: =AMAZON!T106 -> 0 | DE19: =IFERROR(DD19/AMAZON!T50,0) -> 0 | DF19: =TEMU!T51 -> 0 | DG19: =IFERROR(DF19/TEMU!T25,0) -> 0 | DH19: =SHEIN!T40 -> 0 | DI19: =IFERROR(DH19/SHEIN!T20,0) -> 0 | DJ19: =TK!T51 -> 0 | DK19: =IFERROR(DJ19/TK!T25,0) -> 0 | DP19: =DD19+DF19+DH19+DJ19+DL19+DN19 -> 0 | DQ19: =IFERROR(DP19/(DD11+DF11+DH11+DJ11),0) -> 0 | DR19: =IFERROR((DP19-DA19)/DA19,0) -> 0 | DS19: =AMAZON!V106 -> 0 | DT19: =IFERROR(DS19/AMAZON!V50,0) -> 0 | DU19: =TEMU!V51 -> 0 | DV19: =IFERROR(DU19/TEMU!V25,0) -> 0 | DW19: =SHEIN!V40 -> 0 | DX19: =IFERROR(DW19/SHEIN!V20,0) -> 0 | DY19: =TK!V51 -> 0 | DZ19: =IFERROR(DY19/TK!V25,0) -> 0 | EE19: =DS19+DU19+DW19+DY19+EA19+EC19 -> 0 | EF19: =IFERROR(EE19/(DS11+DU11+DW11+DY11),0) -> 0 | EG19: =IFERROR((EE19-DP19)/DP19,0) -> 0 | EH19: =AMAZON!X106 -> 0 | EI19: =IFERROR(EH19/AMAZON!X50,0) -> 0 | EJ19: =TEMU!X51 -> 0 | EK19: =IFERROR(EJ19/TEMU!X25,0) -> 0 | EL19: =SHEIN!X40 -> 0 | EM19: =IFERROR(EL19/SHEIN!X20,0) -> 0 | EN19: =TK!X51 -> 0 | EO19: =IFERROR(EN19/TK!X25,0) -> 0 | ET19: =EH19+EJ19+EL19+EN19+EP19+ER19 -> 0 | EU19: =IFERROR(ET19/(EH11+EJ11+EL11+EN11),0) -> 0 | EV19: =IFERROR((ET19-EE19)/EE19,0) -> 0 | EW19: =AMAZON!Z106 -> 0 | EX19: =IFERROR(EW19/AMAZON!Z50,0) -> 0 | EY19: =TEMU!Z51 -> 0 | EZ19: =IFERROR(EY19/TEMU!Z25,0) -> 0 | FA19: =SHEIN!Z40 -> 0 | FB19: =IFERROR(FA19/SHEIN!Z20,0) -> 0 | FC19: =TK!Z51 -> 0 | FD19: =IFERROR(FC19/TK!Z25,0) -> 0 | FI19: =EW19+EY19+FA19+FC19+FE19+FG19 -> 0 | FJ19: =IFERROR(FI19/(EW11+EY11+FA11+FC11),0) -> 0 | FK19: =IFERROR((FI19-ET19)/ET19,0) -> 0 | FL19: =AMAZON!AB106 -> 0 | FM19: =IFERROR(FL19/AMAZON!AB50,0) -> 0 | FN19: =TEMU!AB51 -> 0 | FO19: =IFERROR(FN19/TEMU!AB25,0) -> 0 | FP19: =SHEIN!AB40 -> 0 | FQ19: =IFERROR(FP19/SHEIN!AB20,0) -> 0 | FR19: =TK!AB51 -> 0 | FS19: =IFERROR(FR19/TK!AB25,0) -> 0 | FX19: =FL19+FN19+FP19+FR19+FT19+FV19 -> 0 | FY19: =IFERROR(FX19/(FL11+FN11+FP11+FR11),0) -> 0 | FZ19: =IFERROR((FX19-FI19)/FI19,0) -> 0 | GA19: =AMAZON!AD106 -> 0 | GB19: =IFERROR(GA19/AMAZON!AD50,0) -> 0 | GC19: =TEMU!AD51 -> 0 | GD19: =IFERROR(GC19/TEMU!AD25,0) -> 0 | GE19: =SHEIN!AD40 -> 0 | GF19: =IFERROR(GE19/SHEIN!AD20,0) -> 0 | GG19: =TK!AD51 -> 0 | GH19: =IFERROR(GG19/TK!AD25,0) -> 0 | GM19: =GA19+GC19+GE19+GG19+GI19+GK19 -> 0 | GN19: =IFERROR(GM19/(GA11+GC11+GE11+GG11),0) -> 0 | GO19: =IFERROR((GM19-FX19)/FX19,0) -> 0
A20: 平台费用 | B20: 推广费 | C20: 元 | D20: =AMAZON!F115 -> 0 | E20: =IFERROR(D20/AMAZON!F50,0) -> 0 | F20: =TEMU!F55 -> 0 | G20: =IFERROR(F20/TEMU!F25,0) -> 0 | H20: =SHEIN!F43 -> 0 | I20: =IFERROR(H20/SHEIN!F20,0) -> 0 | J20: =TK!F55 -> 0 | K20: =IFERROR(J20/TK!F25,0) -> 0 | P20: =D20+F20+H20+J20+L20+N20 -> 0 | Q20: =IFERROR(P20/(D11+F11+H11+J11),0) -> 0 | R20: =AMAZON!H115 -> 0 | S20: =IFERROR(R20/AMAZON!H50,0) -> 0 | T20: =TEMU!H55 -> 0 | U20: =IFERROR(T20/TEMU!H25,0) -> 0 | V20: =SHEIN!H43 -> 0 | W20: =IFERROR(V20/SHEIN!H20,0) -> 0 | X20: =TK!H55 -> 0 | Y20: =IFERROR(X20/TK!H25,0) -> 0 | AD20: =R20+T20+V20+X20+Z20+AB20 -> 0 | AE20: =IFERROR(AD20/(R11+T11+V11+X11),0) -> 0 | AG20: =AMAZON!J115 -> 0 | AH20: =IFERROR(AG20/AMAZON!J50,0) -> 0 | AI20: =TEMU!J55 -> 0 | AJ20: =IFERROR(AI20/TEMU!J25,0) -> 0 | AK20: =SHEIN!J43 -> 0 | AL20: =IFERROR(AK20/SHEIN!J20,0) -> 0 | AM20: =TK!J55 -> 0 | AN20: =IFERROR(AM20/TK!J25,0) -> 0 | AS20: =AG20+AI20+AK20+AM20+AO20+AQ20 -> 0 | AT20: =IFERROR(AS20/(AG11+AI11+AK11+AM11),0) -> 0 | AU20: =IFERROR((AS20-AD20)/AD20,0) -> 0 | AV20: =AMAZON!L115 -> 0 | AW20: =IFERROR(AV20/AMAZON!L50,0) -> 0 | AX20: =TEMU!L55 -> 0 | AY20: =IFERROR(AX20/TEMU!L25,0) -> 0 | AZ20: =SHEIN!L43 -> 0 | BA20: =IFERROR(AZ20/SHEIN!L20,0) -> 0 | BB20: =TK!L55 -> 0 | BC20: =IFERROR(BB20/TK!L25,0) -> 0 | BH20: =AV20+AX20+AZ20+BB20+BD20+BF20 -> 0 | BI20: =IFERROR(BH20/(AV11+AX11+AZ11+BB11),0) -> 0 | BJ20: =IFERROR((BH20-AS20)/AS20,0) -> 0 | BK20: =AMAZON!N115 -> 0 | BL20: =IFERROR(BK20/AMAZON!N50,0) -> 0 | BM20: =TEMU!N55 -> 0 | BN20: =IFERROR(BM20/TEMU!N25,0) -> 0 | BO20: =SHEIN!N43 -> 0 | BP20: =IFERROR(BO20/SHEIN!N20,0) -> 0 | BQ20: =TK!N55 -> 0 | BR20: =IFERROR(BQ20/TK!N25,0) -> 0 | BW20: =BK20+BM20+BO20+BQ20+BS20+BU20 -> 0 | BX20: =IFERROR(BW20/(BK11+BM11+BO11+BQ11),0) -> 0 | BY20: =IFERROR((BW20-BH20)/BH20,0) -> 0 | BZ20: =AMAZON!P115 -> 0 | CA20: =IFERROR(BZ20/AMAZON!P50,0) -> 0 | CB20: =TEMU!P55 -> 0 | CC20: =IFERROR(CB20/TEMU!P25,0) -> 0 | CD20: =SHEIN!P43 -> 0 | CE20: =IFERROR(CD20/SHEIN!P20,0) -> 0 | CF20: =TK!P55 -> 0 | CG20: =IFERROR(CF20/TK!P25,0) -> 0 | CL20: =BZ20+CB20+CD20+CF20+CH20+CJ20 -> 0 | CM20: =IFERROR(CL20/(BZ11+CB11+CD11+CF11),0) -> 0 | CN20: =IFERROR((CL20-BW20)/BW20,0) -> 0 | CO20: =AMAZON!R115 -> 0 | CP20: =IFERROR(CO20/AMAZON!R50,0) -> 0 | CQ20: =TEMU!R55 -> 0 | CR20: =IFERROR(CQ20/TEMU!R25,0) -> 0 | CS20: =SHEIN!R43 -> 0 | CT20: =IFERROR(CS20/SHEIN!R20,0) -> 0 | CU20: =TK!R55 -> 0 | CV20: =IFERROR(CU20/TK!R25,0) -> 0 | DA20: =CO20+CQ20+CS20+CU20+CW20+CY20 -> 0 | DB20: =IFERROR(DA20/(CO11+CQ11+CS11+CU11),0) -> 0 | DC20: =IFERROR((DA20-CL20)/CL20,0) -> 0 | DD20: =AMAZON!T115 -> 0 | DE20: =IFERROR(DD20/AMAZON!T50,0) -> 0 | DF20: =TEMU!T55 -> 0 | DG20: =IFERROR(DF20/TEMU!T25,0) -> 0 | DH20: =SHEIN!T43 -> 0 | DI20: =IFERROR(DH20/SHEIN!T20,0) -> 0 | DJ20: =TK!T55 -> 0 | DK20: =IFERROR(DJ20/TK!T25,0) -> 0 | DP20: =DD20+DF20+DH20+DJ20+DL20+DN20 -> 0 | DQ20: =IFERROR(DP20/(DD11+DF11+DH11+DJ11),0) -> 0 | DR20: =IFERROR((DP20-DA20)/DA20,0) -> 0 | DS20: =AMAZON!V115 -> 0 | DT20: =IFERROR(DS20/AMAZON!V50,0) -> 0 | DU20: =TEMU!V55 -> 0 | DV20: =IFERROR(DU20/TEMU!V25,0) -> 0 | DW20: =SHEIN!V43 -> 0 | DX20: =IFERROR(DW20/SHEIN!V20,0) -> 0 | DY20: =TK!V55 -> 0 | DZ20: =IFERROR(DY20/TK!V25,0) -> 0 | EE20: =DS20+DU20+DW20+DY20+EA20+EC20 -> 0 | EF20: =IFERROR(EE20/(DS11+DU11+DW11+DY11),0) -> 0 | EG20: =IFERROR((EE20-DP20)/DP20,0) -> 0 | EH20: =AMAZON!X115 -> 0 | EI20: =IFERROR(EH20/AMAZON!X50,0) -> 0 | EJ20: =TEMU!X55 -> 0 | EK20: =IFERROR(EJ20/TEMU!X25,0) -> 0 | EL20: =SHEIN!X43 -> 0 | EM20: =IFERROR(EL20/SHEIN!X20,0) -> 0 | EN20: =TK!X55 -> 0 | EO20: =IFERROR(EN20/TK!X25,0) -> 0 | ET20: =EH20+EJ20+EL20+EN20+EP20+ER20 -> 0 | EU20: =IFERROR(ET20/(EH11+EJ11+EL11+EN11),0) -> 0 | EV20: =IFERROR((ET20-EE20)/EE20,0) -> 0 | EW20: =AMAZON!Z115 -> 0 | EX20: =IFERROR(EW20/AMAZON!Z50,0) -> 0 | EY20: =TEMU!Z55 -> 0 | EZ20: =IFERROR(EY20/TEMU!Z25,0) -> 0 | FA20: =SHEIN!Z43 -> 0 | FB20: =IFERROR(FA20/SHEIN!Z20,0) -> 0 | FC20: =TK!Z55 -> 0 | FD20: =IFERROR(FC20/TK!Z25,0) -> 0 | FI20: =EW20+EY20+FA20+FC20+FE20+FG20 -> 0 | FJ20: =IFERROR(FI20/(EW11+EY11+FA11+FC11),0) -> 0 | FK20: =IFERROR((FI20-ET20)/ET20,0) -> 0 | FL20: =AMAZON!AB115 -> 0 | FM20: =IFERROR(FL20/AMAZON!AB50,0) -> 0 | FN20: =TEMU!AB55 -> 0 | FO20: =IFERROR(FN20/TEMU!AB25,0) -> 0 | FP20: =SHEIN!AB43 -> 0 | FQ20: =IFERROR(FP20/SHEIN!AB20,0) -> 0 | FR20: =TK!AB55 -> 0 | FS20: =IFERROR(FR20/TK!AB25,0) -> 0 | FX20: =FL20+FN20+FP20+FR20+FT20+FV20 -> 0 | FY20: =IFERROR(FX20/(FL11+FN11+FP11+FR11),0) -> 0 | FZ20: =IFERROR((FX20-FI20)/FI20,0) -> 0 | GA20: =AMAZON!AD115 -> 0 | GB20: =IFERROR(GA20/AMAZON!AD50,0) -> 0 | GC20: =TEMU!AD55 -> 0 | GD20: =IFERROR(GC20/TEMU!AD25,0) -> 0 | GE20: =SHEIN!AD43 -> 0 | GF20: =IFERROR(GE20/SHEIN!AD20,0) -> 0 | GG20: =TK!AD55 -> 0 | GH20: =IFERROR(GG20/TK!AD25,0) -> 0 | GM20: =GA20+GC20+GE20+GG20+GI20+GK20 -> 0 | GN20: =IFERROR(GM20/(GA11+GC11+GE11+GG11),0) -> 0 | GO20: =IFERROR((GM20-FX20)/FX20,0) -> 0
A21: 平台费用 | B21: 尾程配送 | C21: 元 | D21: =AMAZON!F124 -> 0 | E21: =IFERROR(D21/AMAZON!F50,0) -> 0 | F21: =TEMU!F59 -> 0 | G21: =IFERROR(F21/TEMU!F25,0) -> 0 | H21: =SHEIN!F46 -> 0 | I21: =IFERROR(H21/SHEIN!F20,0) -> 0 | J21: =TK!F59 -> 0 | K21: =IFERROR(J21/TK!F25,0) -> 0 | P21: =D21+F21+H21+J21+L21+N21 -> 0 | Q21: =IFERROR(P21/(D11+F11+H11+J11),0) -> 0 | R21: =AMAZON!H124 -> 0 | S21: =IFERROR(R21/AMAZON!H50,0) -> 0 | T21: =TEMU!H59 -> 0 | U21: =IFERROR(T21/TEMU!H25,0) -> 0 | V21: =SHEIN!H46 -> 0 | W21: =IFERROR(V21/SHEIN!H20,0) -> 0 | X21: =TK!H59 -> 0 | Y21: =IFERROR(X21/TK!H25,0) -> 0 | AD21: =R21+T21+V21+X21+Z21+AB21 -> 0 | AE21: =IFERROR(AD21/(R11+T11+V11+X11),0) -> 0 | AG21: =AMAZON!J124 -> 0 | AH21: =IFERROR(AG21/AMAZON!J50,0) -> 0 | AI21: =TEMU!J59 -> 0 | AJ21: =IFERROR(AI21/TEMU!J25,0) -> 0 | AK21: =SHEIN!J46 -> 0 | AL21: =IFERROR(AK21/SHEIN!J20,0) -> 0 | AM21: =TK!J59 -> 0 | AN21: =IFERROR(AM21/TK!J25,0) -> 0 | AS21: =AG21+AI21+AK21+AM21+AO21+AQ21 -> 0 | AT21: =IFERROR(AS21/(AG11+AI11+AK11+AM11),0) -> 0 | AU21: =IFERROR((AS21-AD21)/AD21,0) -> 0 | AV21: =AMAZON!L124 -> 0 | AW21: =IFERROR(AV21/AMAZON!L50,0) -> 0 | AX21: =TEMU!L59 -> 0 | AY21: =IFERROR(AX21/TEMU!L25,0) -> 0 | AZ21: =SHEIN!L46 -> 0 | BA21: =IFERROR(AZ21/SHEIN!L20,0) -> 0 | BB21: =TK!L59 -> 0 | BC21: =IFERROR(BB21/TK!L25,0) -> 0 | BH21: =AV21+AX21+AZ21+BB21+BD21+BF21 -> 0 | BI21: =IFERROR(BH21/(AV11+AX11+AZ11+BB11),0) -> 0 | BJ21: =IFERROR((BH21-AS21)/AS21,0) -> 0 | BK21: =AMAZON!N124 -> 0 | BL21: =IFERROR(BK21/AMAZON!N50,0) -> 0 | BM21: =TEMU!N59 -> 0 | BN21: =IFERROR(BM21/TEMU!N25,0) -> 0 | BO21: =SHEIN!N46 -> 0 | BP21: =IFERROR(BO21/SHEIN!N20,0) -> 0 | BQ21: =TK!N59 -> 0 | BR21: =IFERROR(BQ21/TK!N25,0) -> 0 | BW21: =BK21+BM21+BO21+BQ21+BS21+BU21 -> 0 | BX21: =IFERROR(BW21/(BK11+BM11+BO11+BQ11),0) -> 0 | BY21: =IFERROR((BW21-BH21)/BH21,0) -> 0 | BZ21: =AMAZON!P124 -> 0 | CA21: =IFERROR(BZ21/AMAZON!P50,0) -> 0 | CB21: =TEMU!P59 -> 0 | CC21: =IFERROR(CB21/TEMU!P25,0) -> 0 | CD21: =SHEIN!P46 -> 0 | CE21: =IFERROR(CD21/SHEIN!P20,0) -> 0 | CF21: =TK!P59 -> 0 | CG21: =IFERROR(CF21/TK!P25,0) -> 0 | CL21: =BZ21+CB21+CD21+CF21+CH21+CJ21 -> 0 | CM21: =IFERROR(CL21/(BZ11+CB11+CD11+CF11),0) -> 0 | CN21: =IFERROR((CL21-BW21)/BW21,0) -> 0 | CO21: =AMAZON!R124 -> 0 | CP21: =IFERROR(CO21/AMAZON!R50,0) -> 0 | CQ21: =TEMU!R59 -> 0 | CR21: =IFERROR(CQ21/TEMU!R25,0) -> 0 | CS21: =SHEIN!R46 -> 0 | CT21: =IFERROR(CS21/SHEIN!R20,0) -> 0 | CU21: =TK!R59 -> 0 | CV21: =IFERROR(CU21/TK!R25,0) -> 0 | DA21: =CO21+CQ21+CS21+CU21+CW21+CY21 -> 0 | DB21: =IFERROR(DA21/(CO11+CQ11+CS11+CU11),0) -> 0 | DC21: =IFERROR((DA21-CL21)/CL21,0) -> 0 | DD21: =AMAZON!T124 -> 0 | DE21: =IFERROR(DD21/AMAZON!T50,0) -> 0 | DF21: =TEMU!T59 -> 0 | DG21: =IFERROR(DF21/TEMU!T25,0) -> 0 | DH21: =SHEIN!T46 -> 0 | DI21: =IFERROR(DH21/SHEIN!T20,0) -> 0 | DJ21: =TK!T59 -> 0 | DK21: =IFERROR(DJ21/TK!T25,0) -> 0 | DP21: =DD21+DF21+DH21+DJ21+DL21+DN21 -> 0 | DQ21: =IFERROR(DP21/(DD11+DF11+DH11+DJ11),0) -> 0 | DR21: =IFERROR((DP21-DA21)/DA21,0) -> 0 | DS21: =AMAZON!V124 -> 0 | DT21: =IFERROR(DS21/AMAZON!V50,0) -> 0 | DU21: =TEMU!V59 -> 0 | DV21: =IFERROR(DU21/TEMU!V25,0) -> 0 | DW21: =SHEIN!V46 -> 0 | DX21: =IFERROR(DW21/SHEIN!V20,0) -> 0 | DY21: =TK!V59 -> 0 | DZ21: =IFERROR(DY21/TK!V25,0) -> 0 | EE21: =DS21+DU21+DW21+DY21+EA21+EC21 -> 0 | EF21: =IFERROR(EE21/(DS11+DU11+DW11+DY11),0) -> 0 | EG21: =IFERROR((EE21-DP21)/DP21,0) -> 0 | EH21: =AMAZON!X124 -> 0 | EI21: =IFERROR(EH21/AMAZON!X50,0) -> 0 | EJ21: =TEMU!X59 -> 0 | EK21: =IFERROR(EJ21/TEMU!X25,0) -> 0 | EL21: =SHEIN!X46 -> 0 | EM21: =IFERROR(EL21/SHEIN!X20,0) -> 0 | EN21: =TK!X59 -> 0 | EO21: =IFERROR(EN21/TK!X25,0) -> 0 | ET21: =EH21+EJ21+EL21+EN21+EP21+ER21 -> 0 | EU21: =IFERROR(ET21/(EH11+EJ11+EL11+EN11),0) -> 0 | EV21: =IFERROR((ET21-EE21)/EE21,0) -> 0 | EW21: =AMAZON!Z124 -> 0 | EX21: =IFERROR(EW21/AMAZON!Z50,0) -> 0 | EY21: =TEMU!Z59 -> 0 | EZ21: =IFERROR(EY21/TEMU!Z25,0) -> 0 | FA21: =SHEIN!Z46 -> 0 | FB21: =IFERROR(FA21/SHEIN!Z20,0) -> 0 | FC21: =TK!Z59 -> 0 | FD21: =IFERROR(FC21/TK!Z25,0) -> 0 | FI21: =EW21+EY21+FA21+FC21+FE21+FG21 -> 0 | FJ21: =IFERROR(FI21/(EW11+EY11+FA11+FC11),0) -> 0 | FK21: =IFERROR((FI21-ET21)/ET21,0) -> 0 | FL21: =AMAZON!AB124 -> 0 | FM21: =IFERROR(FL21/AMAZON!AB50,0) -> 0 | FN21: =TEMU!AB59 -> 0 | FO21: =IFERROR(FN21/TEMU!AB25,0) -> 0 | FP21: =SHEIN!AB46 -> 0 | FQ21: =IFERROR(FP21/SHEIN!AB20,0) -> 0 | FR21: =TK!AB59 -> 0 | FS21: =IFERROR(FR21/TK!AB25,0) -> 0 | FX21: =FL21+FN21+FP21+FR21+FT21+FV21 -> 0 | FY21: =IFERROR(FX21/(FL11+FN11+FP11+FR11),0) -> 0 | FZ21: =IFERROR((FX21-FI21)/FI21,0) -> 0 | GA21: =AMAZON!AD124 -> 0 | GB21: =IFERROR(GA21/AMAZON!AD50,0) -> 0 | GC21: =TEMU!AD59 -> 0 | GD21: =IFERROR(GC21/TEMU!AD25,0) -> 0 | GE21: =SHEIN!AD46 -> 0 | GF21: =IFERROR(GE21/SHEIN!AD20,0) -> 0 | GG21: =TK!AD59 -> 0 | GH21: =IFERROR(GG21/TK!AD25,0) -> 0 | GM21: =GA21+GC21+GE21+GG21+GI21+GK21 -> 0 | GN21: =IFERROR(GM21/(GA11+GC11+GE11+GG11),0) -> 0 | GO21: =IFERROR((GM21-FX21)/FX21,0) -> 0
A22: 平台费用 | B22: 仓租 | C22: 元 | D22: =AMAZON!F133 -> 0 | E22: =IFERROR(D22/AMAZON!F50,0) -> 0 | F22: =TEMU!F63 -> 0 | G22: =IFERROR(F22/TEMU!F25,0) -> 0 | H22: =SHEIN!F49 -> 0 | I22: =IFERROR(H22/SHEIN!F20,0) -> 0 | J22: =TK!F63 -> 0 | K22: =IFERROR(J22/TK!F25,0) -> 0 | P22: =D22+F22+H22+J22+L22+N22 -> 0 | Q22: =IFERROR(P22/(D11+F11+H11+J11),0) -> 0 | R22: =AMAZON!H133 -> 0 | S22: =IFERROR(R22/AMAZON!H50,0) -> 0 | T22: =TEMU!H63 -> 0 | U22: =IFERROR(T22/TEMU!H25,0) -> 0 | V22: =SHEIN!H49 -> 0 | W22: =IFERROR(V22/SHEIN!H20,0) -> 0 | X22: =TK!H63 -> 0 | Y22: =IFERROR(X22/TK!H25,0) -> 0 | AD22: =R22+T22+V22+X22+Z22+AB22 -> 0 | AE22: =IFERROR(AD22/(R11+T11+V11+X11),0) -> 0 | AG22: =AMAZON!J133 -> 0 | AH22: =IFERROR(AG22/AMAZON!J50,0) -> 0 | AI22: =TEMU!J63 -> 0 | AJ22: =IFERROR(AI22/TEMU!J25,0) -> 0 | AK22: =SHEIN!J49 -> 0 | AL22: =IFERROR(AK22/SHEIN!J20,0) -> 0 | AM22: =TK!J63 -> 0 | AN22: =IFERROR(AM22/TK!J25,0) -> 0 | AS22: =AG22+AI22+AK22+AM22+AO22+AQ22 -> 0 | AT22: =IFERROR(AS22/(AG11+AI11+AK11+AM11),0) -> 0 | AU22: =IFERROR((AS22-AD22)/AD22,0) -> 0 | AV22: =AMAZON!L133 -> 0 | AW22: =IFERROR(AV22/AMAZON!L50,0) -> 0 | AX22: =TEMU!L63 -> 0 | AY22: =IFERROR(AX22/TEMU!L25,0) -> 0 | AZ22: =SHEIN!L49 -> 0 | BA22: =IFERROR(AZ22/SHEIN!L20,0) -> 0 | BB22: =TK!L63 -> 0 | BC22: =IFERROR(BB22/TK!L25,0) -> 0 | BH22: =AV22+AX22+AZ22+BB22+BD22+BF22 -> 0 | BI22: =IFERROR(BH22/(AV11+AX11+AZ11+BB11),0) -> 0 | BJ22: =IFERROR((BH22-AS22)/AS22,0) -> 0 | BK22: =AMAZON!N133 -> 0 | BL22: =IFERROR(BK22/AMAZON!N50,0) -> 0 | BM22: =TEMU!N63 -> 0 | BN22: =IFERROR(BM22/TEMU!N25,0) -> 0 | BO22: =SHEIN!N49 -> 0 | BP22: =IFERROR(BO22/SHEIN!N20,0) -> 0 | BQ22: =TK!N63 -> 0 | BR22: =IFERROR(BQ22/TK!N25,0) -> 0 | BW22: =BK22+BM22+BO22+BQ22+BS22+BU22 -> 0 | BX22: =IFERROR(BW22/(BK11+BM11+BO11+BQ11),0) -> 0 | BY22: =IFERROR((BW22-BH22)/BH22,0) -> 0 | BZ22: =AMAZON!P133 -> 0 | CA22: =IFERROR(BZ22/AMAZON!P50,0) -> 0 | CB22: =TEMU!P63 -> 0 | CC22: =IFERROR(CB22/TEMU!P25,0) -> 0 | CD22: =SHEIN!P49 -> 0 | CE22: =IFERROR(CD22/SHEIN!P20,0) -> 0 | CF22: =TK!P63 -> 0 | CG22: =IFERROR(CF22/TK!P25,0) -> 0 | CL22: =BZ22+CB22+CD22+CF22+CH22+CJ22 -> 0 | CM22: =IFERROR(CL22/(BZ11+CB11+CD11+CF11),0) -> 0 | CN22: =IFERROR((CL22-BW22)/BW22,0) -> 0 | CO22: =AMAZON!R133 -> 0 | CP22: =IFERROR(CO22/AMAZON!R50,0) -> 0 | CQ22: =TEMU!R63 -> 0 | CR22: =IFERROR(CQ22/TEMU!R25,0) -> 0 | CS22: =SHEIN!R49 -> 0 | CT22: =IFERROR(CS22/SHEIN!R20,0) -> 0 | CU22: =TK!R63 -> 0 | CV22: =IFERROR(CU22/TK!R25,0) -> 0 | DA22: =CO22+CQ22+CS22+CU22+CW22+CY22 -> 0 | DB22: =IFERROR(DA22/(CO11+CQ11+CS11+CU11),0) -> 0 | DC22: =IFERROR((DA22-CL22)/CL22,0) -> 0 | DD22: =AMAZON!T133 -> 0 | DE22: =IFERROR(DD22/AMAZON!T50,0) -> 0 | DF22: =TEMU!T63 -> 0 | DG22: =IFERROR(DF22/TEMU!T25,0) -> 0 | DH22: =SHEIN!T49 -> 0 | DI22: =IFERROR(DH22/SHEIN!T20,0) -> 0 | DJ22: =TK!T63 -> 0 | DK22: =IFERROR(DJ22/TK!T25,0) -> 0 | DP22: =DD22+DF22+DH22+DJ22+DL22+DN22 -> 0 | DQ22: =IFERROR(DP22/(DD11+DF11+DH11+DJ11),0) -> 0 | DR22: =IFERROR((DP22-DA22)/DA22,0) -> 0 | DS22: =AMAZON!V133 -> 0 | DT22: =IFERROR(DS22/AMAZON!V50,0) -> 0 | DU22: =TEMU!V63 -> 0 | DV22: =IFERROR(DU22/TEMU!V25,0) -> 0 | DW22: =SHEIN!V49 -> 0 | DX22: =IFERROR(DW22/SHEIN!V20,0) -> 0 | DY22: =TK!V63 -> 0 | DZ22: =IFERROR(DY22/TK!V25,0) -> 0 | EE22: =DS22+DU22+DW22+DY22+EA22+EC22 -> 0 | EF22: =IFERROR(EE22/(DS11+DU11+DW11+DY11),0) -> 0 | EG22: =IFERROR((EE22-DP22)/DP22,0) -> 0 | EH22: =AMAZON!X133 -> 0 | EI22: =IFERROR(EH22/AMAZON!X50,0) -> 0 | EJ22: =TEMU!X63 -> 0 | EK22: =IFERROR(EJ22/TEMU!X25,0) -> 0 | EL22: =SHEIN!X49 -> 0 | EM22: =IFERROR(EL22/SHEIN!X20,0) -> 0 | EN22: =TK!X63 -> 0 | EO22: =IFERROR(EN22/TK!X25,0) -> 0 | ET22: =EH22+EJ22+EL22+EN22+EP22+ER22 -> 0 | EU22: =IFERROR(ET22/(EH11+EJ11+EL11+EN11),0) -> 0 | EV22: =IFERROR((ET22-EE22)/EE22,0) -> 0 | EW22: =AMAZON!Z133 -> 0 | EX22: =IFERROR(EW22/AMAZON!Z50,0) -> 0 | EY22: =TEMU!Z63 -> 0 | EZ22: =IFERROR(EY22/TEMU!Z25,0) -> 0 | FA22: =SHEIN!Z49 -> 0 | FB22: =IFERROR(FA22/SHEIN!Z20,0) -> 0 | FC22: =TK!Z63 -> 0 | FD22: =IFERROR(FC22/TK!Z25,0) -> 0 | FI22: =EW22+EY22+FA22+FC22+FE22+FG22 -> 0 | FJ22: =IFERROR(FI22/(EW11+EY11+FA11+FC11),0) -> 0 | FK22: =IFERROR((FI22-ET22)/ET22,0) -> 0 | FL22: =AMAZON!AB133 -> 0 | FM22: =IFERROR(FL22/AMAZON!AB50,0) -> 0 | FN22: =TEMU!AB63 -> 0 | FO22: =IFERROR(FN22/TEMU!AB25,0) -> 0 | FP22: =SHEIN!AB49 -> 0 | FQ22: =IFERROR(FP22/SHEIN!AB20,0) -> 0 | FR22: =TK!AB63 -> 0 | FS22: =IFERROR(FR22/TK!AB25,0) -> 0 | FX22: =FL22+FN22+FP22+FR22+FT22+FV22 -> 0 | FY22: =IFERROR(FX22/(FL11+FN11+FP11+FR11),0) -> 0 | FZ22: =IFERROR((FX22-FI22)/FI22,0) -> 0 | GA22: =AMAZON!AD133 -> 0 | GB22: =IFERROR(GA22/AMAZON!AD50,0) -> 0 | GC22: =TEMU!AD63 -> 0 | GD22: =IFERROR(GC22/TEMU!AD25,0) -> 0 | GE22: =SHEIN!AD49 -> 0 | GF22: =IFERROR(GE22/SHEIN!AD20,0) -> 0 | GG22: =TK!AD63 -> 0 | GH22: =IFERROR(GG22/TK!AD25,0) -> 0 | GM22: =GA22+GC22+GE22+GG22+GI22+GK22 -> 0 | GN22: =IFERROR(GM22/(GA11+GC11+GE11+GG11),0) -> 0 | GO22: =IFERROR((GM22-FX22)/FX22,0) -> 0
A23: 平台费用 | B23: 销毁费 | C23: 元 | D23: =AMAZON!F142 -> 0 | E23: =IFERROR(D23/AMAZON!F50,0) -> 0 | F23: =TEMU!F67 -> 0 | G23: =IFERROR(F23/TEMU!F25,0) -> 0 | H23: =SHEIN!F52 -> 0 | I23: =IFERROR(H23/SHEIN!F20,0) -> 0 | J23: =TK!F67 -> 0 | K23: =IFERROR(J23/TK!F25,0) -> 0 | P23: =D23+F23+H23+J23+L23+N23 -> 0 | Q23: =IFERROR(P23/(D11+F11+H11+J11),0) -> 0 | R23: =AMAZON!H142 -> 0 | S23: =IFERROR(R23/AMAZON!H50,0) -> 0 | T23: =TEMU!H67 -> 0 | U23: =IFERROR(T23/TEMU!H25,0) -> 0 | V23: =SHEIN!H52 -> 0 | W23: =IFERROR(V23/SHEIN!H20,0) -> 0 | X23: =TK!H67 -> 0 | Y23: =IFERROR(X23/TK!H25,0) -> 0 | AD23: =R23+T23+V23+X23+Z23+AB23 -> 0 | AE23: =IFERROR(AD23/(R11+T11+V11+X11),0) -> 0 | AG23: =AMAZON!J142 -> 0 | AH23: =IFERROR(AG23/AMAZON!J50,0) -> 0 | AI23: =TEMU!J67 -> 0 | AJ23: =IFERROR(AI23/TEMU!J25,0) -> 0 | AK23: =SHEIN!J52 -> 0 | AL23: =IFERROR(AK23/SHEIN!J20,0) -> 0 | AM23: =TK!J67 -> 0 | AN23: =IFERROR(AM23/TK!J25,0) -> 0 | AS23: =AG23+AI23+AK23+AM23+AO23+AQ23 -> 0 | AT23: =IFERROR(AS23/(AG11+AI11+AK11+AM11),0) -> 0 | AU23: =IFERROR((AS23-AD23)/AD23,0) -> 0 | AV23: =AMAZON!L142 -> 0 | AW23: =IFERROR(AV23/AMAZON!L50,0) -> 0 | AX23: =TEMU!L67 -> 0 | AY23: =IFERROR(AX23/TEMU!L25,0) -> 0 | AZ23: =SHEIN!L52 -> 0 | BA23: =IFERROR(AZ23/SHEIN!L20,0) -> 0 | BB23: =TK!L67 -> 0 | BC23: =IFERROR(BB23/TK!L25,0) -> 0 | BH23: =AV23+AX23+AZ23+BB23+BD23+BF23 -> 0 | BI23: =IFERROR(BH23/(AV11+AX11+AZ11+BB11),0) -> 0 | BJ23: =IFERROR((BH23-AS23)/AS23,0) -> 0 | BK23: =AMAZON!N142 -> 0 | BL23: =IFERROR(BK23/AMAZON!N50,0) -> 0 | BM23: =TEMU!N67 -> 0 | BN23: =IFERROR(BM23/TEMU!N25,0) -> 0 | BO23: =SHEIN!N52 -> 0 | BP23: =IFERROR(BO23/SHEIN!N20,0) -> 0 | BQ23: =TK!N67 -> 0 | BR23: =IFERROR(BQ23/TK!N25,0) -> 0 | BW23: =BK23+BM23+BO23+BQ23+BS23+BU23 -> 0 | BX23: =IFERROR(BW23/(BK11+BM11+BO11+BQ11),0) -> 0 | BY23: =IFERROR((BW23-BH23)/BH23,0) -> 0 | BZ23: =AMAZON!P142 -> 0 | CA23: =IFERROR(BZ23/AMAZON!P50,0) -> 0 | CB23: =TEMU!P67 -> 0 | CC23: =IFERROR(CB23/TEMU!P25,0) -> 0 | CD23: =SHEIN!P52 -> 0 | CE23: =IFERROR(CD23/SHEIN!P20,0) -> 0 | CF23: =TK!P67 -> 0 | CG23: =IFERROR(CF23/TK!P25,0) -> 0 | CL23: =BZ23+CB23+CD23+CF23+CH23+CJ23 -> 0 | CM23: =IFERROR(CL23/(BZ11+CB11+CD11+CF11),0) -> 0 | CN23: =IFERROR((CL23-BW23)/BW23,0) -> 0 | CO23: =AMAZON!R142 -> 0 | CP23: =IFERROR(CO23/AMAZON!R50,0) -> 0 | CQ23: =TEMU!R67 -> 0 | CR23: =IFERROR(CQ23/TEMU!R25,0) -> 0 | CS23: =SHEIN!R52 -> 0 | CT23: =IFERROR(CS23/SHEIN!R20,0) -> 0 | CU23: =TK!R67 -> 0 | CV23: =IFERROR(CU23/TK!R25,0) -> 0 | DA23: =CO23+CQ23+CS23+CU23+CW23+CY23 -> 0 | DB23: =IFERROR(DA23/(CO11+CQ11+CS11+CU11),0) -> 0 | DC23: =IFERROR((DA23-CL23)/CL23,0) -> 0 | DD23: =AMAZON!T142 -> 0 | DE23: =IFERROR(DD23/AMAZON!T50,0) -> 0 | DF23: =TEMU!T67 -> 0 | DG23: =IFERROR(DF23/TEMU!T25,0) -> 0 | DH23: =SHEIN!T52 -> 0 | DI23: =IFERROR(DH23/SHEIN!T20,0) -> 0 | DJ23: =TK!T67 -> 0 | DK23: =IFERROR(DJ23/TK!T25,0) -> 0 | DP23: =DD23+DF23+DH23+DJ23+DL23+DN23 -> 0 | DQ23: =IFERROR(DP23/(DD11+DF11+DH11+DJ11),0) -> 0 | DR23: =IFERROR((DP23-DA23)/DA23,0) -> 0 | DS23: =AMAZON!V142 -> 0 | DT23: =IFERROR(DS23/AMAZON!V50,0) -> 0 | DU23: =TEMU!V67 -> 0 | DV23: =IFERROR(DU23/TEMU!V25,0) -> 0 | DW23: =SHEIN!V52 -> 0 | DX23: =IFERROR(DW23/SHEIN!V20,0) -> 0 | DY23: =TK!V67 -> 0 | DZ23: =IFERROR(DY23/TK!V25,0) -> 0 | EE23: =DS23+DU23+DW23+DY23+EA23+EC23 -> 0 | EF23: =IFERROR(EE23/(DS11+DU11+DW11+DY11),0) -> 0 | EG23: =IFERROR((EE23-DP23)/DP23,0) -> 0 | EH23: =AMAZON!X142 -> 0 | EI23: =IFERROR(EH23/AMAZON!X50,0) -> 0 | EJ23: =TEMU!X67 -> 0 | EK23: =IFERROR(EJ23/TEMU!X25,0) -> 0 | EL23: =SHEIN!X52 -> 0 | EM23: =IFERROR(EL23/SHEIN!X20,0) -> 0 | EN23: =TK!X67 -> 0 | EO23: =IFERROR(EN23/TK!X25,0) -> 0 | ET23: =EH23+EJ23+EL23+EN23+EP23+ER23 -> 0 | EU23: =IFERROR(ET23/(EH11+EJ11+EL11+EN11),0) -> 0 | EV23: =IFERROR((ET23-EE23)/EE23,0) -> 0 | EW23: =AMAZON!Z142 -> 0 | EX23: =IFERROR(EW23/AMAZON!Z50,0) -> 0 | EY23: =TEMU!Z67 -> 0 | EZ23: =IFERROR(EY23/TEMU!Z25,0) -> 0 | FA23: =SHEIN!Z52 -> 0 | FB23: =IFERROR(FA23/SHEIN!Z20,0) -> 0 | FC23: =TK!Z67 -> 0 | FD23: =IFERROR(FC23/TK!Z25,0) -> 0 | FI23: =EW23+EY23+FA23+FC23+FE23+FG23 -> 0 | FJ23: =IFERROR(FI23/(EW11+EY11+FA11+FC11),0) -> 0 | FK23: =IFERROR((FI23-ET23)/ET23,0) -> 0 | FL23: =AMAZON!AB142 -> 0 | FM23: =IFERROR(FL23/AMAZON!AB50,0) -> 0 | FN23: =TEMU!AB67 -> 0 | FO23: =IFERROR(FN23/TEMU!AB25,0) -> 0 | FP23: =SHEIN!AB52 -> 0 | FQ23: =IFERROR(FP23/SHEIN!AB20,0) -> 0 | FR23: =TK!AB67 -> 0 | FS23: =IFERROR(FR23/TK!AB25,0) -> 0 | FX23: =FL23+FN23+FP23+FR23+FT23+FV23 -> 0 | FY23: =IFERROR(FX23/(FL11+FN11+FP11+FR11),0) -> 0 | FZ23: =IFERROR((FX23-FI23)/FI23,0) -> 0 | GA23: =AMAZON!AD142 -> 0 | GB23: =IFERROR(GA23/AMAZON!AD50,0) -> 0 | GC23: =TEMU!AD67 -> 0 | GD23: =IFERROR(GC23/TEMU!AD25,0) -> 0 | GE23: =SHEIN!AD52 -> 0 | GF23: =IFERROR(GE23/SHEIN!AD20,0) -> 0 | GG23: =TK!AD67 -> 0 | GH23: =IFERROR(GG23/TK!AD25,0) -> 0 | GM23: =GA23+GC23+GE23+GG23+GI23+GK23 -> 0 | GN23: =IFERROR(GM23/(GA11+GC11+GE11+GG11),0) -> 0 | GO23: =IFERROR((GM23-FX23)/FX23,0) -> 0
A24: 平台费用 | B24: 移除费 | C24: 元 | D24: =AMAZON!F151 -> 0 | E24: =IFERROR(D24/AMAZON!F50,0) -> 0 | F24: =TEMU!F71 -> 0 | G24: =IFERROR(F24/TEMU!F25,0) -> 0 | H24: =SHEIN!F55 -> 0 | I24: =IFERROR(H24/SHEIN!F20,0) -> 0 | J24: =TK!F71 -> 0 | K24: =IFERROR(J24/TK!F25,0) -> 0 | P24: =D24+F24+H24+J24+L24+N24 -> 0 | Q24: =IFERROR(P24/(D11+F11+H11+J11),0) -> 0 | R24: =AMAZON!H151 -> 0 | S24: =IFERROR(R24/AMAZON!H50,0) -> 0 | T24: =TEMU!H71 -> 0 | U24: =IFERROR(T24/TEMU!H25,0) -> 0 | V24: =SHEIN!H55 -> 0 | W24: =IFERROR(V24/SHEIN!H20,0) -> 0 | X24: =TK!H71 -> 0 | Y24: =IFERROR(X24/TK!H25,0) -> 0 | AD24: =R24+T24+V24+X24+Z24+AB24 -> 0 | AE24: =IFERROR(AD24/(R11+T11+V11+X11),0) -> 0 | AG24: =AMAZON!J151 -> 0 | AH24: =IFERROR(AG24/AMAZON!J50,0) -> 0 | AI24: =TEMU!J71 -> 0 | AJ24: =IFERROR(AI24/TEMU!J25,0) -> 0 | AK24: =SHEIN!J55 -> 0 | AL24: =IFERROR(AK24/SHEIN!J20,0) -> 0 | AM24: =TK!J71 -> 0 | AN24: =IFERROR(AM24/TK!J25,0) -> 0 | AS24: =AG24+AI24+AK24+AM24+AO24+AQ24 -> 0 | AT24: =IFERROR(AS24/(AG11+AI11+AK11+AM11),0) -> 0 | AU24: =IFERROR((AS24-AD24)/AD24,0) -> 0 | AV24: =AMAZON!L151 -> 0 | AW24: =IFERROR(AV24/AMAZON!L50,0) -> 0 | AX24: =TEMU!L71 -> 0 | AY24: =IFERROR(AX24/TEMU!L25,0) -> 0 | AZ24: =SHEIN!L55 -> 0 | BA24: =IFERROR(AZ24/SHEIN!L20,0) -> 0 | BB24: =TK!L71 -> 0 | BC24: =IFERROR(BB24/TK!L25,0) -> 0 | BH24: =AV24+AX24+AZ24+BB24+BD24+BF24 -> 0 | BI24: =IFERROR(BH24/(AV11+AX11+AZ11+BB11),0) -> 0 | BJ24: =IFERROR((BH24-AS24)/AS24,0) -> 0 | BK24: =AMAZON!N151 -> 0 | BL24: =IFERROR(BK24/AMAZON!N50,0) -> 0 | BM24: =TEMU!N71 -> 0 | BN24: =IFERROR(BM24/TEMU!N25,0) -> 0 | BO24: =SHEIN!N55 -> 0 | BP24: =IFERROR(BO24/SHEIN!N20,0) -> 0 | BQ24: =TK!N71 -> 0 | BR24: =IFERROR(BQ24/TK!N25,0) -> 0 | BW24: =BK24+BM24+BO24+BQ24+BS24+BU24 -> 0 | BX24: =IFERROR(BW24/(BK11+BM11+BO11+BQ11),0) -> 0 | BY24: =IFERROR((BW24-BH24)/BH24,0) -> 0 | BZ24: =AMAZON!P151 -> 0 | CA24: =IFERROR(BZ24/AMAZON!P50,0) -> 0 | CB24: =TEMU!P71 -> 0 | CC24: =IFERROR(CB24/TEMU!P25,0) -> 0 | CD24: =SHEIN!P55 -> 0 | CE24: =IFERROR(CD24/SHEIN!P20,0) -> 0 | CF24: =TK!P71 -> 0 | CG24: =IFERROR(CF24/TK!P25,0) -> 0 | CL24: =BZ24+CB24+CD24+CF24+CH24+CJ24 -> 0 | CM24: =IFERROR(CL24/(BZ11+CB11+CD11+CF11),0) -> 0 | CN24: =IFERROR((CL24-BW24)/BW24,0) -> 0 | CO24: =AMAZON!R151 -> 0 | CP24: =IFERROR(CO24/AMAZON!R50,0) -> 0 | CQ24: =TEMU!R71 -> 0 | CR24: =IFERROR(CQ24/TEMU!R25,0) -> 0 | CS24: =SHEIN!R55 -> 0 | CT24: =IFERROR(CS24/SHEIN!R20,0) -> 0 | CU24: =TK!R71 -> 0 | CV24: =IFERROR(CU24/TK!R25,0) -> 0 | DA24: =CO24+CQ24+CS24+CU24+CW24+CY24 -> 0 | DB24: =IFERROR(DA24/(CO11+CQ11+CS11+CU11),0) -> 0 | DC24: =IFERROR((DA24-CL24)/CL24,0) -> 0 | DD24: =AMAZON!T151 -> 0 | DE24: =IFERROR(DD24/AMAZON!T50,0) -> 0 | DF24: =TEMU!T71 -> 0 | DG24: =IFERROR(DF24/TEMU!T25,0) -> 0 | DH24: =SHEIN!T55 -> 0 | DI24: =IFERROR(DH24/SHEIN!T20,0) -> 0 | DJ24: =TK!T71 -> 0 | DK24: =IFERROR(DJ24/TK!T25,0) -> 0 | DP24: =DD24+DF24+DH24+DJ24+DL24+DN24 -> 0 | DQ24: =IFERROR(DP24/(DD11+DF11+DH11+DJ11),0) -> 0 | DR24: =IFERROR((DP24-DA24)/DA24,0) -> 0 | DS24: =AMAZON!V151 -> 0 | DT24: =IFERROR(DS24/AMAZON!V50,0) -> 0 | DU24: =TEMU!V71 -> 0 | DV24: =IFERROR(DU24/TEMU!V25,0) -> 0 | DW24: =SHEIN!V55 -> 0 | DX24: =IFERROR(DW24/SHEIN!V20,0) -> 0 | DY24: =TK!V71 -> 0 | DZ24: =IFERROR(DY24/TK!V25,0) -> 0 | EE24: =DS24+DU24+DW24+DY24+EA24+EC24 -> 0 | EF24: =IFERROR(EE24/(DS11+DU11+DW11+DY11),0) -> 0 | EG24: =IFERROR((EE24-DP24)/DP24,0) -> 0 | EH24: =AMAZON!X151 -> 0 | EI24: =IFERROR(EH24/AMAZON!X50,0) -> 0 | EJ24: =TEMU!X71 -> 0 | EK24: =IFERROR(EJ24/TEMU!X25,0) -> 0 | EL24: =SHEIN!X55 -> 0 | EM24: =IFERROR(EL24/SHEIN!X20,0) -> 0 | EN24: =TK!X71 -> 0 | EO24: =IFERROR(EN24/TK!X25,0) -> 0 | ET24: =EH24+EJ24+EL24+EN24+EP24+ER24 -> 0 | EU24: =IFERROR(ET24/(EH11+EJ11+EL11+EN11),0) -> 0 | EV24: =IFERROR((ET24-EE24)/EE24,0) -> 0 | EW24: =AMAZON!Z151 -> 0 | EX24: =IFERROR(EW24/AMAZON!Z50,0) -> 0 | EY24: =TEMU!Z71 -> 0 | EZ24: =IFERROR(EY24/TEMU!Z25,0) -> 0 | FA24: =SHEIN!Z55 -> 0 | FB24: =IFERROR(FA24/SHEIN!Z20,0) -> 0 | FC24: =TK!Z71 -> 0 | FD24: =IFERROR(FC24/TK!Z25,0) -> 0 | FI24: =EW24+EY24+FA24+FC24+FE24+FG24 -> 0 | FJ24: =IFERROR(FI24/(EW11+EY11+FA11+FC11),0) -> 0 | FK24: =IFERROR((FI24-ET24)/ET24,0) -> 0 | FL24: =AMAZON!AB151 -> 0 | FM24: =IFERROR(FL24/AMAZON!AB50,0) -> 0 | FN24: =TEMU!AB71 -> 0 | FO24: =IFERROR(FN24/TEMU!AB25,0) -> 0 | FP24: =SHEIN!AB55 -> 0 | FQ24: =IFERROR(FP24/SHEIN!AB20,0) -> 0 | FR24: =TK!AB71 -> 0 | FS24: =IFERROR(FR24/TK!AB25,0) -> 0 | FX24: =FL24+FN24+FP24+FR24+FT24+FV24 -> 0 | FY24: =IFERROR(FX24/(FL11+FN11+FP11+FR11),0) -> 0 | FZ24: =IFERROR((FX24-FI24)/FI24,0) -> 0 | GA24: =AMAZON!AD151 -> 0 | GB24: =IFERROR(GA24/AMAZON!AD50,0) -> 0 | GC24: =TEMU!AD71 -> 0 | GD24: =IFERROR(GC24/TEMU!AD25,0) -> 0 | GE24: =SHEIN!AD55 -> 0 | GF24: =IFERROR(GE24/SHEIN!AD20,0) -> 0 | GG24: =TK!AD71 -> 0 | GH24: =IFERROR(GG24/TK!AD25,0) -> 0 | GM24: =GA24+GC24+GE24+GG24+GI24+GK24 -> 0 | GN24: =IFERROR(GM24/(GA11+GC11+GE11+GG11),0) -> 0 | GO24: =IFERROR((GM24-FX24)/FX24,0) -> 0
A25: 平台费用 | B25: 平台罚款 | C25: 元 | D25: =AMAZON!F160 -> 0 | E25: =IFERROR(D25/AMAZON!F50,0) -> 0 | F25: =TEMU!F75 -> 0 | G25: =IFERROR(F25/TEMU!F25,0) -> 0 | H25: =SHEIN!F58 -> 0 | I25: =IFERROR(H25/SHEIN!F20,0) -> 0 | J25: =TK!F75 -> 0 | K25: =IFERROR(J25/TK!F25,0) -> 0 | P25: =D25+F25+H25+J25+L25+N25 -> 0 | Q25: =IFERROR(P25/(D11+F11+H11+J11),0) -> 0 | R25: =AMAZON!H160 -> 0 | S25: =IFERROR(R25/AMAZON!H50,0) -> 0 | T25: =TEMU!H75 -> 0 | U25: =IFERROR(T25/TEMU!H25,0) -> 0 | V25: =SHEIN!H58 -> 0 | W25: =IFERROR(V25/SHEIN!H20,0) -> 0 | X25: =TK!H75 -> 0 | Y25: =IFERROR(X25/TK!H25,0) -> 0 | AD25: =R25+T25+V25+X25+Z25+AB25 -> 0 | AE25: =IFERROR(AD25/(R11+T11+V11+X11),0) -> 0 | AG25: =AMAZON!J160 -> 0 | AH25: =IFERROR(AG25/AMAZON!J50,0) -> 0 | AI25: =TEMU!J75 -> 0 | AJ25: =IFERROR(AI25/TEMU!J25,0) -> 0 | AK25: =SHEIN!J58 -> 0 | AL25: =IFERROR(AK25/SHEIN!J20,0) -> 0 | AM25: =TK!J75 -> 0 | AN25: =IFERROR(AM25/TK!J25,0) -> 0 | AS25: =AG25+AI25+AK25+AM25+AO25+AQ25 -> 0 | AT25: =IFERROR(AS25/(AG11+AI11+AK11+AM11),0) -> 0 | AU25: =IFERROR((AS25-AD25)/AD25,0) -> 0 | AV25: =AMAZON!L160 -> 0 | AW25: =IFERROR(AV25/AMAZON!L50,0) -> 0 | AX25: =TEMU!L75 -> 0 | AY25: =IFERROR(AX25/TEMU!L25,0) -> 0 | AZ25: =SHEIN!L58 -> 0 | BA25: =IFERROR(AZ25/SHEIN!L20,0) -> 0 | BB25: =TK!L75 -> 0 | BC25: =IFERROR(BB25/TK!L25,0) -> 0 | BH25: =AV25+AX25+AZ25+BB25+BD25+BF25 -> 0 | BI25: =IFERROR(BH25/(AV11+AX11+AZ11+BB11),0) -> 0 | BJ25: =IFERROR((BH25-AS25)/AS25,0) -> 0 | BK25: =AMAZON!N160 -> 0 | BL25: =IFERROR(BK25/AMAZON!N50,0) -> 0 | BM25: =TEMU!N75 -> 0 | BN25: =IFERROR(BM25/TEMU!N25,0) -> 0 | BO25: =SHEIN!N58 -> 0 | BP25: =IFERROR(BO25/SHEIN!N20,0) -> 0 | BQ25: =TK!N75 -> 0 | BR25: =IFERROR(BQ25/TK!N25,0) -> 0 | BW25: =BK25+BM25+BO25+BQ25+BS25+BU25 -> 0 | BX25: =IFERROR(BW25/(BK11+BM11+BO11+BQ11),0) -> 0 | BY25: =IFERROR((BW25-BH25)/BH25,0) -> 0 | BZ25: =AMAZON!P160 -> 0 | CA25: =IFERROR(BZ25/AMAZON!P50,0) -> 0 | CB25: =TEMU!P75 -> 0 | CC25: =IFERROR(CB25/TEMU!P25,0) -> 0 | CD25: =SHEIN!P58 -> 0 | CE25: =IFERROR(CD25/SHEIN!P20,0) -> 0 | CF25: =TK!P75 -> 0 | CG25: =IFERROR(CF25/TK!P25,0) -> 0 | CL25: =BZ25+CB25+CD25+CF25+CH25+CJ25 -> 0 | CM25: =IFERROR(CL25/(BZ11+CB11+CD11+CF11),0) -> 0 | CN25: =IFERROR((CL25-BW25)/BW25,0) -> 0 | CO25: =AMAZON!R160 -> 0 | CP25: =IFERROR(CO25/AMAZON!R50,0) -> 0 | CQ25: =TEMU!R75 -> 0 | CR25: =IFERROR(CQ25/TEMU!R25,0) -> 0 | CS25: =SHEIN!R58 -> 0 | CT25: =IFERROR(CS25/SHEIN!R20,0) -> 0 | CU25: =TK!R75 -> 0 | CV25: =IFERROR(CU25/TK!R25,0) -> 0 | DA25: =CO25+CQ25+CS25+CU25+CW25+CY25 -> 0 | DB25: =IFERROR(DA25/(CO11+CQ11+CS11+CU11),0) -> 0 | DC25: =IFERROR((DA25-CL25)/CL25,0) -> 0 | DD25: =AMAZON!T160 -> 0 | DE25: =IFERROR(DD25/AMAZON!T50,0) -> 0 | DF25: =TEMU!T75 -> 0 | DG25: =IFERROR(DF25/TEMU!T25,0) -> 0 | DH25: =SHEIN!T58 -> 0 | DI25: =IFERROR(DH25/SHEIN!T20,0) -> 0 | DJ25: =TK!T75 -> 0 | DK25: =IFERROR(DJ25/TK!T25,0) -> 0 | DP25: =DD25+DF25+DH25+DJ25+DL25+DN25 -> 0 | DQ25: =IFERROR(DP25/(DD11+DF11+DH11+DJ11),0) -> 0 | DR25: =IFERROR((DP25-DA25)/DA25,0) -> 0 | DS25: =AMAZON!V160 -> 0 | DT25: =IFERROR(DS25/AMAZON!V50,0) -> 0 | DU25: =TEMU!V75 -> 0 | DV25: =IFERROR(DU25/TEMU!V25,0) -> 0 | DW25: =SHEIN!V58 -> 0 | DX25: =IFERROR(DW25/SHEIN!V20,0) -> 0 | DY25: =TK!V75 -> 0 | DZ25: =IFERROR(DY25/TK!V25,0) -> 0 | EE25: =DS25+DU25+DW25+DY25+EA25+EC25 -> 0 | EF25: =IFERROR(EE25/(DS11+DU11+DW11+DY11),0) -> 0 | EG25: =IFERROR((EE25-DP25)/DP25,0) -> 0 | EH25: =AMAZON!X160 -> 0 | EI25: =IFERROR(EH25/AMAZON!X50,0) -> 0 | EJ25: =TEMU!X75 -> 0 | EK25: =IFERROR(EJ25/TEMU!X25,0) -> 0 | EL25: =SHEIN!X58 -> 0 | EM25: =IFERROR(EL25/SHEIN!X20,0) -> 0 | EN25: =TK!X75 -> 0 | EO25: =IFERROR(EN25/TK!X25,0) -> 0 | ET25: =EH25+EJ25+EL25+EN25+EP25+ER25 -> 0 | EU25: =IFERROR(ET25/(EH11+EJ11+EL11+EN11),0) -> 0 | EV25: =IFERROR((ET25-EE25)/EE25,0) -> 0 | EW25: =AMAZON!Z160 -> 0 | EX25: =IFERROR(EW25/AMAZON!Z50,0) -> 0 | EY25: =TEMU!Z75 -> 0 | EZ25: =IFERROR(EY25/TEMU!Z25,0) -> 0 | FA25: =SHEIN!Z58 -> 0 | FB25: =IFERROR(FA25/SHEIN!Z20,0) -> 0 | FC25: =TK!Z75 -> 0 | FD25: =IFERROR(FC25/TK!Z25,0) -> 0 | FI25: =EW25+EY25+FA25+FC25+FE25+FG25 -> 0 | FJ25: =IFERROR(FI25/(EW11+EY11+FA11+FC11),0) -> 0 | FK25: =IFERROR((FI25-ET25)/ET25,0) -> 0 | FL25: =AMAZON!AB160 -> 0 | FM25: =IFERROR(FL25/AMAZON!AB50,0) -> 0 | FN25: =TEMU!AB75 -> 0 | FO25: =IFERROR(FN25/TEMU!AB25,0) -> 0 | FP25: =SHEIN!AB58 -> 0 | FQ25: =IFERROR(FP25/SHEIN!AB20,0) -> 0 | FR25: =TK!AB75 -> 0 | FS25: =IFERROR(FR25/TK!AB25,0) -> 0 | FX25: =FL25+FN25+FP25+FR25+FT25+FV25 -> 0 | FY25: =IFERROR(FX25/(FL11+FN11+FP11+FR11),0) -> 0 | FZ25: =IFERROR((FX25-FI25)/FI25,0) -> 0 | GA25: =AMAZON!AD160 -> 0 | GB25: =IFERROR(GA25/AMAZON!AD50,0) -> 0 | GC25: =TEMU!AD75 -> 0 | GD25: =IFERROR(GC25/TEMU!AD25,0) -> 0 | GE25: =SHEIN!AD58 -> 0 | GF25: =IFERROR(GE25/SHEIN!AD20,0) -> 0 | GG25: =TK!AD75 -> 0 | GH25: =IFERROR(GG25/TK!AD25,0) -> 0 | GM25: =GA25+GC25+GE25+GG25+GI25+GK25 -> 0 | GN25: =IFERROR(GM25/(GA11+GC11+GE11+GG11),0) -> 0 | GO25: =IFERROR((GM25-FX25)/FX25,0) -> 0
A26: 平台费用 | B26: 退货费 | C26: 元 | D26: =AMAZON!F169 -> 0 | E26: =IFERROR(D26/AMAZON!F50,0) -> 0 | F26: =TEMU!F79 -> 0 | G26: =IFERROR(F26/TEMU!F25,0) -> 0 | H26: =SHEIN!F61 -> 0 | I26: =IFERROR(H26/SHEIN!F20,0) -> 0 | J26: =TK!F79 -> 0 | K26: =IFERROR(J26/TK!F25,0) -> 0 | P26: =D26+F26+H26+J26+L26+N26 -> 0 | Q26: =IFERROR(P26/(D11+F11+H11+J11),0) -> 0 | R26: =AMAZON!H169 -> 0 | S26: =IFERROR(R26/AMAZON!H50,0) -> 0 | T26: =TEMU!H79 -> 0 | U26: =IFERROR(T26/TEMU!H25,0) -> 0 | V26: =SHEIN!H61 -> 0 | W26: =IFERROR(V26/SHEIN!H20,0) -> 0 | X26: =TK!H79 -> 0 | Y26: =IFERROR(X26/TK!H25,0) -> 0 | AD26: =R26+T26+V26+X26+Z26+AB26 -> 0 | AE26: =IFERROR(AD26/(R11+T11+V11+X11),0) -> 0 | AG26: =AMAZON!J169 -> 0 | AH26: =IFERROR(AG26/AMAZON!J50,0) -> 0 | AI26: =TEMU!J79 -> 0 | AJ26: =IFERROR(AI26/TEMU!J25,0) -> 0 | AK26: =SHEIN!J61 -> 0 | AL26: =IFERROR(AK26/SHEIN!J20,0) -> 0 | AM26: =TK!J79 -> 0 | AN26: =IFERROR(AM26/TK!J25,0) -> 0 | AS26: =AG26+AI26+AK26+AM26+AO26+AQ26 -> 0 | AT26: =IFERROR(AS26/(AG11+AI11+AK11+AM11),0) -> 0 | AU26: =IFERROR((AS26-AD26)/AD26,0) -> 0 | AV26: =AMAZON!L169 -> 0 | AW26: =IFERROR(AV26/AMAZON!L50,0) -> 0 | AX26: =TEMU!L79 -> 0 | AY26: =IFERROR(AX26/TEMU!L25,0) -> 0 | AZ26: =SHEIN!L61 -> 0 | BA26: =IFERROR(AZ26/SHEIN!L20,0) -> 0 | BB26: =TK!L79 -> 0 | BC26: =IFERROR(BB26/TK!L25,0) -> 0 | BH26: =AV26+AX26+AZ26+BB26+BD26+BF26 -> 0 | BI26: =IFERROR(BH26/(AV11+AX11+AZ11+BB11),0) -> 0 | BJ26: =IFERROR((BH26-AS26)/AS26,0) -> 0 | BK26: =AMAZON!N169 -> 0 | BL26: =IFERROR(BK26/AMAZON!N50,0) -> 0 | BM26: =TEMU!N79 -> 0 | BN26: =IFERROR(BM26/TEMU!N25,0) -> 0 | BO26: =SHEIN!N61 -> 0 | BP26: =IFERROR(BO26/SHEIN!N20,0) -> 0 | BQ26: =TK!N79 -> 0 | BR26: =IFERROR(BQ26/TK!N25,0) -> 0 | BW26: =BK26+BM26+BO26+BQ26+BS26+BU26 -> 0 | BX26: =IFERROR(BW26/(BK11+BM11+BO11+BQ11),0) -> 0 | BY26: =IFERROR((BW26-BH26)/BH26,0) -> 0 | BZ26: =AMAZON!P169 -> 0 | CA26: =IFERROR(BZ26/AMAZON!P50,0) -> 0 | CB26: =TEMU!P79 -> 0 | CC26: =IFERROR(CB26/TEMU!P25,0) -> 0 | CD26: =SHEIN!P61 -> 0 | CE26: =IFERROR(CD26/SHEIN!P20,0) -> 0 | CF26: =TK!P79 -> 0 | CG26: =IFERROR(CF26/TK!P25,0) -> 0 | CL26: =BZ26+CB26+CD26+CF26+CH26+CJ26 -> 0 | CM26: =IFERROR(CL26/(BZ11+CB11+CD11+CF11),0) -> 0 | CN26: =IFERROR((CL26-BW26)/BW26,0) -> 0 | CO26: =AMAZON!R169 -> 0 | CP26: =IFERROR(CO26/AMAZON!R50,0) -> 0 | CQ26: =TEMU!R79 -> 0 | CR26: =IFERROR(CQ26/TEMU!R25,0) -> 0 | CS26: =SHEIN!R61 -> 0 | CT26: =IFERROR(CS26/SHEIN!R20,0) -> 0 | CU26: =TK!R79 -> 0 | CV26: =IFERROR(CU26/TK!R25,0) -> 0 | DA26: =CO26+CQ26+CS26+CU26+CW26+CY26 -> 0 | DB26: =IFERROR(DA26/(CO11+CQ11+CS11+CU11),0) -> 0 | DC26: =IFERROR((DA26-CL26)/CL26,0) -> 0 | DD26: =AMAZON!T169 -> 0 | DE26: =IFERROR(DD26/AMAZON!T50,0) -> 0 | DF26: =TEMU!T79 -> 0 | DG26: =IFERROR(DF26/TEMU!T25,0) -> 0 | DH26: =SHEIN!T61 -> 0 | DI26: =IFERROR(DH26/SHEIN!T20,0) -> 0 | DJ26: =TK!T79 -> 0 | DK26: =IFERROR(DJ26/TK!T25,0) -> 0 | DP26: =DD26+DF26+DH26+DJ26+DL26+DN26 -> 0 | DQ26: =IFERROR(DP26/(DD11+DF11+DH11+DJ11),0) -> 0 | DR26: =IFERROR((DP26-DA26)/DA26,0) -> 0 | DS26: =AMAZON!V169 -> 0 | DT26: =IFERROR(DS26/AMAZON!V50,0) -> 0 | DU26: =TEMU!V79 -> 0 | DV26: =IFERROR(DU26/TEMU!V25,0) -> 0 | DW26: =SHEIN!V61 -> 0 | DX26: =IFERROR(DW26/SHEIN!V20,0) -> 0 | DY26: =TK!V79 -> 0 | DZ26: =IFERROR(DY26/TK!V25,0) -> 0 | EE26: =DS26+DU26+DW26+DY26+EA26+EC26 -> 0 | EF26: =IFERROR(EE26/(DS11+DU11+DW11+DY11),0) -> 0 | EG26: =IFERROR((EE26-DP26)/DP26,0) -> 0 | EH26: =AMAZON!X169 -> 0 | EI26: =IFERROR(EH26/AMAZON!X50,0) -> 0 | EJ26: =TEMU!X79 -> 0 | EK26: =IFERROR(EJ26/TEMU!X25,0) -> 0 | EL26: =SHEIN!X61 -> 0 | EM26: =IFERROR(EL26/SHEIN!X20,0) -> 0 | EN26: =TK!X79 -> 0 | EO26: =IFERROR(EN26/TK!X25,0) -> 0 | ET26: =EH26+EJ26+EL26+EN26+EP26+ER26 -> 0 | EU26: =IFERROR(ET26/(EH11+EJ11+EL11+EN11),0) -> 0 | EV26: =IFERROR((ET26-EE26)/EE26,0) -> 0 | EW26: =AMAZON!Z169 -> 0 | EX26: =IFERROR(EW26/AMAZON!Z50,0) -> 0 | EY26: =TEMU!Z79 -> 0 | EZ26: =IFERROR(EY26/TEMU!Z25,0) -> 0 | FA26: =SHEIN!Z61 -> 0 | FB26: =IFERROR(FA26/SHEIN!Z20,0) -> 0 | FC26: =TK!Z79 -> 0 | FD26: =IFERROR(FC26/TK!Z25,0) -> 0 | FI26: =EW26+EY26+FA26+FC26+FE26+FG26 -> 0 | FJ26: =IFERROR(FI26/(EW11+EY11+FA11+FC11),0) -> 0 | FK26: =IFERROR((FI26-ET26)/ET26,0) -> 0 | FL26: =AMAZON!AB169 -> 0 | FM26: =IFERROR(FL26/AMAZON!AB50,0) -> 0 | FN26: =TEMU!AB79 -> 0 | FO26: =IFERROR(FN26/TEMU!AB25,0) -> 0 | FP26: =SHEIN!AB61 -> 0 | FQ26: =IFERROR(FP26/SHEIN!AB20,0) -> 0 | FR26: =TK!AB79 -> 0 | FS26: =IFERROR(FR26/TK!AB25,0) -> 0 | FX26: =FL26+FN26+FP26+FR26+FT26+FV26 -> 0 | FY26: =IFERROR(FX26/(FL11+FN11+FP11+FR11),0) -> 0 | FZ26: =IFERROR((FX26-FI26)/FI26,0) -> 0 | GA26: =AMAZON!AD169 -> 0 | GB26: =IFERROR(GA26/AMAZON!AD50,0) -> 0 | GC26: =TEMU!AD79 -> 0 | GD26: =IFERROR(GC26/TEMU!AD25,0) -> 0 | GE26: =SHEIN!AD61 -> 0 | GF26: =IFERROR(GE26/SHEIN!AD20,0) -> 0 | GG26: =TK!AD79 -> 0 | GH26: =IFERROR(GG26/TK!AD25,0) -> 0 | GM26: =GA26+GC26+GE26+GG26+GI26+GK26 -> 0 | GN26: =IFERROR(GM26/(GA11+GC11+GE11+GG11),0) -> 0 | GO26: =IFERROR((GM26-FX26)/FX26,0) -> 0
A27: 成本 | C27: 元 | D27: =AMAZON!F178 -> 0 | E27: =IFERROR(D27/AMAZON!F50,0) -> 0 | F27: =TEMU!F83 -> 0 | G27: =IFERROR(F27/TEMU!F25,0) -> 0 | H27: =SHEIN!F64 -> 0 | I27: =IFERROR(H27/SHEIN!F20,0) -> 0 | J27: =TK!F83 -> 0 | K27: =IFERROR(J27/TK!F25,0) -> 0 | P27: =D27+F27+H27+J27+L27+N27 -> 0 | Q27: =IFERROR(P27/(D11+F11+H11+J11),0) -> 0 | R27: =AMAZON!H178 -> 0 | S27: =IFERROR(R27/AMAZON!H50,0) -> 0 | T27: =TEMU!H83 -> 0 | U27: =IFERROR(T27/TEMU!H25,0) -> 0 | V27: =SHEIN!H64 -> 0 | W27: =IFERROR(V27/SHEIN!H20,0) -> 0 | X27: =TK!H83 -> 0 | Y27: =IFERROR(X27/TK!H25,0) -> 0 | AD27: =R27+T27+V27+X27+Z27+AB27 -> 0 | AE27: =IFERROR(AD27/(R11+T11+V11+X11),0) -> 0 | AG27: =AMAZON!J178 -> 0 | AH27: =IFERROR(AG27/AMAZON!J50,0) -> 0 | AI27: =TEMU!J83 -> 0 | AJ27: =IFERROR(AI27/TEMU!J25,0) -> 0 | AK27: =SHEIN!J64 -> 0 | AL27: =IFERROR(AK27/SHEIN!J20,0) -> 0 | AM27: =TK!J83 -> 0 | AN27: =IFERROR(AM27/TK!J25,0) -> 0 | AS27: =AG27+AI27+AK27+AM27+AO27+AQ27 -> 0 | AT27: =IFERROR(AS27/(AG11+AI11+AK11+AM11),0) -> 0 | AU27: =IFERROR((AS27-AD27)/AD27,0) -> 0 | AV27: =AMAZON!L178 -> 0 | AW27: =IFERROR(AV27/AMAZON!L50,0) -> 0 | AX27: =TEMU!L83 -> 0 | AY27: =IFERROR(AX27/TEMU!L25,0) -> 0 | AZ27: =SHEIN!L64 -> 0 | BA27: =IFERROR(AZ27/SHEIN!L20,0) -> 0 | BB27: =TK!L83 -> 0 | BC27: =IFERROR(BB27/TK!L25,0) -> 0 | BH27: =AV27+AX27+AZ27+BB27+BD27+BF27 -> 0 | BI27: =IFERROR(BH27/(AV11+AX11+AZ11+BB11),0) -> 0 | BJ27: =IFERROR((BH27-AS27)/AS27,0) -> 0 | BK27: =AMAZON!N178 -> 0 | BL27: =IFERROR(BK27/AMAZON!N50,0) -> 0 | BM27: =TEMU!N83 -> 0 | BN27: =IFERROR(BM27/TEMU!N25,0) -> 0 | BO27: =SHEIN!N64 -> 0 | BP27: =IFERROR(BO27/SHEIN!N20,0) -> 0 | BQ27: =TK!N83 -> 0 | BR27: =IFERROR(BQ27/TK!N25,0) -> 0 | BW27: =BK27+BM27+BO27+BQ27+BS27+BU27 -> 0 | BX27: =IFERROR(BW27/(BK11+BM11+BO11+BQ11),0) -> 0 | BY27: =IFERROR((BW27-BH27)/BH27,0) -> 0 | BZ27: =AMAZON!P178 -> 0 | CA27: =IFERROR(BZ27/AMAZON!P50,0) -> 0 | CB27: =TEMU!P83 -> 0 | CC27: =IFERROR(CB27/TEMU!P25,0) -> 0 | CD27: =SHEIN!P64 -> 0 | CE27: =IFERROR(CD27/SHEIN!P20,0) -> 0 | CF27: =TK!P83 -> 0 | CG27: =IFERROR(CF27/TK!P25,0) -> 0 | CL27: =BZ27+CB27+CD27+CF27+CH27+CJ27 -> 0 | CM27: =IFERROR(CL27/(BZ11+CB11+CD11+CF11),0) -> 0 | CN27: =IFERROR((CL27-BW27)/BW27,0) -> 0 | CO27: =AMAZON!R178 -> 0 | CP27: =IFERROR(CO27/AMAZON!R50,0) -> 0 | CQ27: =TEMU!R83 -> 0 | CR27: =IFERROR(CQ27/TEMU!R25,0) -> 0 | CS27: =SHEIN!R64 -> 0 | CT27: =IFERROR(CS27/SHEIN!R20,0) -> 0 | CU27: =TK!R83 -> 0 | CV27: =IFERROR(CU27/TK!R25,0) -> 0 | DA27: =CO27+CQ27+CS27+CU27+CW27+CY27 -> 0 | DB27: =IFERROR(DA27/(CO11+CQ11+CS11+CU11),0) -> 0 | DC27: =IFERROR((DA27-CL27)/CL27,0) -> 0 | DD27: =AMAZON!T178 -> 0 | DE27: =IFERROR(DD27/AMAZON!T50,0) -> 0 | DF27: =TEMU!T83 -> 0 | DG27: =IFERROR(DF27/TEMU!T25,0) -> 0 | DH27: =SHEIN!T64 -> 0 | DI27: =IFERROR(DH27/SHEIN!T20,0) -> 0 | DJ27: =TK!T83 -> 0 | DK27: =IFERROR(DJ27/TK!T25,0) -> 0 | DP27: =DD27+DF27+DH27+DJ27+DL27+DN27 -> 0 | DQ27: =IFERROR(DP27/(DD11+DF11+DH11+DJ11),0) -> 0 | DR27: =IFERROR((DP27-DA27)/DA27,0) -> 0 | DS27: =AMAZON!V178 -> 0 | DT27: =IFERROR(DS27/AMAZON!V50,0) -> 0 | DU27: =TEMU!V83 -> 0 | DV27: =IFERROR(DU27/TEMU!V25,0) -> 0 | DW27: =SHEIN!V64 -> 0 | DX27: =IFERROR(DW27/SHEIN!V20,0) -> 0 | DY27: =TK!V83 -> 0 | DZ27: =IFERROR(DY27/TK!V25,0) -> 0 | EE27: =DS27+DU27+DW27+DY27+EA27+EC27 -> 0 | EF27: =IFERROR(EE27/(DS11+DU11+DW11+DY11),0) -> 0 | EG27: =IFERROR((EE27-DP27)/DP27,0) -> 0 | EH27: =AMAZON!X178 -> 0 | EI27: =IFERROR(EH27/AMAZON!X50,0) -> 0 | EJ27: =TEMU!X83 -> 0 | EK27: =IFERROR(EJ27/TEMU!X25,0) -> 0 | EL27: =SHEIN!X64 -> 0 | EM27: =IFERROR(EL27/SHEIN!X20,0) -> 0 | EN27: =TK!X83 -> 0 | EO27: =IFERROR(EN27/TK!X25,0) -> 0 | ET27: =EH27+EJ27+EL27+EN27+EP27+ER27 -> 0 | EU27: =IFERROR(ET27/(EH11+EJ11+EL11+EN11),0) -> 0 | EV27: =IFERROR((ET27-EE27)/EE27,0) -> 0 | EW27: =AMAZON!Z178 -> 0 | EX27: =IFERROR(EW27/AMAZON!Z50,0) -> 0 | EY27: =TEMU!Z83 -> 0 | EZ27: =IFERROR(EY27/TEMU!Z25,0) -> 0 | FA27: =SHEIN!Z64 -> 0 | FB27: =IFERROR(FA27/SHEIN!Z20,0) -> 0 | FC27: =TK!Z83 -> 0 | FD27: =IFERROR(FC27/TK!Z25,0) -> 0 | FI27: =EW27+EY27+FA27+FC27+FE27+FG27 -> 0 | FJ27: =IFERROR(FI27/(EW11+EY11+FA11+FC11),0) -> 0 | FK27: =IFERROR((FI27-ET27)/ET27,0) -> 0 | FL27: =AMAZON!AB178 -> 0 | FM27: =IFERROR(FL27/AMAZON!AB50,0) -> 0 | FN27: =TEMU!AB83 -> 0 | FO27: =IFERROR(FN27/TEMU!AB25,0) -> 0 | FP27: =SHEIN!AB64 -> 0 | FQ27: =IFERROR(FP27/SHEIN!AB20,0) -> 0 | FR27: =TK!AB83 -> 0 | FS27: =IFERROR(FR27/TK!AB25,0) -> 0 | FX27: =FL27+FN27+FP27+FR27+FT27+FV27 -> 0 | FY27: =IFERROR(FX27/(FL11+FN11+FP11+FR11),0) -> 0 | FZ27: =IFERROR((FX27-FI27)/FI27,0) -> 0 | GA27: =AMAZON!AD178 -> 0 | GB27: =IFERROR(GA27/AMAZON!AD50,0) -> 0 | GC27: =TEMU!AD83 -> 0 | GD27: =IFERROR(GC27/TEMU!AD25,0) -> 0 | GE27: =SHEIN!AD64 -> 0 | GF27: =IFERROR(GE27/SHEIN!AD20,0) -> 0 | GG27: =TK!AD83 -> 0 | GH27: =IFERROR(GG27/TK!AD25,0) -> 0 | GM27: =GA27+GC27+GE27+GG27+GI27+GK27 -> 0 | GN27: =IFERROR(GM27/(GA11+GC11+GE11+GG11),0) -> 0 | GO27: =IFERROR((GM27-FX27)/FX27,0) -> 0
A28: 成本 | B28: 采购成本 | C28: 元 | D28: =AMAZON!F187 -> 0 | E28: =IFERROR(D28/AMAZON!F50,0) -> 0 | F28: =TEMU!F87 -> 0 | G28: =IFERROR(F28/TEMU!F25,0) -> 0 | H28: =SHEIN!F67 -> 0 | I28: =IFERROR(H28/SHEIN!F20,0) -> 0 | J28: =TK!F87 -> 0 | K28: =IFERROR(J28/TK!F25,0) -> 0 | P28: =D28+F28+H28+J28+L28+N28 -> 0 | Q28: =IFERROR(P28/(D11+F11+H11+J11),0) -> 0 | R28: =AMAZON!H187 -> 0 | S28: =IFERROR(R28/AMAZON!H50,0) -> 0 | T28: =TEMU!H87 -> 0 | U28: =IFERROR(T28/TEMU!H25,0) -> 0 | V28: =SHEIN!H67 -> 0 | W28: =IFERROR(V28/SHEIN!H20,0) -> 0 | X28: =TK!H87 -> 0 | Y28: =IFERROR(X28/TK!H25,0) -> 0 | AD28: =R28+T28+V28+X28+Z28+AB28 -> 0 | AE28: =IFERROR(AD28/(R11+T11+V11+X11),0) -> 0 | AG28: =AMAZON!J187 -> 0 | AH28: =IFERROR(AG28/AMAZON!J50,0) -> 0 | AI28: =TEMU!J87 -> 0 | AJ28: =IFERROR(AI28/TEMU!J25,0) -> 0 | AK28: =SHEIN!J67 -> 0 | AL28: =IFERROR(AK28/SHEIN!J20,0) -> 0 | AM28: =TK!J87 -> 0 | AN28: =IFERROR(AM28/TK!J25,0) -> 0 | AS28: =AG28+AI28+AK28+AM28+AO28+AQ28 -> 0 | AT28: =IFERROR(AS28/(AG11+AI11+AK11+AM11),0) -> 0 | AU28: =IFERROR((AS28-AD28)/AD28,0) -> 0 | AV28: =AMAZON!L187 -> 0 | AW28: =IFERROR(AV28/AMAZON!L50,0) -> 0 | AX28: =TEMU!L87 -> 0 | AY28: =IFERROR(AX28/TEMU!L25,0) -> 0 | AZ28: =SHEIN!L67 -> 0 | BA28: =IFERROR(AZ28/SHEIN!L20,0) -> 0 | BB28: =TK!L87 -> 0 | BC28: =IFERROR(BB28/TK!L25,0) -> 0 | BH28: =AV28+AX28+AZ28+BB28+BD28+BF28 -> 0 | BI28: =IFERROR(BH28/(AV11+AX11+AZ11+BB11),0) -> 0 | BJ28: =IFERROR((BH28-AS28)/AS28,0) -> 0 | BK28: =AMAZON!N187 -> 0 | BL28: =IFERROR(BK28/AMAZON!N50,0) -> 0 | BM28: =TEMU!N87 -> 0 | BN28: =IFERROR(BM28/TEMU!N25,0) -> 0 | BO28: =SHEIN!N67 -> 0 | BP28: =IFERROR(BO28/SHEIN!N20,0) -> 0 | BQ28: =TK!N87 -> 0 | BR28: =IFERROR(BQ28/TK!N25,0) -> 0 | BW28: =BK28+BM28+BO28+BQ28+BS28+BU28 -> 0 | BX28: =IFERROR(BW28/(BK11+BM11+BO11+BQ11),0) -> 0 | BY28: =IFERROR((BW28-BH28)/BH28,0) -> 0 | BZ28: =AMAZON!P187 -> 0 | CA28: =IFERROR(BZ28/AMAZON!P50,0) -> 0 | CB28: =TEMU!P87 -> 0 | CC28: =IFERROR(CB28/TEMU!P25,0) -> 0 | CD28: =SHEIN!P67 -> 0 | CE28: =IFERROR(CD28/SHEIN!P20,0) -> 0 | CF28: =TK!P87 -> 0 | CG28: =IFERROR(CF28/TK!P25,0) -> 0 | CL28: =BZ28+CB28+CD28+CF28+CH28+CJ28 -> 0 | CM28: =IFERROR(CL28/(BZ11+CB11+CD11+CF11),0) -> 0 | CN28: =IFERROR((CL28-BW28)/BW28,0) -> 0 | CO28: =AMAZON!R187 -> 0 | CP28: =IFERROR(CO28/AMAZON!R50,0) -> 0 | CQ28: =TEMU!R87 -> 0 | CR28: =IFERROR(CQ28/TEMU!R25,0) -> 0 | CS28: =SHEIN!R67 -> 0 | CT28: =IFERROR(CS28/SHEIN!R20,0) -> 0 | CU28: =TK!R87 -> 0 | CV28: =IFERROR(CU28/TK!R25,0) -> 0 | DA28: =CO28+CQ28+CS28+CU28+CW28+CY28 -> 0 | DB28: =IFERROR(DA28/(CO11+CQ11+CS11+CU11),0) -> 0 | DC28: =IFERROR((DA28-CL28)/CL28,0) -> 0 | DD28: =AMAZON!T187 -> 0 | DE28: =IFERROR(DD28/AMAZON!T50,0) -> 0 | DF28: =TEMU!T87 -> 0 | DG28: =IFERROR(DF28/TEMU!T25,0) -> 0 | DH28: =SHEIN!T67 -> 0 | DI28: =IFERROR(DH28/SHEIN!T20,0) -> 0 | DJ28: =TK!T87 -> 0 | DK28: =IFERROR(DJ28/TK!T25,0) -> 0 | DP28: =DD28+DF28+DH28+DJ28+DL28+DN28 -> 0 | DQ28: =IFERROR(DP28/(DD11+DF11+DH11+DJ11),0) -> 0 | DR28: =IFERROR((DP28-DA28)/DA28,0) -> 0 | DS28: =AMAZON!V187 -> 0 | DT28: =IFERROR(DS28/AMAZON!V50,0) -> 0 | DU28: =TEMU!V87 -> 0 | DV28: =IFERROR(DU28/TEMU!V25,0) -> 0 | DW28: =SHEIN!V67 -> 0 | DX28: =IFERROR(DW28/SHEIN!V20,0) -> 0 | DY28: =TK!V87 -> 0 | DZ28: =IFERROR(DY28/TK!V25,0) -> 0 | EE28: =DS28+DU28+DW28+DY28+EA28+EC28 -> 0 | EF28: =IFERROR(EE28/(DS11+DU11+DW11+DY11),0) -> 0 | EG28: =IFERROR((EE28-DP28)/DP28,0) -> 0 | EH28: =AMAZON!X187 -> 0 | EI28: =IFERROR(EH28/AMAZON!X50,0) -> 0 | EJ28: =TEMU!X87 -> 0 | EK28: =IFERROR(EJ28/TEMU!X25,0) -> 0 | EL28: =SHEIN!X67 -> 0 | EM28: =IFERROR(EL28/SHEIN!X20,0) -> 0 | EN28: =TK!X87 -> 0 | EO28: =IFERROR(EN28/TK!X25,0) -> 0 | ET28: =EH28+EJ28+EL28+EN28+EP28+ER28 -> 0 | EU28: =IFERROR(ET28/(EH11+EJ11+EL11+EN11),0) -> 0 | EV28: =IFERROR((ET28-EE28)/EE28,0) -> 0 | EW28: =AMAZON!Z187 -> 0 | EX28: =IFERROR(EW28/AMAZON!Z50,0) -> 0 | EY28: =TEMU!Z87 -> 0 | EZ28: =IFERROR(EY28/TEMU!Z25,0) -> 0 | FA28: =SHEIN!Z67 -> 0 | FB28: =IFERROR(FA28/SHEIN!Z20,0) -> 0 | FC28: =TK!Z87 -> 0 | FD28: =IFERROR(FC28/TK!Z25,0) -> 0 | FI28: =EW28+EY28+FA28+FC28+FE28+FG28 -> 0 | FJ28: =IFERROR(FI28/(EW11+EY11+FA11+FC11),0) -> 0 | FK28: =IFERROR((FI28-ET28)/ET28,0) -> 0 | FL28: =AMAZON!AB187 -> 0 | FM28: =IFERROR(FL28/AMAZON!AB50,0) -> 0 | FN28: =TEMU!AB87 -> 0 | FO28: =IFERROR(FN28/TEMU!AB25,0) -> 0 | FP28: =SHEIN!AB67 -> 0 | FQ28: =IFERROR(FP28/SHEIN!AB20,0) -> 0 | FR28: =TK!AB87 -> 0 | FS28: =IFERROR(FR28/TK!AB25,0) -> 0 | FX28: =FL28+FN28+FP28+FR28+FT28+FV28 -> 0 | FY28: =IFERROR(FX28/(FL11+FN11+FP11+FR11),0) -> 0 | FZ28: =IFERROR((FX28-FI28)/FI28,0) -> 0 | GA28: =AMAZON!AD187 -> 0 | GB28: =IFERROR(GA28/AMAZON!AD50,0) -> 0 | GC28: =TEMU!AD87 -> 0 | GD28: =IFERROR(GC28/TEMU!AD25,0) -> 0 | GE28: =SHEIN!AD67 -> 0 | GF28: =IFERROR(GE28/SHEIN!AD20,0) -> 0 | GG28: =TK!AD87 -> 0 | GH28: =IFERROR(GG28/TK!AD25,0) -> 0 | GM28: =GA28+GC28+GE28+GG28+GI28+GK28 -> 0 | GN28: =IFERROR(GM28/(GA11+GC11+GE11+GG11),0) -> 0 | GO28: =IFERROR((GM28-FX28)/FX28,0) -> 0
A29: 成本 | B29: 头程成本 | C29: 元 | D29: =AMAZON!F196 -> 0 | E29: =IFERROR(D29/AMAZON!F50,0) -> 0 | F29: =TEMU!F91 -> 0 | G29: =IFERROR(F29/TEMU!F25,0) -> 0 | H29: =SHEIN!F70 -> 0 | I29: =IFERROR(H29/SHEIN!F20,0) -> 0 | J29: =TK!F91 -> 0 | K29: =IFERROR(J29/TK!F25,0) -> 0 | P29: =D29+F29+H29+J29+L29+N29 -> 0 | Q29: =IFERROR(P29/(D11+F11+H11+J11),0) -> 0 | R29: =AMAZON!H196 -> 0 | S29: =IFERROR(R29/AMAZON!H50,0) -> 0 | T29: =TEMU!H91 -> 0 | U29: =IFERROR(T29/TEMU!H25,0) -> 0 | V29: =SHEIN!H70 -> 0 | W29: =IFERROR(V29/SHEIN!H20,0) -> 0 | X29: =TK!H91 -> 0 | Y29: =IFERROR(X29/TK!H25,0) -> 0 | AD29: =R29+T29+V29+X29+Z29+AB29 -> 0 | AE29: =IFERROR(AD29/(R11+T11+V11+X11),0) -> 0 | AG29: =AMAZON!J196 -> 0 | AH29: =IFERROR(AG29/AMAZON!J50,0) -> 0 | AI29: =TEMU!J91 -> 0 | AJ29: =IFERROR(AI29/TEMU!J25,0) -> 0 | AK29: =SHEIN!J70 -> 0 | AL29: =IFERROR(AK29/SHEIN!J20,0) -> 0 | AM29: =TK!J91 -> 0 | AN29: =IFERROR(AM29/TK!J25,0) -> 0 | AS29: =AG29+AI29+AK29+AM29+AO29+AQ29 -> 0 | AT29: =IFERROR(AS29/(AG11+AI11+AK11+AM11),0) -> 0 | AU29: =IFERROR((AS29-AD29)/AD29,0) -> 0 | AV29: =AMAZON!L196 -> 0 | AW29: =IFERROR(AV29/AMAZON!L50,0) -> 0 | AX29: =TEMU!L91 -> 0 | AY29: =IFERROR(AX29/TEMU!L25,0) -> 0 | AZ29: =SHEIN!L70 -> 0 | BA29: =IFERROR(AZ29/SHEIN!L20,0) -> 0 | BB29: =TK!L91 -> 0 | BC29: =IFERROR(BB29/TK!L25,0) -> 0 | BH29: =AV29+AX29+AZ29+BB29+BD29+BF29 -> 0 | BI29: =IFERROR(BH29/(AV11+AX11+AZ11+BB11),0) -> 0 | BJ29: =IFERROR((BH29-AS29)/AS29,0) -> 0 | BK29: =AMAZON!N196 -> 0 | BL29: =IFERROR(BK29/AMAZON!N50,0) -> 0 | BM29: =TEMU!N91 -> 0 | BN29: =IFERROR(BM29/TEMU!N25,0) -> 0 | BO29: =SHEIN!N70 -> 0 | BP29: =IFERROR(BO29/SHEIN!N20,0) -> 0 | BQ29: =TK!N91 -> 0 | BR29: =IFERROR(BQ29/TK!N25,0) -> 0 | BW29: =BK29+BM29+BO29+BQ29+BS29+BU29 -> 0 | BX29: =IFERROR(BW29/(BK11+BM11+BO11+BQ11),0) -> 0 | BY29: =IFERROR((BW29-BH29)/BH29,0) -> 0 | BZ29: =AMAZON!P196 -> 0 | CA29: =IFERROR(BZ29/AMAZON!P50,0) -> 0 | CB29: =TEMU!P91 -> 0 | CC29: =IFERROR(CB29/TEMU!P25,0) -> 0 | CD29: =SHEIN!P70 -> 0 | CE29: =IFERROR(CD29/SHEIN!P20,0) -> 0 | CF29: =TK!P91 -> 0 | CG29: =IFERROR(CF29/TK!P25,0) -> 0 | CL29: =BZ29+CB29+CD29+CF29+CH29+CJ29 -> 0 | CM29: =IFERROR(CL29/(BZ11+CB11+CD11+CF11),0) -> 0 | CN29: =IFERROR((CL29-BW29)/BW29,0) -> 0 | CO29: =AMAZON!R196 -> 0 | CP29: =IFERROR(CO29/AMAZON!R50,0) -> 0 | CQ29: =TEMU!R91 -> 0 | CR29: =IFERROR(CQ29/TEMU!R25,0) -> 0 | CS29: =SHEIN!R70 -> 0 | CT29: =IFERROR(CS29/SHEIN!R20,0) -> 0 | CU29: =TK!R91 -> 0 | CV29: =IFERROR(CU29/TK!R25,0) -> 0 | DA29: =CO29+CQ29+CS29+CU29+CW29+CY29 -> 0 | DB29: =IFERROR(DA29/(CO11+CQ11+CS11+CU11),0) -> 0 | DC29: =IFERROR((DA29-CL29)/CL29,0) -> 0 | DD29: =AMAZON!T196 -> 0 | DE29: =IFERROR(DD29/AMAZON!T50,0) -> 0 | DF29: =TEMU!T91 -> 0 | DG29: =IFERROR(DF29/TEMU!T25,0) -> 0 | DH29: =SHEIN!T70 -> 0 | DI29: =IFERROR(DH29/SHEIN!T20,0) -> 0 | DJ29: =TK!T91 -> 0 | DK29: =IFERROR(DJ29/TK!T25,0) -> 0 | DP29: =DD29+DF29+DH29+DJ29+DL29+DN29 -> 0 | DQ29: =IFERROR(DP29/(DD11+DF11+DH11+DJ11),0) -> 0 | DR29: =IFERROR((DP29-DA29)/DA29,0) -> 0 | DS29: =AMAZON!V196 -> 0 | DT29: =IFERROR(DS29/AMAZON!V50,0) -> 0 | DU29: =TEMU!V91 -> 0 | DV29: =IFERROR(DU29/TEMU!V25,0) -> 0 | DW29: =SHEIN!V70 -> 0 | DX29: =IFERROR(DW29/SHEIN!V20,0) -> 0 | DY29: =TK!V91 -> 0 | DZ29: =IFERROR(DY29/TK!V25,0) -> 0 | EE29: =DS29+DU29+DW29+DY29+EA29+EC29 -> 0 | EF29: =IFERROR(EE29/(DS11+DU11+DW11+DY11),0) -> 0 | EG29: =IFERROR((EE29-DP29)/DP29,0) -> 0 | EH29: =AMAZON!X196 -> 0 | EI29: =IFERROR(EH29/AMAZON!X50,0) -> 0 | EJ29: =TEMU!X91 -> 0 | EK29: =IFERROR(EJ29/TEMU!X25,0) -> 0 | EL29: =SHEIN!X70 -> 0 | EM29: =IFERROR(EL29/SHEIN!X20,0) -> 0 | EN29: =TK!X91 -> 0 | EO29: =IFERROR(EN29/TK!X25,0) -> 0 | ET29: =EH29+EJ29+EL29+EN29+EP29+ER29 -> 0 | EU29: =IFERROR(ET29/(EH11+EJ11+EL11+EN11),0) -> 0 | EV29: =IFERROR((ET29-EE29)/EE29,0) -> 0 | EW29: =AMAZON!Z196 -> 0 | EX29: =IFERROR(EW29/AMAZON!Z50,0) -> 0 | EY29: =TEMU!Z91 -> 0 | EZ29: =IFERROR(EY29/TEMU!Z25,0) -> 0 | FA29: =SHEIN!Z70 -> 0 | FB29: =IFERROR(FA29/SHEIN!Z20,0) -> 0 | FC29: =TK!Z91 -> 0 | FD29: =IFERROR(FC29/TK!Z25,0) -> 0 | FI29: =EW29+EY29+FA29+FC29+FE29+FG29 -> 0 | FJ29: =IFERROR(FI29/(EW11+EY11+FA11+FC11),0) -> 0 | FK29: =IFERROR((FI29-ET29)/ET29,0) -> 0 | FL29: =AMAZON!AB196 -> 0 | FM29: =IFERROR(FL29/AMAZON!AB50,0) -> 0 | FN29: =TEMU!AB91 -> 0 | FO29: =IFERROR(FN29/TEMU!AB25,0) -> 0 | FP29: =SHEIN!AB70 -> 0 | FQ29: =IFERROR(FP29/SHEIN!AB20,0) -> 0 | FR29: =TK!AB91 -> 0 | FS29: =IFERROR(FR29/TK!AB25,0) -> 0 | FX29: =FL29+FN29+FP29+FR29+FT29+FV29 -> 0 | FY29: =IFERROR(FX29/(FL11+FN11+FP11+FR11),0) -> 0 | FZ29: =IFERROR((FX29-FI29)/FI29,0) -> 0 | GA29: =AMAZON!AD196 -> 0 | GB29: =IFERROR(GA29/AMAZON!AD50,0) -> 0 | GC29: =TEMU!AD91 -> 0 | GD29: =IFERROR(GC29/TEMU!AD25,0) -> 0 | GE29: =SHEIN!AD70 -> 0 | GF29: =IFERROR(GE29/SHEIN!AD20,0) -> 0 | GG29: =TK!AD91 -> 0 | GH29: =IFERROR(GG29/TK!AD25,0) -> 0 | GM29: =GA29+GC29+GE29+GG29+GI29+GK29 -> 0 | GN29: =IFERROR(GM29/(GA11+GC11+GE11+GG11),0) -> 0 | GO29: =IFERROR((GM29-FX29)/FX29,0) -> 0
A30: 其他项目 | C30: 元 | D30: =AMAZON!F205 -> 0 | E30: =IFERROR(D30/AMAZON!F50,0) -> 0 | F30: =TEMU!F95 -> 0 | G30: =IFERROR(F30/TEMU!F25,0) -> 0 | H30: =SHEIN!F73 -> 0 | I30: =IFERROR(H30/SHEIN!F20,0) -> 0 | J30: =TK!F95 -> 0 | K30: =IFERROR(J30/TK!F25,0) -> 0 | P30: =D30+F30+H30+J30+L30+N30 -> 0 | Q30: =IFERROR(P30/(D11+F11+H11+J11),0) -> 0 | R30: =AMAZON!H205 -> 0 | S30: =IFERROR(R30/AMAZON!H50,0) -> 0 | T30: =TEMU!H95 -> 0 | U30: =IFERROR(T30/TEMU!H25,0) -> 0 | V30: =SHEIN!H73 -> 0 | W30: =IFERROR(V30/SHEIN!H20,0) -> 0 | X30: =TK!H95 -> 0 | Y30: =IFERROR(X30/TK!H25,0) -> 0 | AD30: =R30+T30+V30+X30+Z30+AB30 -> 0 | AE30: =IFERROR(AD30/(R11+T11+V11+X11),0) -> 0 | AG30: =AMAZON!J205 -> 0 | AH30: =IFERROR(AG30/AMAZON!J50,0) -> 0 | AI30: =TEMU!J95 -> 0 | AJ30: =IFERROR(AI30/TEMU!J25,0) -> 0 | AK30: =SHEIN!J73 -> 0 | AL30: =IFERROR(AK30/SHEIN!J20,0) -> 0 | AM30: =TK!J95 -> 0 | AN30: =IFERROR(AM30/TK!J25,0) -> 0 | AS30: =AG30+AI30+AK30+AM30+AO30+AQ30 -> 0 | AT30: =IFERROR(AS30/(AG11+AI11+AK11+AM11),0) -> 0 | AU30: =IFERROR((AS30-AD30)/AD30,0) -> 0 | AV30: =AMAZON!L205 -> 0 | AW30: =IFERROR(AV30/AMAZON!L50,0) -> 0 | AX30: =TEMU!L95 -> 0 | AY30: =IFERROR(AX30/TEMU!L25,0) -> 0 | AZ30: =SHEIN!L73 -> 0 | BA30: =IFERROR(AZ30/SHEIN!L20,0) -> 0 | BB30: =TK!L95 -> 0 | BC30: =IFERROR(BB30/TK!L25,0) -> 0 | BH30: =AV30+AX30+AZ30+BB30+BD30+BF30 -> 0 | BI30: =IFERROR(BH30/(AV11+AX11+AZ11+BB11),0) -> 0 | BJ30: =IFERROR((BH30-AS30)/AS30,0) -> 0 | BK30: =AMAZON!N205 -> 0 | BL30: =IFERROR(BK30/AMAZON!N50,0) -> 0 | BM30: =TEMU!N95 -> 0 | BN30: =IFERROR(BM30/TEMU!N25,0) -> 0 | BO30: =SHEIN!N73 -> 0 | BP30: =IFERROR(BO30/SHEIN!N20,0) -> 0 | BQ30: =TK!N95 -> 0 | BR30: =IFERROR(BQ30/TK!N25,0) -> 0 | BW30: =BK30+BM30+BO30+BQ30+BS30+BU30 -> 0 | BX30: =IFERROR(BW30/(BK11+BM11+BO11+BQ11),0) -> 0 | BY30: =IFERROR((BW30-BH30)/BH30,0) -> 0 | BZ30: =AMAZON!P205 -> 0 | CA30: =IFERROR(BZ30/AMAZON!P50,0) -> 0 | CB30: =TEMU!P95 -> 0 | CC30: =IFERROR(CB30/TEMU!P25,0) -> 0 | CD30: =SHEIN!P73 -> 0 | CE30: =IFERROR(CD30/SHEIN!P20,0) -> 0 | CF30: =TK!P95 -> 0 | CG30: =IFERROR(CF30/TK!P25,0) -> 0 | CL30: =BZ30+CB30+CD30+CF30+CH30+CJ30 -> 0 | CM30: =IFERROR(CL30/(BZ11+CB11+CD11+CF11),0) -> 0 | CN30: =IFERROR((CL30-BW30)/BW30,0) -> 0 | CO30: =AMAZON!R205 -> 0 | CP30: =IFERROR(CO30/AMAZON!R50,0) -> 0 | CQ30: =TEMU!R95 -> 0 | CR30: =IFERROR(CQ30/TEMU!R25,0) -> 0 | CS30: =SHEIN!R73 -> 0 | CT30: =IFERROR(CS30/SHEIN!R20,0) -> 0 | CU30: =TK!R95 -> 0 | CV30: =IFERROR(CU30/TK!R25,0) -> 0 | DA30: =CO30+CQ30+CS30+CU30+CW30+CY30 -> 0 | DB30: =IFERROR(DA30/(CO11+CQ11+CS11+CU11),0) -> 0 | DC30: =IFERROR((DA30-CL30)/CL30,0) -> 0 | DD30: =AMAZON!T205 -> 0 | DE30: =IFERROR(DD30/AMAZON!T50,0) -> 0 | DF30: =TEMU!T95 -> 0 | DG30: =IFERROR(DF30/TEMU!T25,0) -> 0 | DH30: =SHEIN!T73 -> 0 | DI30: =IFERROR(DH30/SHEIN!T20,0) -> 0 | DJ30: =TK!T95 -> 0 | DK30: =IFERROR(DJ30/TK!T25,0) -> 0 | DP30: =DD30+DF30+DH30+DJ30+DL30+DN30 -> 0 | DQ30: =IFERROR(DP30/(DD11+DF11+DH11+DJ11),0) -> 0 | DR30: =IFERROR((DP30-DA30)/DA30,0) -> 0 | DS30: =AMAZON!V205 -> 0 | DT30: =IFERROR(DS30/AMAZON!V50,0) -> 0 | DU30: =TEMU!V95 -> 0 | DV30: =IFERROR(DU30/TEMU!V25,0) -> 0 | DW30: =SHEIN!V73 -> 0 | DX30: =IFERROR(DW30/SHEIN!V20,0) -> 0 | DY30: =TK!V95 -> 0 | DZ30: =IFERROR(DY30/TK!V25,0) -> 0 | EE30: =DS30+DU30+DW30+DY30+EA30+EC30 -> 0 | EF30: =IFERROR(EE30/(DS11+DU11+DW11+DY11),0) -> 0 | EG30: =IFERROR((EE30-DP30)/DP30,0) -> 0 | EH30: =AMAZON!X205 -> 0 | EI30: =IFERROR(EH30/AMAZON!X50,0) -> 0 | EJ30: =TEMU!X95 -> 0 | EK30: =IFERROR(EJ30/TEMU!X25,0) -> 0 | EL30: =SHEIN!X73 -> 0 | EM30: =IFERROR(EL30/SHEIN!X20,0) -> 0 | EN30: =TK!X95 -> 0 | EO30: =IFERROR(EN30/TK!X25,0) -> 0 | ET30: =EH30+EJ30+EL30+EN30+EP30+ER30 -> 0 | EU30: =IFERROR(ET30/(EH11+EJ11+EL11+EN11),0) -> 0 | EV30: =IFERROR((ET30-EE30)/EE30,0) -> 0 | EW30: =AMAZON!Z205 -> 0 | EX30: =IFERROR(EW30/AMAZON!Z50,0) -> 0 | EY30: =TEMU!Z95 -> 0 | EZ30: =IFERROR(EY30/TEMU!Z25,0) -> 0 | FA30: =SHEIN!Z73 -> 0 | FB30: =IFERROR(FA30/SHEIN!Z20,0) -> 0 | FC30: =TK!Z95 -> 0 | FD30: =IFERROR(FC30/TK!Z25,0) -> 0 | FI30: =EW30+EY30+FA30+FC30+FE30+FG30 -> 0 | FJ30: =IFERROR(FI30/(EW11+EY11+FA11+FC11),0) -> 0 | FK30: =IFERROR((FI30-ET30)/ET30,0) -> 0 | FL30: =AMAZON!AB205 -> 0 | FM30: =IFERROR(FL30/AMAZON!AB50,0) -> 0 | FN30: =TEMU!AB95 -> 0 | FO30: =IFERROR(FN30/TEMU!AB25,0) -> 0 | FP30: =SHEIN!AB73 -> 0 | FQ30: =IFERROR(FP30/SHEIN!AB20,0) -> 0 | FR30: =TK!AB95 -> 0 | FS30: =IFERROR(FR30/TK!AB25,0) -> 0 | FX30: =FL30+FN30+FP30+FR30+FT30+FV30 -> 0 | FY30: =IFERROR(FX30/(FL11+FN11+FP11+FR11),0) -> 0 | FZ30: =IFERROR((FX30-FI30)/FI30,0) -> 0 | GA30: =AMAZON!AD205 -> 0 | GB30: =IFERROR(GA30/AMAZON!AD50,0) -> 0 | GC30: =TEMU!AD95 -> 0 | GD30: =IFERROR(GC30/TEMU!AD25,0) -> 0 | GE30: =SHEIN!AD73 -> 0 | GF30: =IFERROR(GE30/SHEIN!AD20,0) -> 0 | GG30: =TK!AD95 -> 0 | GH30: =IFERROR(GG30/TK!AD25,0) -> 0 | GM30: =GA30+GC30+GE30+GG30+GI30+GK30 -> 0 | GN30: =IFERROR(GM30/(GA11+GC11+GE11+GG11),0) -> 0 | GO30: =IFERROR((GM30-FX30)/FX30,0) -> 0
A31: 其他项目 | B31: 其他收入 | C31: 元 | D31: =AMAZON!F214 -> 0 | E31: =IFERROR(D31/AMAZON!F50,0) -> 0 | F31: =TEMU!F99 -> 0 | G31: =IFERROR(F31/TEMU!F25,0) -> 0 | H31: =SHEIN!F76 -> 0 | I31: =IFERROR(H31/SHEIN!F20,0) -> 0 | J31: =TK!F99 -> 0 | K31: =IFERROR(J31/TK!F25,0) -> 0 | P31: =D31+F31+H31+J31+L31+N31 -> 0 | Q31: =IFERROR(P31/(D11+F11+H11+J11),0) -> 0 | R31: =AMAZON!H214 -> 0 | S31: =IFERROR(R31/AMAZON!H50,0) -> 0 | T31: =TEMU!H99 -> 0 | U31: =IFERROR(T31/TEMU!H25,0) -> 0 | V31: =SHEIN!H76 -> 0 | W31: =IFERROR(V31/SHEIN!H20,0) -> 0 | X31: =TK!H99 -> 0 | Y31: =IFERROR(X31/TK!H25,0) -> 0 | AD31: =R31+T31+V31+X31+Z31+AB31 -> 0 | AE31: =IFERROR(AD31/(R11+T11+V11+X11),0) -> 0 | AG31: =AMAZON!J214 -> 0 | AH31: =IFERROR(AG31/AMAZON!J50,0) -> 0 | AI31: =TEMU!J99 -> 0 | AJ31: =IFERROR(AI31/TEMU!J25,0) -> 0 | AK31: =SHEIN!J76 -> 0 | AL31: =IFERROR(AK31/SHEIN!J20,0) -> 0 | AM31: =TK!J99 -> 0 | AN31: =IFERROR(AM31/TK!J25,0) -> 0 | AS31: =AG31+AI31+AK31+AM31+AO31+AQ31 -> 0 | AT31: =IFERROR(AS31/(AG11+AI11+AK11+AM11),0) -> 0 | AU31: =IFERROR((AS31-AD31)/AD31,0) -> 0 | AV31: =AMAZON!L214 -> 0 | AW31: =IFERROR(AV31/AMAZON!L50,0) -> 0 | AX31: =TEMU!L99 -> 0 | AY31: =IFERROR(AX31/TEMU!L25,0) -> 0 | AZ31: =SHEIN!L76 -> 0 | BA31: =IFERROR(AZ31/SHEIN!L20,0) -> 0 | BB31: =TK!L99 -> 0 | BC31: =IFERROR(BB31/TK!L25,0) -> 0 | BH31: =AV31+AX31+AZ31+BB31+BD31+BF31 -> 0 | BI31: =IFERROR(BH31/(AV11+AX11+AZ11+BB11),0) -> 0 | BJ31: =IFERROR((BH31-AS31)/AS31,0) -> 0 | BK31: =AMAZON!N214 -> 0 | BL31: =IFERROR(BK31/AMAZON!N50,0) -> 0 | BM31: =TEMU!N99 -> 0 | BN31: =IFERROR(BM31/TEMU!N25,0) -> 0 | BO31: =SHEIN!N76 -> 0 | BP31: =IFERROR(BO31/SHEIN!N20,0) -> 0 | BQ31: =TK!N99 -> 0 | BR31: =IFERROR(BQ31/TK!N25,0) -> 0 | BW31: =BK31+BM31+BO31+BQ31+BS31+BU31 -> 0 | BX31: =IFERROR(BW31/(BK11+BM11+BO11+BQ11),0) -> 0 | BY31: =IFERROR((BW31-BH31)/BH31,0) -> 0 | BZ31: =AMAZON!P214 -> 0 | CA31: =IFERROR(BZ31/AMAZON!P50,0) -> 0 | CB31: =TEMU!P99 -> 0 | CC31: =IFERROR(CB31/TEMU!P25,0) -> 0 | CD31: =SHEIN!P76 -> 0 | CE31: =IFERROR(CD31/SHEIN!P20,0) -> 0 | CF31: =TK!P99 -> 0 | CG31: =IFERROR(CF31/TK!P25,0) -> 0 | CL31: =BZ31+CB31+CD31+CF31+CH31+CJ31 -> 0 | CM31: =IFERROR(CL31/(BZ11+CB11+CD11+CF11),0) -> 0 | CN31: =IFERROR((CL31-BW31)/BW31,0) -> 0 | CO31: =AMAZON!R214 -> 0 | CP31: =IFERROR(CO31/AMAZON!R50,0) -> 0 | CQ31: =TEMU!R99 -> 0 | CR31: =IFERROR(CQ31/TEMU!R25,0) -> 0 | CS31: =SHEIN!R76 -> 0 | CT31: =IFERROR(CS31/SHEIN!R20,0) -> 0 | CU31: =TK!R99 -> 0 | CV31: =IFERROR(CU31/TK!R25,0) -> 0 | DA31: =CO31+CQ31+CS31+CU31+CW31+CY31 -> 0 | DB31: =IFERROR(DA31/(CO11+CQ11+CS11+CU11),0) -> 0 | DC31: =IFERROR((DA31-CL31)/CL31,0) -> 0 | DD31: =AMAZON!T214 -> 0 | DE31: =IFERROR(DD31/AMAZON!T50,0) -> 0 | DF31: =TEMU!T99 -> 0 | DG31: =IFERROR(DF31/TEMU!T25,0) -> 0 | DH31: =SHEIN!T76 -> 0 | DI31: =IFERROR(DH31/SHEIN!T20,0) -> 0 | DJ31: =TK!T99 -> 0 | DK31: =IFERROR(DJ31/TK!T25,0) -> 0 | DP31: =DD31+DF31+DH31+DJ31+DL31+DN31 -> 0 | DQ31: =IFERROR(DP31/(DD11+DF11+DH11+DJ11),0) -> 0 | DR31: =IFERROR((DP31-DA31)/DA31,0) -> 0 | DS31: =AMAZON!V214 -> 0 | DT31: =IFERROR(DS31/AMAZON!V50,0) -> 0 | DU31: =TEMU!V99 -> 0 | DV31: =IFERROR(DU31/TEMU!V25,0) -> 0 | DW31: =SHEIN!V76 -> 0 | DX31: =IFERROR(DW31/SHEIN!V20,0) -> 0 | DY31: =TK!V99 -> 0 | DZ31: =IFERROR(DY31/TK!V25,0) -> 0 | EE31: =DS31+DU31+DW31+DY31+EA31+EC31 -> 0 | EF31: =IFERROR(EE31/(DS11+DU11+DW11+DY11),0) -> 0 | EG31: =IFERROR((EE31-DP31)/DP31,0) -> 0 | EH31: =AMAZON!X214 -> 0 | EI31: =IFERROR(EH31/AMAZON!X50,0) -> 0 | EJ31: =TEMU!X99 -> 0 | EK31: =IFERROR(EJ31/TEMU!X25,0) -> 0 | EL31: =SHEIN!X76 -> 0 | EM31: =IFERROR(EL31/SHEIN!X20,0) -> 0 | EN31: =TK!X99 -> 0 | EO31: =IFERROR(EN31/TK!X25,0) -> 0 | ET31: =EH31+EJ31+EL31+EN31+EP31+ER31 -> 0 | EU31: =IFERROR(ET31/(EH11+EJ11+EL11+EN11),0) -> 0 | EV31: =IFERROR((ET31-EE31)/EE31,0) -> 0 | EW31: =AMAZON!Z214 -> 0 | EX31: =IFERROR(EW31/AMAZON!Z50,0) -> 0 | EY31: =TEMU!Z99 -> 0 | EZ31: =IFERROR(EY31/TEMU!Z25,0) -> 0 | FA31: =SHEIN!Z76 -> 0 | FB31: =IFERROR(FA31/SHEIN!Z20,0) -> 0 | FC31: =TK!Z99 -> 0 | FD31: =IFERROR(FC31/TK!Z25,0) -> 0 | FI31: =EW31+EY31+FA31+FC31+FE31+FG31 -> 0 | FJ31: =IFERROR(FI31/(EW11+EY11+FA11+FC11),0) -> 0 | FK31: =IFERROR((FI31-ET31)/ET31,0) -> 0 | FL31: =AMAZON!AB214 -> 0 | FM31: =IFERROR(FL31/AMAZON!AB50,0) -> 0 | FN31: =TEMU!AB99 -> 0 | FO31: =IFERROR(FN31/TEMU!AB25,0) -> 0 | FP31: =SHEIN!AB76 -> 0 | FQ31: =IFERROR(FP31/SHEIN!AB20,0) -> 0 | FR31: =TK!AB99 -> 0 | FS31: =IFERROR(FR31/TK!AB25,0) -> 0 | FX31: =FL31+FN31+FP31+FR31+FT31+FV31 -> 0 | FY31: =IFERROR(FX31/(FL11+FN11+FP11+FR11),0) -> 0 | FZ31: =IFERROR((FX31-FI31)/FI31,0) -> 0 | GA31: =AMAZON!AD214 -> 0 | GB31: =IFERROR(GA31/AMAZON!AD50,0) -> 0 | GC31: =TEMU!AD99 -> 0 | GD31: =IFERROR(GC31/TEMU!AD25,0) -> 0 | GE31: =SHEIN!AD76 -> 0 | GF31: =IFERROR(GE31/SHEIN!AD20,0) -> 0 | GG31: =TK!AD99 -> 0 | GH31: =IFERROR(GG31/TK!AD25,0) -> 0 | GM31: =GA31+GC31+GE31+GG31+GI31+GK31 -> 0 | GN31: =IFERROR(GM31/(GA11+GC11+GE11+GG11),0) -> 0 | GO31: =IFERROR((GM31-FX31)/FX31,0) -> 0
A32: 其他项目 | B32: 其他支出 | C32: 元 | D32: =AMAZON!F223 -> 0 | E32: =IFERROR(D32/AMAZON!F50,0) -> 0 | F32: =TEMU!F103 -> 0 | G32: =IFERROR(F32/TEMU!F25,0) -> 0 | H32: =SHEIN!F79 -> 0 | I32: =IFERROR(H32/SHEIN!F20,0) -> 0 | J32: =TK!F103 -> 0 | K32: =IFERROR(J32/TK!F25,0) -> 0 | P32: =D32+F32+H32+J32+L32+N32 -> 0 | Q32: =IFERROR(P32/(D11+F11+H11+J11),0) -> 0 | R32: =AMAZON!H223 -> 0 | S32: =IFERROR(R32/AMAZON!H50,0) -> 0 | T32: =TEMU!H103 -> 0 | U32: =IFERROR(T32/TEMU!H25,0) -> 0 | V32: =SHEIN!H79 -> 0 | W32: =IFERROR(V32/SHEIN!H20,0) -> 0 | X32: =TK!H103 -> 0 | Y32: =IFERROR(X32/TK!H25,0) -> 0 | AD32: =R32+T32+V32+X32+Z32+AB32 -> 0 | AE32: =IFERROR(AD32/(R11+T11+V11+X11),0) -> 0 | AG32: =AMAZON!J223 -> 0 | AH32: =IFERROR(AG32/AMAZON!J50,0) -> 0 | AI32: =TEMU!J103 -> 0 | AJ32: =IFERROR(AI32/TEMU!J25,0) -> 0 | AK32: =SHEIN!J79 -> 0 | AL32: =IFERROR(AK32/SHEIN!J20,0) -> 0 | AM32: =TK!J103 -> 0 | AN32: =IFERROR(AM32/TK!J25,0) -> 0 | AS32: =AG32+AI32+AK32+AM32+AO32+AQ32 -> 0 | AT32: =IFERROR(AS32/(AG11+AI11+AK11+AM11),0) -> 0 | AU32: =IFERROR((AS32-AD32)/AD32,0) -> 0 | AV32: =AMAZON!L223 -> 0 | AW32: =IFERROR(AV32/AMAZON!L50,0) -> 0 | AX32: =TEMU!L103 -> 0 | AY32: =IFERROR(AX32/TEMU!L25,0) -> 0 | AZ32: =SHEIN!L79 -> 0 | BA32: =IFERROR(AZ32/SHEIN!L20,0) -> 0 | BB32: =TK!L103 -> 0 | BC32: =IFERROR(BB32/TK!L25,0) -> 0 | BH32: =AV32+AX32+AZ32+BB32+BD32+BF32 -> 0 | BI32: =IFERROR(BH32/(AV11+AX11+AZ11+BB11),0) -> 0 | BJ32: =IFERROR((BH32-AS32)/AS32,0) -> 0 | BK32: =AMAZON!N223 -> 0 | BL32: =IFERROR(BK32/AMAZON!N50,0) -> 0 | BM32: =TEMU!N103 -> 0 | BN32: =IFERROR(BM32/TEMU!N25,0) -> 0 | BO32: =SHEIN!N79 -> 0 | BP32: =IFERROR(BO32/SHEIN!N20,0) -> 0 | BQ32: =TK!N103 -> 0 | BR32: =IFERROR(BQ32/TK!N25,0) -> 0 | BW32: =BK32+BM32+BO32+BQ32+BS32+BU32 -> 0 | BX32: =IFERROR(BW32/(BK11+BM11+BO11+BQ11),0) -> 0 | BY32: =IFERROR((BW32-BH32)/BH32,0) -> 0 | BZ32: =AMAZON!P223 -> 0 | CA32: =IFERROR(BZ32/AMAZON!P50,0) -> 0 | CB32: =TEMU!P103 -> 0 | CC32: =IFERROR(CB32/TEMU!P25,0) -> 0 | CD32: =SHEIN!P79 -> 0 | CE32: =IFERROR(CD32/SHEIN!P20,0) -> 0 | CF32: =TK!P103 -> 0 | CG32: =IFERROR(CF32/TK!P25,0) -> 0 | CL32: =BZ32+CB32+CD32+CF32+CH32+CJ32 -> 0 | CM32: =IFERROR(CL32/(BZ11+CB11+CD11+CF11),0) -> 0 | CN32: =IFERROR((CL32-BW32)/BW32,0) -> 0 | CO32: =AMAZON!R223 -> 0 | CP32: =IFERROR(CO32/AMAZON!R50,0) -> 0 | CQ32: =TEMU!R103 -> 0 | CR32: =IFERROR(CQ32/TEMU!R25,0) -> 0 | CS32: =SHEIN!R79 -> 0 | CT32: =IFERROR(CS32/SHEIN!R20,0) -> 0 | CU32: =TK!R103 -> 0 | CV32: =IFERROR(CU32/TK!R25,0) -> 0 | DA32: =CO32+CQ32+CS32+CU32+CW32+CY32 -> 0 | DB32: =IFERROR(DA32/(CO11+CQ11+CS11+CU11),0) -> 0 | DC32: =IFERROR((DA32-CL32)/CL32,0) -> 0 | DD32: =AMAZON!T223 -> 0 | DE32: =IFERROR(DD32/AMAZON!T50,0) -> 0 | DF32: =TEMU!T103 -> 0 | DG32: =IFERROR(DF32/TEMU!T25,0) -> 0 | DH32: =SHEIN!T79 -> 0 | DI32: =IFERROR(DH32/SHEIN!T20,0) -> 0 | DJ32: =TK!T103 -> 0 | DK32: =IFERROR(DJ32/TK!T25,0) -> 0 | DP32: =DD32+DF32+DH32+DJ32+DL32+DN32 -> 0 | DQ32: =IFERROR(DP32/(DD11+DF11+DH11+DJ11),0) -> 0 | DR32: =IFERROR((DP32-DA32)/DA32,0) -> 0 | DS32: =AMAZON!V223 -> 0 | DT32: =IFERROR(DS32/AMAZON!V50,0) -> 0 | DU32: =TEMU!V103 -> 0 | DV32: =IFERROR(DU32/TEMU!V25,0) -> 0 | DW32: =SHEIN!V79 -> 0 | DX32: =IFERROR(DW32/SHEIN!V20,0) -> 0 | DY32: =TK!V103 -> 0 | DZ32: =IFERROR(DY32/TK!V25,0) -> 0 | EE32: =DS32+DU32+DW32+DY32+EA32+EC32 -> 0 | EF32: =IFERROR(EE32/(DS11+DU11+DW11+DY11),0) -> 0 | EG32: =IFERROR((EE32-DP32)/DP32,0) -> 0 | EH32: =AMAZON!X223 -> 0 | EI32: =IFERROR(EH32/AMAZON!X50,0) -> 0 | EJ32: =TEMU!X103 -> 0 | EK32: =IFERROR(EJ32/TEMU!X25,0) -> 0 | EL32: =SHEIN!X79 -> 0 | EM32: =IFERROR(EL32/SHEIN!X20,0) -> 0 | EN32: =TK!X103 -> 0 | EO32: =IFERROR(EN32/TK!X25,0) -> 0 | ET32: =EH32+EJ32+EL32+EN32+EP32+ER32 -> 0 | EU32: =IFERROR(ET32/(EH11+EJ11+EL11+EN11),0) -> 0 | EV32: =IFERROR((ET32-EE32)/EE32,0) -> 0 | EW32: =AMAZON!Z223 -> 0 | EX32: =IFERROR(EW32/AMAZON!Z50,0) -> 0 | EY32: =TEMU!Z103 -> 0 | EZ32: =IFERROR(EY32/TEMU!Z25,0) -> 0 | FA32: =SHEIN!Z79 -> 0 | FB32: =IFERROR(FA32/SHEIN!Z20,0) -> 0 | FC32: =TK!Z103 -> 0 | FD32: =IFERROR(FC32/TK!Z25,0) -> 0 | FI32: =EW32+EY32+FA32+FC32+FE32+FG32 -> 0 | FJ32: =IFERROR(FI32/(EW11+EY11+FA11+FC11),0) -> 0 | FK32: =IFERROR((FI32-ET32)/ET32,0) -> 0 | FL32: =AMAZON!AB223 -> 0 | FM32: =IFERROR(FL32/AMAZON!AB50,0) -> 0 | FN32: =TEMU!AB103 -> 0 | FO32: =IFERROR(FN32/TEMU!AB25,0) -> 0 | FP32: =SHEIN!AB79 -> 0 | FQ32: =IFERROR(FP32/SHEIN!AB20,0) -> 0 | FR32: =TK!AB103 -> 0 | FS32: =IFERROR(FR32/TK!AB25,0) -> 0 | FX32: =FL32+FN32+FP32+FR32+FT32+FV32 -> 0 | FY32: =IFERROR(FX32/(FL11+FN11+FP11+FR11),0) -> 0 | FZ32: =IFERROR((FX32-FI32)/FI32,0) -> 0 | GA32: =AMAZON!AD223 -> 0 | GB32: =IFERROR(GA32/AMAZON!AD50,0) -> 0 | GC32: =TEMU!AD103 -> 0 | GD32: =IFERROR(GC32/TEMU!AD25,0) -> 0 | GE32: =SHEIN!AD79 -> 0 | GF32: =IFERROR(GE32/SHEIN!AD20,0) -> 0 | GG32: =TK!AD103 -> 0 | GH32: =IFERROR(GG32/TK!AD25,0) -> 0 | GM32: =GA32+GC32+GE32+GG32+GI32+GK32 -> 0 | GN32: =IFERROR(GM32/(GA11+GC11+GE11+GG11),0) -> 0 | GO32: =IFERROR((GM32-FX32)/FX32,0) -> 0
A33: 其他项目 | B33: 中转费 | C33: 元 | D33: =AMAZON!F232 -> 0 | E33: =IFERROR(D33/AMAZON!F50,0) -> 0 | F33: =TEMU!F107 -> 0 | G33: =IFERROR(F33/TEMU!F25,0) -> 0 | H33: =SHEIN!F82 -> 0 | I33: =IFERROR(H33/SHEIN!F20,0) -> 0 | J33: =TK!F107 -> 0 | K33: =IFERROR(J33/TK!F25,0) -> 0 | P33: =D33+F33+H33+J33+L33+N33 -> 0 | Q33: =IFERROR(P33/(D11+F11+H11+J11),0) -> 0 | R33: =AMAZON!H232 -> 0 | S33: =IFERROR(R33/AMAZON!H50,0) -> 0 | T33: =TEMU!H107 -> 0 | U33: =IFERROR(T33/TEMU!H25,0) -> 0 | V33: =SHEIN!H82 -> 0 | W33: =IFERROR(V33/SHEIN!H20,0) -> 0 | X33: =TK!H107 -> 0 | Y33: =IFERROR(X33/TK!H25,0) -> 0 | AD33: =R33+T33+V33+X33+Z33+AB33 -> 0 | AE33: =IFERROR(AD33/(R11+T11+V11+X11),0) -> 0 | AG33: =AMAZON!J232 -> 0 | AH33: =IFERROR(AG33/AMAZON!J50,0) -> 0 | AI33: =TEMU!J107 -> 0 | AJ33: =IFERROR(AI33/TEMU!J25,0) -> 0 | AK33: =SHEIN!J82 -> 0 | AL33: =IFERROR(AK33/SHEIN!J20,0) -> 0 | AM33: =TK!J107 -> 0 | AN33: =IFERROR(AM33/TK!J25,0) -> 0 | AS33: =AG33+AI33+AK33+AM33+AO33+AQ33 -> 0 | AT33: =IFERROR(AS33/(AG11+AI11+AK11+AM11),0) -> 0 | AU33: =IFERROR((AS33-AD33)/AD33,0) -> 0 | AV33: =AMAZON!L232 -> 0 | AW33: =IFERROR(AV33/AMAZON!L50,0) -> 0 | AX33: =TEMU!L107 -> 0 | AY33: =IFERROR(AX33/TEMU!L25,0) -> 0 | AZ33: =SHEIN!L82 -> 0 | BA33: =IFERROR(AZ33/SHEIN!L20,0) -> 0 | BB33: =TK!L107 -> 0 | BC33: =IFERROR(BB33/TK!L25,0) -> 0 | BH33: =AV33+AX33+AZ33+BB33+BD33+BF33 -> 0 | BI33: =IFERROR(BH33/(AV11+AX11+AZ11+BB11),0) -> 0 | BJ33: =IFERROR((BH33-AS33)/AS33,0) -> 0 | BK33: =AMAZON!N232 -> 0 | BL33: =IFERROR(BK33/AMAZON!N50,0) -> 0 | BM33: =TEMU!N107 -> 0 | BN33: =IFERROR(BM33/TEMU!N25,0) -> 0 | BO33: =SHEIN!N82 -> 0 | BP33: =IFERROR(BO33/SHEIN!N20,0) -> 0 | BQ33: =TK!N107 -> 0 | BR33: =IFERROR(BQ33/TK!N25,0) -> 0 | BW33: =BK33+BM33+BO33+BQ33+BS33+BU33 -> 0 | BX33: =IFERROR(BW33/(BK11+BM11+BO11+BQ11),0) -> 0 | BY33: =IFERROR((BW33-BH33)/BH33,0) -> 0 | BZ33: =AMAZON!P232 -> 0 | CA33: =IFERROR(BZ33/AMAZON!P50,0) -> 0 | CB33: =TEMU!P107 -> 0 | CC33: =IFERROR(CB33/TEMU!P25,0) -> 0 | CD33: =SHEIN!P82 -> 0 | CE33: =IFERROR(CD33/SHEIN!P20,0) -> 0 | CF33: =TK!P107 -> 0 | CG33: =IFERROR(CF33/TK!P25,0) -> 0 | CL33: =BZ33+CB33+CD33+CF33+CH33+CJ33 -> 0 | CM33: =IFERROR(CL33/(BZ11+CB11+CD11+CF11),0) -> 0 | CN33: =IFERROR((CL33-BW33)/BW33,0) -> 0 | CO33: =AMAZON!R232 -> 0 | CP33: =IFERROR(CO33/AMAZON!R50,0) -> 0 | CQ33: =TEMU!R107 -> 0 | CR33: =IFERROR(CQ33/TEMU!R25,0) -> 0 | CS33: =SHEIN!R82 -> 0 | CT33: =IFERROR(CS33/SHEIN!R20,0) -> 0 | CU33: =TK!R107 -> 0 | CV33: =IFERROR(CU33/TK!R25,0) -> 0 | DA33: =CO33+CQ33+CS33+CU33+CW33+CY33 -> 0 | DB33: =IFERROR(DA33/(CO11+CQ11+CS11+CU11),0) -> 0 | DC33: =IFERROR((DA33-CL33)/CL33,0) -> 0 | DD33: =AMAZON!T232 -> 0 | DE33: =IFERROR(DD33/AMAZON!T50,0) -> 0 | DF33: =TEMU!T107 -> 0 | DG33: =IFERROR(DF33/TEMU!T25,0) -> 0 | DH33: =SHEIN!T82 -> 0 | DI33: =IFERROR(DH33/SHEIN!T20,0) -> 0 | DJ33: =TK!T107 -> 0 | DK33: =IFERROR(DJ33/TK!T25,0) -> 0 | DP33: =DD33+DF33+DH33+DJ33+DL33+DN33 -> 0 | DQ33: =IFERROR(DP33/(DD11+DF11+DH11+DJ11),0) -> 0 | DR33: =IFERROR((DP33-DA33)/DA33,0) -> 0 | DS33: =AMAZON!V232 -> 0 | DT33: =IFERROR(DS33/AMAZON!V50,0) -> 0 | DU33: =TEMU!V107 -> 0 | DV33: =IFERROR(DU33/TEMU!V25,0) -> 0 | DW33: =SHEIN!V82 -> 0 | DX33: =IFERROR(DW33/SHEIN!V20,0) -> 0 | DY33: =TK!V107 -> 0 | DZ33: =IFERROR(DY33/TK!V25,0) -> 0 | EE33: =DS33+DU33+DW33+DY33+EA33+EC33 -> 0 | EF33: =IFERROR(EE33/(DS11+DU11+DW11+DY11),0) -> 0 | EG33: =IFERROR((EE33-DP33)/DP33,0) -> 0 | EH33: =AMAZON!X232 -> 0 | EI33: =IFERROR(EH33/AMAZON!X50,0) -> 0 | EJ33: =TEMU!X107 -> 0 | EK33: =IFERROR(EJ33/TEMU!X25,0) -> 0 | EL33: =SHEIN!X82 -> 0 | EM33: =IFERROR(EL33/SHEIN!X20,0) -> 0 | EN33: =TK!X107 -> 0 | EO33: =IFERROR(EN33/TK!X25,0) -> 0 | ET33: =EH33+EJ33+EL33+EN33+EP33+ER33 -> 0 | EU33: =IFERROR(ET33/(EH11+EJ11+EL11+EN11),0) -> 0 | EV33: =IFERROR((ET33-EE33)/EE33,0) -> 0 | EW33: =AMAZON!Z232 -> 0 | EX33: =IFERROR(EW33/AMAZON!Z50,0) -> 0 | EY33: =TEMU!Z107 -> 0 | EZ33: =IFERROR(EY33/TEMU!Z25,0) -> 0 | FA33: =SHEIN!Z82 -> 0 | FB33: =IFERROR(FA33/SHEIN!Z20,0) -> 0 | FC33: =TK!Z107 -> 0 | FD33: =IFERROR(FC33/TK!Z25,0) -> 0 | FI33: =EW33+EY33+FA33+FC33+FE33+FG33 -> 0 | FJ33: =IFERROR(FI33/(EW11+EY11+FA11+FC11),0) -> 0 | FK33: =IFERROR((FI33-ET33)/ET33,0) -> 0 | FL33: =AMAZON!AB232 -> 0 | FM33: =IFERROR(FL33/AMAZON!AB50,0) -> 0 | FN33: =TEMU!AB107 -> 0 | FO33: =IFERROR(FN33/TEMU!AB25,0) -> 0 | FP33: =SHEIN!AB82 -> 0 | FQ33: =IFERROR(FP33/SHEIN!AB20,0) -> 0 | FR33: =TK!AB107 -> 0 | FS33: =IFERROR(FR33/TK!AB25,0) -> 0 | FX33: =FL33+FN33+FP33+FR33+FT33+FV33 -> 0 | FY33: =IFERROR(FX33/(FL11+FN11+FP11+FR11),0) -> 0 | FZ33: =IFERROR((FX33-FI33)/FI33,0) -> 0 | GA33: =AMAZON!AD232 -> 0 | GB33: =IFERROR(GA33/AMAZON!AD50,0) -> 0 | GC33: =TEMU!AD107 -> 0 | GD33: =IFERROR(GC33/TEMU!AD25,0) -> 0 | GE33: =SHEIN!AD82 -> 0 | GF33: =IFERROR(GE33/SHEIN!AD20,0) -> 0 | GG33: =TK!AD107 -> 0 | GH33: =IFERROR(GG33/TK!AD25,0) -> 0 | GM33: =GA33+GC33+GE33+GG33+GI33+GK33 -> 0 | GN33: =IFERROR(GM33/(GA11+GC11+GE11+GG11),0) -> 0 | GO33: =IFERROR((GM33-FX33)/FX33,0) -> 0
A34: 其他项目 | B34: 操作费 | C34: 元 | D34: =AMAZON!F241 -> 0 | E34: =IFERROR(D34/AMAZON!F50,0) -> 0 | F34: =TEMU!F111 -> 0 | G34: =IFERROR(F34/TEMU!F25,0) -> 0 | H34: =SHEIN!F85 -> 0 | I34: =IFERROR(H34/SHEIN!F20,0) -> 0 | J34: =TK!F111 -> 0 | K34: =IFERROR(J34/TK!F25,0) -> 0 | P34: =D34+F34+H34+J34+L34+N34 -> 0 | Q34: =IFERROR(P34/(D11+F11+H11+J11),0) -> 0 | R34: =AMAZON!H241 -> 0 | S34: =IFERROR(R34/AMAZON!H50,0) -> 0 | T34: =TEMU!H111 -> 0 | U34: =IFERROR(T34/TEMU!H25,0) -> 0 | V34: =SHEIN!H85 -> 0 | W34: =IFERROR(V34/SHEIN!H20,0) -> 0 | X34: =TK!H111 -> 0 | Y34: =IFERROR(X34/TK!H25,0) -> 0 | AD34: =R34+T34+V34+X34+Z34+AB34 -> 0 | AE34: =IFERROR(AD34/(R11+T11+V11+X11),0) -> 0 | AG34: =AMAZON!J241 -> 0 | AH34: =IFERROR(AG34/AMAZON!J50,0) -> 0 | AI34: =TEMU!J111 -> 0 | AJ34: =IFERROR(AI34/TEMU!J25,0) -> 0 | AK34: =SHEIN!J85 -> 0 | AL34: =IFERROR(AK34/SHEIN!J20,0) -> 0 | AM34: =TK!J111 -> 0 | AN34: =IFERROR(AM34/TK!J25,0) -> 0 | AS34: =AG34+AI34+AK34+AM34+AO34+AQ34 -> 0 | AT34: =IFERROR(AS34/(AG11+AI11+AK11+AM11),0) -> 0 | AU34: =IFERROR((AS34-AD34)/AD34,0) -> 0 | AV34: =AMAZON!L241 -> 0 | AW34: =IFERROR(AV34/AMAZON!L50,0) -> 0 | AX34: =TEMU!L111 -> 0 | AY34: =IFERROR(AX34/TEMU!L25,0) -> 0 | AZ34: =SHEIN!L85 -> 0 | BA34: =IFERROR(AZ34/SHEIN!L20,0) -> 0 | BB34: =TK!L111 -> 0 | BC34: =IFERROR(BB34/TK!L25,0) -> 0 | BH34: =AV34+AX34+AZ34+BB34+BD34+BF34 -> 0 | BI34: =IFERROR(BH34/(AV11+AX11+AZ11+BB11),0) -> 0 | BJ34: =IFERROR((BH34-AS34)/AS34,0) -> 0 | BK34: =AMAZON!N241 -> 0 | BL34: =IFERROR(BK34/AMAZON!N50,0) -> 0 | BM34: =TEMU!N111 -> 0 | BN34: =IFERROR(BM34/TEMU!N25,0) -> 0 | BO34: =SHEIN!N85 -> 0 | BP34: =IFERROR(BO34/SHEIN!N20,0) -> 0 | BQ34: =TK!N111 -> 0 | BR34: =IFERROR(BQ34/TK!N25,0) -> 0 | BW34: =BK34+BM34+BO34+BQ34+BS34+BU34 -> 0 | BX34: =IFERROR(BW34/(BK11+BM11+BO11+BQ11),0) -> 0 | BY34: =IFERROR((BW34-BH34)/BH34,0) -> 0 | BZ34: =AMAZON!P241 -> 0 | CA34: =IFERROR(BZ34/AMAZON!P50,0) -> 0 | CB34: =TEMU!P111 -> 0 | CC34: =IFERROR(CB34/TEMU!P25,0) -> 0 | CD34: =SHEIN!P85 -> 0 | CE34: =IFERROR(CD34/SHEIN!P20,0) -> 0 | CF34: =TK!P111 -> 0 | CG34: =IFERROR(CF34/TK!P25,0) -> 0 | CL34: =BZ34+CB34+CD34+CF34+CH34+CJ34 -> 0 | CM34: =IFERROR(CL34/(BZ11+CB11+CD11+CF11),0) -> 0 | CN34: =IFERROR((CL34-BW34)/BW34,0) -> 0 | CO34: =AMAZON!R241 -> 0 | CP34: =IFERROR(CO34/AMAZON!R50,0) -> 0 | CQ34: =TEMU!R111 -> 0 | CR34: =IFERROR(CQ34/TEMU!R25,0) -> 0 | CS34: =SHEIN!R85 -> 0 | CT34: =IFERROR(CS34/SHEIN!R20,0) -> 0 | CU34: =TK!R111 -> 0 | CV34: =IFERROR(CU34/TK!R25,0) -> 0 | DA34: =CO34+CQ34+CS34+CU34+CW34+CY34 -> 0 | DB34: =IFERROR(DA34/(CO11+CQ11+CS11+CU11),0) -> 0 | DC34: =IFERROR((DA34-CL34)/CL34,0) -> 0 | DD34: =AMAZON!T241 -> 0 | DE34: =IFERROR(DD34/AMAZON!T50,0) -> 0 | DF34: =TEMU!T111 -> 0 | DG34: =IFERROR(DF34/TEMU!T25,0) -> 0 | DH34: =SHEIN!T85 -> 0 | DI34: =IFERROR(DH34/SHEIN!T20,0) -> 0 | DJ34: =TK!T111 -> 0 | DK34: =IFERROR(DJ34/TK!T25,0) -> 0 | DP34: =DD34+DF34+DH34+DJ34+DL34+DN34 -> 0 | DQ34: =IFERROR(DP34/(DD11+DF11+DH11+DJ11),0) -> 0 | DR34: =IFERROR((DP34-DA34)/DA34,0) -> 0 | DS34: =AMAZON!V241 -> 0 | DT34: =IFERROR(DS34/AMAZON!V50,0) -> 0 | DU34: =TEMU!V111 -> 0 | DV34: =IFERROR(DU34/TEMU!V25,0) -> 0 | DW34: =SHEIN!V85 -> 0 | DX34: =IFERROR(DW34/SHEIN!V20,0) -> 0 | DY34: =TK!V111 -> 0 | DZ34: =IFERROR(DY34/TK!V25,0) -> 0 | EE34: =DS34+DU34+DW34+DY34+EA34+EC34 -> 0 | EF34: =IFERROR(EE34/(DS11+DU11+DW11+DY11),0) -> 0 | EG34: =IFERROR((EE34-DP34)/DP34,0) -> 0 | EH34: =AMAZON!X241 -> 0 | EI34: =IFERROR(EH34/AMAZON!X50,0) -> 0 | EJ34: =TEMU!X111 -> 0 | EK34: =IFERROR(EJ34/TEMU!X25,0) -> 0 | EL34: =SHEIN!X85 -> 0 | EM34: =IFERROR(EL34/SHEIN!X20,0) -> 0 | EN34: =TK!X111 -> 0 | EO34: =IFERROR(EN34/TK!X25,0) -> 0 | ET34: =EH34+EJ34+EL34+EN34+EP34+ER34 -> 0 | EU34: =IFERROR(ET34/(EH11+EJ11+EL11+EN11),0) -> 0 | EV34: =IFERROR((ET34-EE34)/EE34,0) -> 0 | EW34: =AMAZON!Z241 -> 0 | EX34: =IFERROR(EW34/AMAZON!Z50,0) -> 0 | EY34: =TEMU!Z111 -> 0 | EZ34: =IFERROR(EY34/TEMU!Z25,0) -> 0 | FA34: =SHEIN!Z85 -> 0 | FB34: =IFERROR(FA34/SHEIN!Z20,0) -> 0 | FC34: =TK!Z111 -> 0 | FD34: =IFERROR(FC34/TK!Z25,0) -> 0 | FI34: =EW34+EY34+FA34+FC34+FE34+FG34 -> 0 | FJ34: =IFERROR(FI34/(EW11+EY11+FA11+FC11),0) -> 0 | FK34: =IFERROR((FI34-ET34)/ET34,0) -> 0 | FL34: =AMAZON!AB241 -> 0 | FM34: =IFERROR(FL34/AMAZON!AB50,0) -> 0 | FN34: =TEMU!AB111 -> 0 | FO34: =IFERROR(FN34/TEMU!AB25,0) -> 0 | FP34: =SHEIN!AB85 -> 0 | FQ34: =IFERROR(FP34/SHEIN!AB20,0) -> 0 | FR34: =TK!AB111 -> 0 | FS34: =IFERROR(FR34/TK!AB25,0) -> 0 | FX34: =FL34+FN34+FP34+FR34+FT34+FV34 -> 0 | FY34: =IFERROR(FX34/(FL11+FN11+FP11+FR11),0) -> 0 | FZ34: =IFERROR((FX34-FI34)/FI34,0) -> 0 | GA34: =AMAZON!AD241 -> 0 | GB34: =IFERROR(GA34/AMAZON!AD50,0) -> 0 | GC34: =TEMU!AD111 -> 0 | GD34: =IFERROR(GC34/TEMU!AD25,0) -> 0 | GE34: =SHEIN!AD85 -> 0 | GF34: =IFERROR(GE34/SHEIN!AD20,0) -> 0 | GG34: =TK!AD111 -> 0 | GH34: =IFERROR(GG34/TK!AD25,0) -> 0 | GM34: =GA34+GC34+GE34+GG34+GI34+GK34 -> 0 | GN34: =IFERROR(GM34/(GA11+GC11+GE11+GG11),0) -> 0 | GO34: =IFERROR((GM34-FX34)/FX34,0) -> 0
A35: 其他项目 | B35: 情趣利润 | C35: 元 | D35: =AMAZON!F250 -> 0 | E35: =IFERROR(D35/AMAZON!F50,0) -> 0 | F35: =TEMU!F115 -> 0 | G35: =IFERROR(F35/TEMU!F25,0) -> 0 | H35: =SHEIN!F88 -> 0 | I35: =IFERROR(H35/SHEIN!F20,0) -> 0 | J35: =TK!F115 -> 0 | K35: =IFERROR(J35/TK!F25,0) -> 0 | P35: =D35+F35+H35+J35+L35+N35 -> 0 | Q35: =IFERROR(P35/(D11+F11+H11+J11),0) -> 0 | R35: =AMAZON!H250 -> 0 | S35: =IFERROR(R35/AMAZON!H50,0) -> 0 | T35: =TEMU!H115 -> 0 | U35: =IFERROR(T35/TEMU!H25,0) -> 0 | V35: =SHEIN!H88 -> 0 | W35: =IFERROR(V35/SHEIN!H20,0) -> 0 | X35: =TK!H115 -> 0 | Y35: =IFERROR(X35/TK!H25,0) -> 0 | AD35: =R35+T35+V35+X35+Z35+AB35 -> 0 | AE35: =IFERROR(AD35/(R11+T11+V11+X11),0) -> 0 | AG35: =AMAZON!J250 -> 0 | AH35: =IFERROR(AG35/AMAZON!J50,0) -> 0 | AI35: =TEMU!J115 -> 0 | AJ35: =IFERROR(AI35/TEMU!J25,0) -> 0 | AK35: =SHEIN!J88 -> 0 | AL35: =IFERROR(AK35/SHEIN!J20,0) -> 0 | AM35: =TK!J115 -> 0 | AN35: =IFERROR(AM35/TK!J25,0) -> 0 | AS35: =AG35+AI35+AK35+AM35+AO35+AQ35 -> 0 | AT35: =IFERROR(AS35/(AG11+AI11+AK11+AM11),0) -> 0 | AU35: =IFERROR((AS35-AD35)/AD35,0) -> 0 | AV35: =AMAZON!L250 -> 0 | AW35: =IFERROR(AV35/AMAZON!L50,0) -> 0 | AX35: =TEMU!L115 -> 0 | AY35: =IFERROR(AX35/TEMU!L25,0) -> 0 | AZ35: =SHEIN!L88 -> 0 | BA35: =IFERROR(AZ35/SHEIN!L20,0) -> 0 | BB35: =TK!L115 -> 0 | BC35: =IFERROR(BB35/TK!L25,0) -> 0 | BH35: =AV35+AX35+AZ35+BB35+BD35+BF35 -> 0 | BI35: =IFERROR(BH35/(AV11+AX11+AZ11+BB11),0) -> 0 | BJ35: =IFERROR((BH35-AS35)/AS35,0) -> 0 | BK35: =AMAZON!N250 -> 0 | BL35: =IFERROR(BK35/AMAZON!N50,0) -> 0 | BM35: =TEMU!N115 -> 0 | BN35: =IFERROR(BM35/TEMU!N25,0) -> 0 | BO35: =SHEIN!N88 -> 0 | BP35: =IFERROR(BO35/SHEIN!N20,0) -> 0 | BQ35: =TK!N115 -> 0 | BR35: =IFERROR(BQ35/TK!N25,0) -> 0 | BW35: =BK35+BM35+BO35+BQ35+BS35+BU35 -> 0 | BX35: =IFERROR(BW35/(BK11+BM11+BO11+BQ11),0) -> 0 | BY35: =IFERROR((BW35-BH35)/BH35,0) -> 0 | BZ35: =AMAZON!P250 -> 0 | CA35: =IFERROR(BZ35/AMAZON!P50,0) -> 0 | CB35: =TEMU!P115 -> 0 | CC35: =IFERROR(CB35/TEMU!P25,0) -> 0 | CD35: =SHEIN!P88 -> 0 | CE35: =IFERROR(CD35/SHEIN!P20,0) -> 0 | CF35: =TK!P115 -> 0 | CG35: =IFERROR(CF35/TK!P25,0) -> 0 | CL35: =BZ35+CB35+CD35+CF35+CH35+CJ35 -> 0 | CM35: =IFERROR(CL35/(BZ11+CB11+CD11+CF11),0) -> 0 | CN35: =IFERROR((CL35-BW35)/BW35,0) -> 0 | CO35: =AMAZON!R250 -> 0 | CP35: =IFERROR(CO35/AMAZON!R50,0) -> 0 | CQ35: =TEMU!R115 -> 0 | CR35: =IFERROR(CQ35/TEMU!R25,0) -> 0 | CS35: =SHEIN!R88 -> 0 | CT35: =IFERROR(CS35/SHEIN!R20,0) -> 0 | CU35: =TK!R115 -> 0 | CV35: =IFERROR(CU35/TK!R25,0) -> 0 | DA35: =CO35+CQ35+CS35+CU35+CW35+CY35 -> 0 | DB35: =IFERROR(DA35/(CO11+CQ11+CS11+CU11),0) -> 0 | DC35: =IFERROR((DA35-CL35)/CL35,0) -> 0 | DD35: =AMAZON!T250 -> 0 | DE35: =IFERROR(DD35/AMAZON!T50,0) -> 0 | DF35: =TEMU!T115 -> 0 | DG35: =IFERROR(DF35/TEMU!T25,0) -> 0 | DH35: =SHEIN!T88 -> 0 | DI35: =IFERROR(DH35/SHEIN!T20,0) -> 0 | DJ35: =TK!T115 -> 0 | DK35: =IFERROR(DJ35/TK!T25,0) -> 0 | DP35: =DD35+DF35+DH35+DJ35+DL35+DN35 -> 0 | DQ35: =IFERROR(DP35/(DD11+DF11+DH11+DJ11),0) -> 0 | DR35: =IFERROR((DP35-DA35)/DA35,0) -> 0 | DS35: =AMAZON!V250 -> 0 | DT35: =IFERROR(DS35/AMAZON!V50,0) -> 0 | DU35: =TEMU!V115 -> 0 | DV35: =IFERROR(DU35/TEMU!V25,0) -> 0 | DW35: =SHEIN!V88 -> 0 | DX35: =IFERROR(DW35/SHEIN!V20,0) -> 0 | DY35: =TK!V115 -> 0 | DZ35: =IFERROR(DY35/TK!V25,0) -> 0 | EE35: =DS35+DU35+DW35+DY35+EA35+EC35 -> 0 | EF35: =IFERROR(EE35/(DS11+DU11+DW11+DY11),0) -> 0 | EG35: =IFERROR((EE35-DP35)/DP35,0) -> 0 | EH35: =AMAZON!X250 -> 0 | EI35: =IFERROR(EH35/AMAZON!X50,0) -> 0 | EJ35: =TEMU!X115 -> 0 | EK35: =IFERROR(EJ35/TEMU!X25,0) -> 0 | EL35: =SHEIN!X88 -> 0 | EM35: =IFERROR(EL35/SHEIN!X20,0) -> 0 | EN35: =TK!X115 -> 0 | EO35: =IFERROR(EN35/TK!X25,0) -> 0 | ET35: =EH35+EJ35+EL35+EN35+EP35+ER35 -> 0 | EU35: =IFERROR(ET35/(EH11+EJ11+EL11+EN11),0) -> 0 | EV35: =IFERROR((ET35-EE35)/EE35,0) -> 0 | EW35: =AMAZON!Z250 -> 0 | EX35: =IFERROR(EW35/AMAZON!Z50,0) -> 0 | EY35: =TEMU!Z115 -> 0 | EZ35: =IFERROR(EY35/TEMU!Z25,0) -> 0 | FA35: =SHEIN!Z88 -> 0 | FB35: =IFERROR(FA35/SHEIN!Z20,0) -> 0 | FC35: =TK!Z115 -> 0 | FD35: =IFERROR(FC35/TK!Z25,0) -> 0 | FI35: =EW35+EY35+FA35+FC35+FE35+FG35 -> 0 | FJ35: =IFERROR(FI35/(EW11+EY11+FA11+FC11),0) -> 0 | FK35: =IFERROR((FI35-ET35)/ET35,0) -> 0 | FL35: =AMAZON!AB250 -> 0 | FM35: =IFERROR(FL35/AMAZON!AB50,0) -> 0 | FN35: =TEMU!AB115 -> 0 | FO35: =IFERROR(FN35/TEMU!AB25,0) -> 0 | FP35: =SHEIN!AB88 -> 0 | FQ35: =IFERROR(FP35/SHEIN!AB20,0) -> 0 | FR35: =TK!AB115 -> 0 | FS35: =IFERROR(FR35/TK!AB25,0) -> 0 | FX35: =FL35+FN35+FP35+FR35+FT35+FV35 -> 0 | FY35: =IFERROR(FX35/(FL11+FN11+FP11+FR11),0) -> 0 | FZ35: =IFERROR((FX35-FI35)/FI35,0) -> 0 | GA35: =AMAZON!AD250 -> 0 | GB35: =IFERROR(GA35/AMAZON!AD50,0) -> 0 | GC35: =TEMU!AD115 -> 0 | GD35: =IFERROR(GC35/TEMU!AD25,0) -> 0 | GE35: =SHEIN!AD88 -> 0 | GF35: =IFERROR(GE35/SHEIN!AD20,0) -> 0 | GG35: =TK!AD115 -> 0 | GH35: =IFERROR(GG35/TK!AD25,0) -> 0 | GM35: =GA35+GC35+GE35+GG35+GI35+GK35 -> 0 | GN35: =IFERROR(GM35/(GA11+GC11+GE11+GG11),0) -> 0 | GO35: =IFERROR((GM35-FX35)/FX35,0) -> 0
A36: 其他项目 | B36: 黑猫利润 | C36: 元 | D36: =AMAZON!F259 -> 0 | E36: =IFERROR(D36/AMAZON!F50,0) -> 0 | F36: =TEMU!F119 -> 0 | G36: =IFERROR(F36/TEMU!F25,0) -> 0 | H36: =SHEIN!F91 -> 0 | I36: =IFERROR(H36/SHEIN!F20,0) -> 0 | J36: =TK!F119 -> 0 | K36: =IFERROR(J36/TK!F25,0) -> 0 | P36: =D36+F36+H36+J36+L36+N36 -> 0 | Q36: =IFERROR(P36/(D11+F11+H11+J11),0) -> 0 | R36: =AMAZON!H259 -> 0 | S36: =IFERROR(R36/AMAZON!H50,0) -> 0 | T36: =TEMU!H119 -> 0 | U36: =IFERROR(T36/TEMU!H25,0) -> 0 | V36: =SHEIN!H91 -> 0 | W36: =IFERROR(V36/SHEIN!H20,0) -> 0 | X36: =TK!H119 -> 0 | Y36: =IFERROR(X36/TK!H25,0) -> 0 | AD36: =R36+T36+V36+X36+Z36+AB36 -> 0 | AE36: =IFERROR(AD36/(R11+T11+V11+X11),0) -> 0 | AG36: =AMAZON!J259 -> 0 | AH36: =IFERROR(AG36/AMAZON!J50,0) -> 0 | AI36: =TEMU!J119 -> 0 | AJ36: =IFERROR(AI36/TEMU!J25,0) -> 0 | AK36: =SHEIN!J91 -> 0 | AL36: =IFERROR(AK36/SHEIN!J20,0) -> 0 | AM36: =TK!J119 -> 0 | AN36: =IFERROR(AM36/TK!J25,0) -> 0 | AS36: =AG36+AI36+AK36+AM36+AO36+AQ36 -> 0 | AT36: =IFERROR(AS36/(AG11+AI11+AK11+AM11),0) -> 0 | AU36: =IFERROR((AS36-AD36)/AD36,0) -> 0 | AV36: =AMAZON!L259 -> 0 | AW36: =IFERROR(AV36/AMAZON!L50,0) -> 0 | AX36: =TEMU!L119 -> 0 | AY36: =IFERROR(AX36/TEMU!L25,0) -> 0 | AZ36: =SHEIN!L91 -> 0 | BA36: =IFERROR(AZ36/SHEIN!L20,0) -> 0 | BB36: =TK!L119 -> 0 | BC36: =IFERROR(BB36/TK!L25,0) -> 0 | BH36: =AV36+AX36+AZ36+BB36+BD36+BF36 -> 0 | BI36: =IFERROR(BH36/(AV11+AX11+AZ11+BB11),0) -> 0 | BJ36: =IFERROR((BH36-AS36)/AS36,0) -> 0 | BK36: =AMAZON!N259 -> 0 | BL36: =IFERROR(BK36/AMAZON!N50,0) -> 0 | BM36: =TEMU!N119 -> 0 | BN36: =IFERROR(BM36/TEMU!N25,0) -> 0 | BO36: =SHEIN!N91 -> 0 | BP36: =IFERROR(BO36/SHEIN!N20,0) -> 0 | BQ36: =TK!N119 -> 0 | BR36: =IFERROR(BQ36/TK!N25,0) -> 0 | BW36: =BK36+BM36+BO36+BQ36+BS36+BU36 -> 0 | BX36: =IFERROR(BW36/(BK11+BM11+BO11+BQ11),0) -> 0 | BY36: =IFERROR((BW36-BH36)/BH36,0) -> 0 | BZ36: =AMAZON!P259 -> 0 | CA36: =IFERROR(BZ36/AMAZON!P50,0) -> 0 | CB36: =TEMU!P119 -> 0 | CC36: =IFERROR(CB36/TEMU!P25,0) -> 0 | CD36: =SHEIN!P91 -> 0 | CE36: =IFERROR(CD36/SHEIN!P20,0) -> 0 | CF36: =TK!P119 -> 0 | CG36: =IFERROR(CF36/TK!P25,0) -> 0 | CL36: =BZ36+CB36+CD36+CF36+CH36+CJ36 -> 0 | CM36: =IFERROR(CL36/(BZ11+CB11+CD11+CF11),0) -> 0 | CN36: =IFERROR((CL36-BW36)/BW36,0) -> 0 | CO36: =AMAZON!R259 -> 0 | CP36: =IFERROR(CO36/AMAZON!R50,0) -> 0 | CQ36: =TEMU!R119 -> 0 | CR36: =IFERROR(CQ36/TEMU!R25,0) -> 0 | CS36: =SHEIN!R91 -> 0 | CT36: =IFERROR(CS36/SHEIN!R20,0) -> 0 | CU36: =TK!R119 -> 0 | CV36: =IFERROR(CU36/TK!R25,0) -> 0 | DA36: =CO36+CQ36+CS36+CU36+CW36+CY36 -> 0 | DB36: =IFERROR(DA36/(CO11+CQ11+CS11+CU11),0) -> 0 | DC36: =IFERROR((DA36-CL36)/CL36,0) -> 0 | DD36: =AMAZON!T259 -> 0 | DE36: =IFERROR(DD36/AMAZON!T50,0) -> 0 | DF36: =TEMU!T119 -> 0 | DG36: =IFERROR(DF36/TEMU!T25,0) -> 0 | DH36: =SHEIN!T91 -> 0 | DI36: =IFERROR(DH36/SHEIN!T20,0) -> 0 | DJ36: =TK!T119 -> 0 | DK36: =IFERROR(DJ36/TK!T25,0) -> 0 | DP36: =DD36+DF36+DH36+DJ36+DL36+DN36 -> 0 | DQ36: =IFERROR(DP36/(DD11+DF11+DH11+DJ11),0) -> 0 | DR36: =IFERROR((DP36-DA36)/DA36,0) -> 0 | DS36: =AMAZON!V259 -> 0 | DT36: =IFERROR(DS36/AMAZON!V50,0) -> 0 | DU36: =TEMU!V119 -> 0 | DV36: =IFERROR(DU36/TEMU!V25,0) -> 0 | DW36: =SHEIN!V91 -> 0 | DX36: =IFERROR(DW36/SHEIN!V20,0) -> 0 | DY36: =TK!V119 -> 0 | DZ36: =IFERROR(DY36/TK!V25,0) -> 0 | EE36: =DS36+DU36+DW36+DY36+EA36+EC36 -> 0 | EF36: =IFERROR(EE36/(DS11+DU11+DW11+DY11),0) -> 0 | EG36: =IFERROR((EE36-DP36)/DP36,0) -> 0 | EH36: =AMAZON!X259 -> 0 | EI36: =IFERROR(EH36/AMAZON!X50,0) -> 0 | EJ36: =TEMU!X119 -> 0 | EK36: =IFERROR(EJ36/TEMU!X25,0) -> 0 | EL36: =SHEIN!X91 -> 0 | EM36: =IFERROR(EL36/SHEIN!X20,0) -> 0 | EN36: =TK!X119 -> 0 | EO36: =IFERROR(EN36/TK!X25,0) -> 0 | ET36: =EH36+EJ36+EL36+EN36+EP36+ER36 -> 0 | EU36: =IFERROR(ET36/(EH11+EJ11+EL11+EN11),0) -> 0 | EV36: =IFERROR((ET36-EE36)/EE36,0) -> 0 | EW36: =AMAZON!Z259 -> 0 | EX36: =IFERROR(EW36/AMAZON!Z50,0) -> 0 | EY36: =TEMU!Z119 -> 0 | EZ36: =IFERROR(EY36/TEMU!Z25,0) -> 0 | FA36: =SHEIN!Z91 -> 0 | FB36: =IFERROR(FA36/SHEIN!Z20,0) -> 0 | FC36: =TK!Z119 -> 0 | FD36: =IFERROR(FC36/TK!Z25,0) -> 0 | FI36: =EW36+EY36+FA36+FC36+FE36+FG36 -> 0 | FJ36: =IFERROR(FI36/(EW11+EY11+FA11+FC11),0) -> 0 | FK36: =IFERROR((FI36-ET36)/ET36,0) -> 0 | FL36: =AMAZON!AB259 -> 0 | FM36: =IFERROR(FL36/AMAZON!AB50,0) -> 0 | FN36: =TEMU!AB119 -> 0 | FO36: =IFERROR(FN36/TEMU!AB25,0) -> 0 | FP36: =SHEIN!AB91 -> 0 | FQ36: =IFERROR(FP36/SHEIN!AB20,0) -> 0 | FR36: =TK!AB119 -> 0 | FS36: =IFERROR(FR36/TK!AB25,0) -> 0 | FX36: =FL36+FN36+FP36+FR36+FT36+FV36 -> 0 | FY36: =IFERROR(FX36/(FL11+FN11+FP11+FR11),0) -> 0 | FZ36: =IFERROR((FX36-FI36)/FI36,0) -> 0 | GA36: =AMAZON!AD259 -> 0 | GB36: =IFERROR(GA36/AMAZON!AD50,0) -> 0 | GC36: =TEMU!AD119 -> 0 | GD36: =IFERROR(GC36/TEMU!AD25,0) -> 0 | GE36: =SHEIN!AD91 -> 0 | GF36: =IFERROR(GE36/SHEIN!AD20,0) -> 0 | GG36: =TK!AD119 -> 0 | GH36: =IFERROR(GG36/TK!AD25,0) -> 0 | GM36: =GA36+GC36+GE36+GG36+GI36+GK36 -> 0 | GN36: =IFERROR(GM36/(GA11+GC11+GE11+GG11),0) -> 0 | GO36: =IFERROR((GM36-FX36)/FX36,0) -> 0
A37: 其他项目 | B37: 快递罚款 | C37: 元 | D37: =AMAZON!F268 -> 0 | E37: =IFERROR(D37/AMAZON!F50,0) -> 0 | F37: =TEMU!F123 -> 0 | G37: =IFERROR(F37/TEMU!F25,0) -> 0 | H37: =SHEIN!F94 -> 0 | I37: =IFERROR(H37/SHEIN!F20,0) -> 0 | J37: =TK!F123 -> 0 | K37: =IFERROR(J37/TK!F25,0) -> 0 | P37: =D37+F37+H37+J37+L37+N37 -> 0 | Q37: =IFERROR(P37/(D11+F11+H11+J11),0) -> 0 | R37: =AMAZON!H268 -> 0 | S37: =IFERROR(R37/AMAZON!H50,0) -> 0 | T37: =TEMU!H123 -> 0 | U37: =IFERROR(T37/TEMU!H25,0) -> 0 | V37: =SHEIN!H94 -> 0 | W37: =IFERROR(V37/SHEIN!H20,0) -> 0 | X37: =TK!H123 -> 0 | Y37: =IFERROR(X37/TK!H25,0) -> 0 | AD37: =R37+T37+V37+X37+Z37+AB37 -> 0 | AE37: =IFERROR(AD37/(R11+T11+V11+X11),0) -> 0 | AG37: =AMAZON!J268 -> 0 | AH37: =IFERROR(AG37/AMAZON!J50,0) -> 0 | AI37: =TEMU!J123 -> 0 | AJ37: =IFERROR(AI37/TEMU!J25,0) -> 0 | AK37: =SHEIN!J94 -> 0 | AL37: =IFERROR(AK37/SHEIN!J20,0) -> 0 | AM37: =TK!J123 -> 0 | AN37: =IFERROR(AM37/TK!J25,0) -> 0 | AS37: =AG37+AI37+AK37+AM37+AO37+AQ37 -> 0 | AT37: =IFERROR(AS37/(AG11+AI11+AK11+AM11),0) -> 0 | AU37: =IFERROR((AS37-AD37)/AD37,0) -> 0 | AV37: =AMAZON!L268 -> 0 | AW37: =IFERROR(AV37/AMAZON!L50,0) -> 0 | AX37: =TEMU!L123 -> 0 | AY37: =IFERROR(AX37/TEMU!L25,0) -> 0 | AZ37: =SHEIN!L94 -> 0 | BA37: =IFERROR(AZ37/SHEIN!L20,0) -> 0 | BB37: =TK!L123 -> 0 | BC37: =IFERROR(BB37/TK!L25,0) -> 0 | BH37: =AV37+AX37+AZ37+BB37+BD37+BF37 -> 0 | BI37: =IFERROR(BH37/(AV11+AX11+AZ11+BB11),0) -> 0 | BJ37: =IFERROR((BH37-AS37)/AS37,0) -> 0 | BK37: =AMAZON!N268 -> 0 | BL37: =IFERROR(BK37/AMAZON!N50,0) -> 0 | BM37: =TEMU!N123 -> 0 | BN37: =IFERROR(BM37/TEMU!N25,0) -> 0 | BO37: =SHEIN!N94 -> 0 | BP37: =IFERROR(BO37/SHEIN!N20,0) -> 0 | BQ37: =TK!N123 -> 0 | BR37: =IFERROR(BQ37/TK!N25,0) -> 0 | BW37: =BK37+BM37+BO37+BQ37+BS37+BU37 -> 0 | BX37: =IFERROR(BW37/(BK11+BM11+BO11+BQ11),0) -> 0 | BY37: =IFERROR((BW37-BH37)/BH37,0) -> 0 | BZ37: =AMAZON!P268 -> 0 | CA37: =IFERROR(BZ37/AMAZON!P50,0) -> 0 | CB37: =TEMU!P123 -> 0 | CC37: =IFERROR(CB37/TEMU!P25,0) -> 0 | CD37: =SHEIN!P94 -> 0 | CE37: =IFERROR(CD37/SHEIN!P20,0) -> 0 | CF37: =TK!P123 -> 0 | CG37: =IFERROR(CF37/TK!P25,0) -> 0 | CL37: =BZ37+CB37+CD37+CF37+CH37+CJ37 -> 0 | CM37: =IFERROR(CL37/(BZ11+CB11+CD11+CF11),0) -> 0 | CN37: =IFERROR((CL37-BW37)/BW37,0) -> 0 | CO37: =AMAZON!R268 -> 0 | CP37: =IFERROR(CO37/AMAZON!R50,0) -> 0 | CQ37: =TEMU!R123 -> 0 | CR37: =IFERROR(CQ37/TEMU!R25,0) -> 0 | CS37: =SHEIN!R94 -> 0 | CT37: =IFERROR(CS37/SHEIN!R20,0) -> 0 | CU37: =TK!R123 -> 0 | CV37: =IFERROR(CU37/TK!R25,0) -> 0 | DA37: =CO37+CQ37+CS37+CU37+CW37+CY37 -> 0 | DB37: =IFERROR(DA37/(CO11+CQ11+CS11+CU11),0) -> 0 | DC37: =IFERROR((DA37-CL37)/CL37,0) -> 0 | DD37: =AMAZON!T268 -> 0 | DE37: =IFERROR(DD37/AMAZON!T50,0) -> 0 | DF37: =TEMU!T123 -> 0 | DG37: =IFERROR(DF37/TEMU!T25,0) -> 0 | DH37: =SHEIN!T94 -> 0 | DI37: =IFERROR(DH37/SHEIN!T20,0) -> 0 | DJ37: =TK!T123 -> 0 | DK37: =IFERROR(DJ37/TK!T25,0) -> 0 | DP37: =DD37+DF37+DH37+DJ37+DL37+DN37 -> 0 | DQ37: =IFERROR(DP37/(DD11+DF11+DH11+DJ11),0) -> 0 | DR37: =IFERROR((DP37-DA37)/DA37,0) -> 0 | DS37: =AMAZON!V268 -> 0 | DT37: =IFERROR(DS37/AMAZON!V50,0) -> 0 | DU37: =TEMU!V123 -> 0 | DV37: =IFERROR(DU37/TEMU!V25,0) -> 0 | DW37: =SHEIN!V94 -> 0 | DX37: =IFERROR(DW37/SHEIN!V20,0) -> 0 | DY37: =TK!V123 -> 0 | DZ37: =IFERROR(DY37/TK!V25,0) -> 0 | EE37: =DS37+DU37+DW37+DY37+EA37+EC37 -> 0 | EF37: =IFERROR(EE37/(DS11+DU11+DW11+DY11),0) -> 0 | EG37: =IFERROR((EE37-DP37)/DP37,0) -> 0 | EH37: =AMAZON!X268 -> 0 | EI37: =IFERROR(EH37/AMAZON!X50,0) -> 0 | EJ37: =TEMU!X123 -> 0 | EK37: =IFERROR(EJ37/TEMU!X25,0) -> 0 | EL37: =SHEIN!X94 -> 0 | EM37: =IFERROR(EL37/SHEIN!X20,0) -> 0 | EN37: =TK!X123 -> 0 | EO37: =IFERROR(EN37/TK!X25,0) -> 0 | ET37: =EH37+EJ37+EL37+EN37+EP37+ER37 -> 0 | EU37: =IFERROR(ET37/(EH11+EJ11+EL11+EN11),0) -> 0 | EV37: =IFERROR((ET37-EE37)/EE37,0) -> 0 | EW37: =AMAZON!Z268 -> 0 | EX37: =IFERROR(EW37/AMAZON!Z50,0) -> 0 | EY37: =TEMU!Z123 -> 0 | EZ37: =IFERROR(EY37/TEMU!Z25,0) -> 0 | FA37: =SHEIN!Z94 -> 0 | FB37: =IFERROR(FA37/SHEIN!Z20,0) -> 0 | FC37: =TK!Z123 -> 0 | FD37: =IFERROR(FC37/TK!Z25,0) -> 0 | FI37: =EW37+EY37+FA37+FC37+FE37+FG37 -> 0 | FJ37: =IFERROR(FI37/(EW11+EY11+FA11+FC11),0) -> 0 | FK37: =IFERROR((FI37-ET37)/ET37,0) -> 0 | FL37: =AMAZON!AB268 -> 0 | FM37: =IFERROR(FL37/AMAZON!AB50,0) -> 0 | FN37: =TEMU!AB123 -> 0 | FO37: =IFERROR(FN37/TEMU!AB25,0) -> 0 | FP37: =SHEIN!AB94 -> 0 | FQ37: =IFERROR(FP37/SHEIN!AB20,0) -> 0 | FR37: =TK!AB123 -> 0 | FS37: =IFERROR(FR37/TK!AB25,0) -> 0 | FX37: =FL37+FN37+FP37+FR37+FT37+FV37 -> 0 | FY37: =IFERROR(FX37/(FL11+FN11+FP11+FR11),0) -> 0 | FZ37: =IFERROR((FX37-FI37)/FI37,0) -> 0 | GA37: =AMAZON!AD268 -> 0 | GB37: =IFERROR(GA37/AMAZON!AD50,0) -> 0 | GC37: =TEMU!AD123 -> 0 | GD37: =IFERROR(GC37/TEMU!AD25,0) -> 0 | GE37: =SHEIN!AD94 -> 0 | GF37: =IFERROR(GE37/SHEIN!AD20,0) -> 0 | GG37: =TK!AD123 -> 0 | GH37: =IFERROR(GG37/TK!AD25,0) -> 0 | GM37: =GA37+GC37+GE37+GG37+GI37+GK37 -> 0 | GN37: =IFERROR(GM37/(GA11+GC11+GE11+GG11),0) -> 0 | GO37: =IFERROR((GM37-FX37)/FX37,0) -> 0
A38: 其他项目 | B38: 退税收入 | C38: 元 | D38: =AMAZON!F277 -> 0 | E38: =IFERROR(D38/AMAZON!F50,0) -> 0 | F38: =TEMU!F127 -> 0 | G38: =IFERROR(F38/TEMU!F25,0) -> 0 | H38: =SHEIN!F97 -> 0 | I38: =IFERROR(H38/SHEIN!F20,0) -> 0 | J38: =TK!F127 -> 0 | K38: =IFERROR(J38/TK!F25,0) -> 0 | P38: =D38+F38+H38+J38+L38+N38 -> 0 | Q38: =IFERROR(P38/(D11+F11+H11+J11),0) -> 0 | R38: =AMAZON!H277 -> 0 | S38: =IFERROR(R38/AMAZON!H50,0) -> 0 | T38: =TEMU!H127 -> 0 | U38: =IFERROR(T38/TEMU!H25,0) -> 0 | V38: =SHEIN!H97 -> 0 | W38: =IFERROR(V38/SHEIN!H20,0) -> 0 | X38: =TK!H127 -> 0 | Y38: =IFERROR(X38/TK!H25,0) -> 0 | AD38: =R38+T38+V38+X38+Z38+AB38 -> 0 | AE38: =IFERROR(AD38/(R11+T11+V11+X11),0) -> 0 | AG38: =AMAZON!J277 -> 0 | AH38: =IFERROR(AG38/AMAZON!J50,0) -> 0 | AI38: =TEMU!J127 -> 0 | AJ38: =IFERROR(AI38/TEMU!J25,0) -> 0 | AK38: =SHEIN!J97 -> 0 | AL38: =IFERROR(AK38/SHEIN!J20,0) -> 0 | AM38: =TK!J127 -> 0 | AN38: =IFERROR(AM38/TK!J25,0) -> 0 | AS38: =AG38+AI38+AK38+AM38+AO38+AQ38 -> 0 | AT38: =IFERROR(AS38/(AG11+AI11+AK11+AM11),0) -> 0 | AU38: =IFERROR((AS38-AD38)/AD38,0) -> 0 | AV38: =AMAZON!L277 -> 0 | AW38: =IFERROR(AV38/AMAZON!L50,0) -> 0 | AX38: =TEMU!L127 -> 0 | AY38: =IFERROR(AX38/TEMU!L25,0) -> 0 | AZ38: =SHEIN!L97 -> 0 | BA38: =IFERROR(AZ38/SHEIN!L20,0) -> 0 | BB38: =TK!L127 -> 0 | BC38: =IFERROR(BB38/TK!L25,0) -> 0 | BH38: =AV38+AX38+AZ38+BB38+BD38+BF38 -> 0 | BI38: =IFERROR(BH38/(AV11+AX11+AZ11+BB11),0) -> 0 | BJ38: =IFERROR((BH38-AS38)/AS38,0) -> 0 | BK38: =AMAZON!N277 -> 0 | BL38: =IFERROR(BK38/AMAZON!N50,0) -> 0 | BM38: =TEMU!N127 -> 0 | BN38: =IFERROR(BM38/TEMU!N25,0) -> 0 | BO38: =SHEIN!N97 -> 0 | BP38: =IFERROR(BO38/SHEIN!N20,0) -> 0 | BQ38: =TK!N127 -> 0 | BR38: =IFERROR(BQ38/TK!N25,0) -> 0 | BW38: =BK38+BM38+BO38+BQ38+BS38+BU38 -> 0 | BX38: =IFERROR(BW38/(BK11+BM11+BO11+BQ11),0) -> 0 | BY38: =IFERROR((BW38-BH38)/BH38,0) -> 0 | BZ38: =AMAZON!P277 -> 0 | CA38: =IFERROR(BZ38/AMAZON!P50,0) -> 0 | CB38: =TEMU!P127 -> 0 | CC38: =IFERROR(CB38/TEMU!P25,0) -> 0 | CD38: =SHEIN!P97 -> 0 | CE38: =IFERROR(CD38/SHEIN!P20,0) -> 0 | CF38: =TK!P127 -> 0 | CG38: =IFERROR(CF38/TK!P25,0) -> 0 | CL38: =BZ38+CB38+CD38+CF38+CH38+CJ38 -> 0 | CM38: =IFERROR(CL38/(BZ11+CB11+CD11+CF11),0) -> 0 | CN38: =IFERROR((CL38-BW38)/BW38,0) -> 0 | CO38: =AMAZON!R277 -> 0 | CP38: =IFERROR(CO38/AMAZON!R50,0) -> 0 | CQ38: =TEMU!R127 -> 0 | CR38: =IFERROR(CQ38/TEMU!R25,0) -> 0 | CS38: =SHEIN!R97 -> 0 | CT38: =IFERROR(CS38/SHEIN!R20,0) -> 0 | CU38: =TK!R127 -> 0 | CV38: =IFERROR(CU38/TK!R25,0) -> 0 | DA38: =CO38+CQ38+CS38+CU38+CW38+CY38 -> 0 | DB38: =IFERROR(DA38/(CO11+CQ11+CS11+CU11),0) -> 0 | DC38: =IFERROR((DA38-CL38)/CL38,0) -> 0 | DD38: =AMAZON!T277 -> 0 | DE38: =IFERROR(DD38/AMAZON!T50,0) -> 0 | DF38: =TEMU!T127 -> 0 | DG38: =IFERROR(DF38/TEMU!T25,0) -> 0 | DH38: =SHEIN!T97 -> 0 | DI38: =IFERROR(DH38/SHEIN!T20,0) -> 0 | DJ38: =TK!T127 -> 0 | DK38: =IFERROR(DJ38/TK!T25,0) -> 0 | DP38: =DD38+DF38+DH38+DJ38+DL38+DN38 -> 0 | DQ38: =IFERROR(DP38/(DD11+DF11+DH11+DJ11),0) -> 0 | DR38: =IFERROR((DP38-DA38)/DA38,0) -> 0 | DS38: =AMAZON!V277 -> 0 | DT38: =IFERROR(DS38/AMAZON!V50,0) -> 0 | DU38: =TEMU!V127 -> 0 | DV38: =IFERROR(DU38/TEMU!V25,0) -> 0 | DW38: =SHEIN!V97 -> 0 | DX38: =IFERROR(DW38/SHEIN!V20,0) -> 0 | DY38: =TK!V127 -> 0 | DZ38: =IFERROR(DY38/TK!V25,0) -> 0 | EE38: =DS38+DU38+DW38+DY38+EA38+EC38 -> 0 | EF38: =IFERROR(EE38/(DS11+DU11+DW11+DY11),0) -> 0 | EG38: =IFERROR((EE38-DP38)/DP38,0) -> 0 | EH38: =AMAZON!X277 -> 0 | EI38: =IFERROR(EH38/AMAZON!X50,0) -> 0 | EJ38: =TEMU!X127 -> 0 | EK38: =IFERROR(EJ38/TEMU!X25,0) -> 0 | EL38: =SHEIN!X97 -> 0 | EM38: =IFERROR(EL38/SHEIN!X20,0) -> 0 | EN38: =TK!X127 -> 0 | EO38: =IFERROR(EN38/TK!X25,0) -> 0 | ET38: =EH38+EJ38+EL38+EN38+EP38+ER38 -> 0 | EU38: =IFERROR(ET38/(EH11+EJ11+EL11+EN11),0) -> 0 | EV38: =IFERROR((ET38-EE38)/EE38,0) -> 0 | EW38: =AMAZON!Z277 -> 0 | EX38: =IFERROR(EW38/AMAZON!Z50,0) -> 0 | EY38: =TEMU!Z127 -> 0 | EZ38: =IFERROR(EY38/TEMU!Z25,0) -> 0 | FA38: =SHEIN!Z97 -> 0 | FB38: =IFERROR(FA38/SHEIN!Z20,0) -> 0 | FC38: =TK!Z127 -> 0 | FD38: =IFERROR(FC38/TK!Z25,0) -> 0 | FI38: =EW38+EY38+FA38+FC38+FE38+FG38 -> 0 | FJ38: =IFERROR(FI38/(EW11+EY11+FA11+FC11),0) -> 0 | FK38: =IFERROR((FI38-ET38)/ET38,0) -> 0 | FL38: =AMAZON!AB277 -> 0 | FM38: =IFERROR(FL38/AMAZON!AB50,0) -> 0 | FN38: =TEMU!AB127 -> 0 | FO38: =IFERROR(FN38/TEMU!AB25,0) -> 0 | FP38: =SHEIN!AB97 -> 0 | FQ38: =IFERROR(FP38/SHEIN!AB20,0) -> 0 | FR38: =TK!AB127 -> 0 | FS38: =IFERROR(FR38/TK!AB25,0) -> 0 | FX38: =FL38+FN38+FP38+FR38+FT38+FV38 -> 0 | FY38: =IFERROR(FX38/(FL11+FN11+FP11+FR11),0) -> 0 | FZ38: =IFERROR((FX38-FI38)/FI38,0) -> 0 | GA38: =AMAZON!AD277 -> 0 | GB38: =IFERROR(GA38/AMAZON!AD50,0) -> 0 | GC38: =TEMU!AD127 -> 0 | GD38: =IFERROR(GC38/TEMU!AD25,0) -> 0 | GE38: =SHEIN!AD97 -> 0 | GF38: =IFERROR(GE38/SHEIN!AD20,0) -> 0 | GG38: =TK!AD127 -> 0 | GH38: =IFERROR(GG38/TK!AD25,0) -> 0 | GM38: =GA38+GC38+GE38+GG38+GI38+GK38 -> 0 | GN38: =IFERROR(GM38/(GA11+GC11+GE11+GG11),0) -> 0 | GO38: =IFERROR((GM38-FX38)/FX38,0) -> 0
A39: 其他项目 | B39: 税金收入 | C39: 元 | D39: =AMAZON!F278 -> 0 | E39: =IFERROR(D39/AMAZON!F50,0) -> 0 | F39: =TEMU!F128 -> 0 | G39: =IFERROR(F39/TEMU!F25,0) -> 0 | H39: =SHEIN!F98 -> 0 | I39: =IFERROR(H39/SHEIN!F20,0) -> 0 | J39: =TK!F128 -> 0 | K39: =IFERROR(J39/TK!F25,0) -> 0 | P39: =D39+F39+H39+J39+L39+N39 -> 0 | Q39: =IFERROR(P39/(D11+F11+H11+J11),0) -> 0 | R39: =AMAZON!H278 -> 0 | S39: =IFERROR(R39/AMAZON!H50,0) -> 0 | T39: =TEMU!H128 -> 0 | U39: =IFERROR(T39/TEMU!H25,0) -> 0 | V39: =SHEIN!H98 -> 0 | W39: =IFERROR(V39/SHEIN!H20,0) -> 0 | X39: =TK!H128 -> 0 | Y39: =IFERROR(X39/TK!H25,0) -> 0 | AD39: =R39+T39+V39+X39+Z39+AB39 -> 0 | AE39: =IFERROR(AD39/(R11+T11+V11+X11),0) -> 0 | AG39: =AMAZON!J278 -> 0 | AH39: =IFERROR(AG39/AMAZON!J50,0) -> 0 | AI39: =TEMU!J128 -> 0 | AJ39: =IFERROR(AI39/TEMU!J25,0) -> 0 | AK39: =SHEIN!J98 -> 0 | AL39: =IFERROR(AK39/SHEIN!J20,0) -> 0 | AM39: =TK!J128 -> 0 | AN39: =IFERROR(AM39/TK!J25,0) -> 0 | AS39: =AG39+AI39+AK39+AM39+AO39+AQ39 -> 0 | AT39: =IFERROR(AS39/(AG11+AI11+AK11+AM11),0) -> 0 | AU39: =IFERROR((AS39-AD39)/AD39,0) -> 0 | AV39: =AMAZON!L278 -> 0 | AW39: =IFERROR(AV39/AMAZON!L50,0) -> 0 | AX39: =TEMU!L128 -> 0 | AY39: =IFERROR(AX39/TEMU!L25,0) -> 0 | AZ39: =SHEIN!L98 -> 0 | BA39: =IFERROR(AZ39/SHEIN!L20,0) -> 0 | BB39: =TK!L128 -> 0 | BC39: =IFERROR(BB39/TK!L25,0) -> 0 | BH39: =AV39+AX39+AZ39+BB39+BD39+BF39 -> 0 | BI39: =IFERROR(BH39/(AV11+AX11+AZ11+BB11),0) -> 0 | BJ39: =IFERROR((BH39-AS39)/AS39,0) -> 0 | BK39: =AMAZON!N278 -> 0 | BL39: =IFERROR(BK39/AMAZON!N50,0) -> 0 | BM39: =TEMU!N128 -> 0 | BN39: =IFERROR(BM39/TEMU!N25,0) -> 0 | BO39: =SHEIN!N98 -> 0 | BP39: =IFERROR(BO39/SHEIN!N20,0) -> 0 | BQ39: =TK!N128 -> 0 | BR39: =IFERROR(BQ39/TK!N25,0) -> 0 | BW39: =BK39+BM39+BO39+BQ39+BS39+BU39 -> 0 | BX39: =IFERROR(BW39/(BK11+BM11+BO11+BQ11),0) -> 0 | BY39: =IFERROR((BW39-BH39)/BH39,0) -> 0 | BZ39: =AMAZON!P278 -> 0 | CA39: =IFERROR(BZ39/AMAZON!P50,0) -> 0 | CB39: =TEMU!P128 -> 0 | CC39: =IFERROR(CB39/TEMU!P25,0) -> 0 | CD39: =SHEIN!P98 -> 0 | CE39: =IFERROR(CD39/SHEIN!P20,0) -> 0 | CF39: =TK!P128 -> 0 | CG39: =IFERROR(CF39/TK!P25,0) -> 0 | CL39: =BZ39+CB39+CD39+CF39+CH39+CJ39 -> 0 | CM39: =IFERROR(CL39/(BZ11+CB11+CD11+CF11),0) -> 0 | CN39: =IFERROR((CL39-BW39)/BW39,0) -> 0 | CO39: =AMAZON!R278 -> 0 | CP39: =IFERROR(CO39/AMAZON!R50,0) -> 0 | CQ39: =TEMU!R128 -> 0 | CR39: =IFERROR(CQ39/TEMU!R25,0) -> 0 | CS39: =SHEIN!R98 -> 0 | CT39: =IFERROR(CS39/SHEIN!R20,0) -> 0 | CU39: =TK!R128 -> 0 | CV39: =IFERROR(CU39/TK!R25,0) -> 0 | DA39: =CO39+CQ39+CS39+CU39+CW39+CY39 -> 0 | DB39: =IFERROR(DA39/(CO11+CQ11+CS11+CU11),0) -> 0 | DC39: =IFERROR((DA39-CL39)/CL39,0) -> 0 | DD39: =AMAZON!T278 -> 0 | DE39: =IFERROR(DD39/AMAZON!T50,0) -> 0 | DF39: =TEMU!T128 -> 0 | DG39: =IFERROR(DF39/TEMU!T25,0) -> 0 | DH39: =SHEIN!T98 -> 0 | DI39: =IFERROR(DH39/SHEIN!T20,0) -> 0 | DJ39: =TK!T128 -> 0 | DK39: =IFERROR(DJ39/TK!T25,0) -> 0 | DP39: =DD39+DF39+DH39+DJ39+DL39+DN39 -> 0 | DQ39: =IFERROR(DP39/(DD11+DF11+DH11+DJ11),0) -> 0 | DR39: =IFERROR((DP39-DA39)/DA39,0) -> 0 | DS39: =AMAZON!V278 -> 0 | DT39: =IFERROR(DS39/AMAZON!V50,0) -> 0 | DU39: =TEMU!V128 -> 0 | DV39: =IFERROR(DU39/TEMU!V25,0) -> 0 | DW39: =SHEIN!V98 -> 0 | DX39: =IFERROR(DW39/SHEIN!V20,0) -> 0 | DY39: =TK!V128 -> 0 | DZ39: =IFERROR(DY39/TK!V25,0) -> 0 | EE39: =DS39+DU39+DW39+DY39+EA39+EC39 -> 0 | EF39: =IFERROR(EE39/(DS11+DU11+DW11+DY11),0) -> 0 | EG39: =IFERROR((EE39-DP39)/DP39,0) -> 0 | EH39: =AMAZON!X278 -> 0 | EI39: =IFERROR(EH39/AMAZON!X50,0) -> 0 | EJ39: =TEMU!X128 -> 0 | EK39: =IFERROR(EJ39/TEMU!X25,0) -> 0 | EL39: =SHEIN!X98 -> 0 | EM39: =IFERROR(EL39/SHEIN!X20,0) -> 0 | EN39: =TK!X128 -> 0 | EO39: =IFERROR(EN39/TK!X25,0) -> 0 | ET39: =EH39+EJ39+EL39+EN39+EP39+ER39 -> 0 | EU39: =IFERROR(ET39/(EH11+EJ11+EL11+EN11),0) -> 0 | EV39: =IFERROR((ET39-EE39)/EE39,0) -> 0 | EW39: =AMAZON!Z278 -> 0 | EX39: =IFERROR(EW39/AMAZON!Z50,0) -> 0 | EY39: =TEMU!Z128 -> 0 | EZ39: =IFERROR(EY39/TEMU!Z25,0) -> 0 | FA39: =SHEIN!Z98 -> 0 | FB39: =IFERROR(FA39/SHEIN!Z20,0) -> 0 | FC39: =TK!Z128 -> 0 | FD39: =IFERROR(FC39/TK!Z25,0) -> 0 | FI39: =EW39+EY39+FA39+FC39+FE39+FG39 -> 0 | FJ39: =IFERROR(FI39/(EW11+EY11+FA11+FC11),0) -> 0 | FK39: =IFERROR((FI39-ET39)/ET39,0) -> 0 | FL39: =AMAZON!AB278 -> 0 | FM39: =IFERROR(FL39/AMAZON!AB50,0) -> 0 | FN39: =TEMU!AB128 -> 0 | FO39: =IFERROR(FN39/TEMU!AB25,0) -> 0 | FP39: =SHEIN!AB98 -> 0 | FQ39: =IFERROR(FP39/SHEIN!AB20,0) -> 0 | FR39: =TK!AB128 -> 0 | FS39: =IFERROR(FR39/TK!AB25,0) -> 0 | FX39: =FL39+FN39+FP39+FR39+FT39+FV39 -> 0 | FY39: =IFERROR(FX39/(FL11+FN11+FP11+FR11),0) -> 0 | FZ39: =IFERROR((FX39-FI39)/FI39,0) -> 0 | GA39: =AMAZON!AD278 -> 0 | GB39: =IFERROR(GA39/AMAZON!AD50,0) -> 0 | GC39: =TEMU!AD128 -> 0 | GD39: =IFERROR(GC39/TEMU!AD25,0) -> 0 | GE39: =SHEIN!AD98 -> 0 | GF39: =IFERROR(GE39/SHEIN!AD20,0) -> 0 | GG39: =TK!AD128 -> 0 | GH39: =IFERROR(GG39/TK!AD25,0) -> 0 | GM39: =GA39+GC39+GE39+GG39+GI39+GK39 -> 0 | GN39: =IFERROR(GM39/(GA11+GC11+GE11+GG11),0) -> 0 | GO39: =IFERROR((GM39-FX39)/FX39,0) -> 0
A40: 其他项目 | B40: 提款手续费 | C40: 元 | D40: =AMAZON!F287 -> 0 | E40: =IFERROR(D40/AMAZON!F50,0) -> 0 | F40: =TEMU!F132 -> 0 | G40: =IFERROR(F40/TEMU!F25,0) -> 0 | H40: =SHEIN!F101 -> 0 | I40: =IFERROR(H40/SHEIN!F20,0) -> 0 | J40: =TK!F132 -> 0 | K40: =IFERROR(J40/TK!F25,0) -> 0 | P40: =D40+F40+H40+J40+L40+N40 -> 0 | Q40: =IFERROR(P40/(D11+F11+H11+J11),0) -> 0 | R40: =AMAZON!H287 -> 0 | S40: =IFERROR(R40/AMAZON!H50,0) -> 0 | T40: =TEMU!H132 -> 0 | U40: =IFERROR(T40/TEMU!H25,0) -> 0 | V40: =SHEIN!H101 -> 0 | W40: =IFERROR(V40/SHEIN!H20,0) -> 0 | X40: =TK!H132 -> 0 | Y40: =IFERROR(X40/TK!H25,0) -> 0 | AD40: =R40+T40+V40+X40+Z40+AB40 -> 0 | AE40: =IFERROR(AD40/(R11+T11+V11+X11),0) -> 0 | AG40: =AMAZON!J287 -> 0 | AH40: =IFERROR(AG40/AMAZON!J50,0) -> 0 | AI40: =TEMU!J132 -> 0 | AJ40: =IFERROR(AI40/TEMU!J25,0) -> 0 | AK40: =SHEIN!J101 -> 0 | AL40: =IFERROR(AK40/SHEIN!J20,0) -> 0 | AM40: =TK!J132 -> 0 | AN40: =IFERROR(AM40/TK!J25,0) -> 0 | AS40: =AG40+AI40+AK40+AM40+AO40+AQ40 -> 0 | AT40: =IFERROR(AS40/(AG11+AI11+AK11+AM11),0) -> 0 | AU40: =IFERROR((AS40-AD40)/AD40,0) -> 0 | AV40: =AMAZON!L287 -> 0 | AW40: =IFERROR(AV40/AMAZON!L50,0) -> 0 | AX40: =TEMU!L132 -> 0 | AY40: =IFERROR(AX40/TEMU!L25,0) -> 0 | AZ40: =SHEIN!L101 -> 0 | BA40: =IFERROR(AZ40/SHEIN!L20,0) -> 0 | BB40: =TK!L132 -> 0 | BC40: =IFERROR(BB40/TK!L25,0) -> 0 | BH40: =AV40+AX40+AZ40+BB40+BD40+BF40 -> 0 | BI40: =IFERROR(BH40/(AV11+AX11+AZ11+BB11),0) -> 0 | BJ40: =IFERROR((BH40-AS40)/AS40,0) -> 0 | BK40: =AMAZON!N287 -> 0 | BL40: =IFERROR(BK40/AMAZON!N50,0) -> 0 | BM40: =TEMU!N132 -> 0 | BN40: =IFERROR(BM40/TEMU!N25,0) -> 0 | BO40: =SHEIN!N101 -> 0 | BP40: =IFERROR(BO40/SHEIN!N20,0) -> 0 | BQ40: =TK!N132 -> 0 | BR40: =IFERROR(BQ40/TK!N25,0) -> 0 | BW40: =BK40+BM40+BO40+BQ40+BS40+BU40 -> 0 | BX40: =IFERROR(BW40/(BK11+BM11+BO11+BQ11),0) -> 0 | BY40: =IFERROR((BW40-BH40)/BH40,0) -> 0 | BZ40: =AMAZON!P287 -> 0 | CA40: =IFERROR(BZ40/AMAZON!P50,0) -> 0 | CB40: =TEMU!P132 -> 0 | CC40: =IFERROR(CB40/TEMU!P25,0) -> 0 | CD40: =SHEIN!P101 -> 0 | CE40: =IFERROR(CD40/SHEIN!P20,0) -> 0 | CF40: =TK!P132 -> 0 | CG40: =IFERROR(CF40/TK!P25,0) -> 0 | CL40: =BZ40+CB40+CD40+CF40+CH40+CJ40 -> 0 | CM40: =IFERROR(CL40/(BZ11+CB11+CD11+CF11),0) -> 0 | CN40: =IFERROR((CL40-BW40)/BW40,0) -> 0 | CO40: =AMAZON!R287 -> 0 | CP40: =IFERROR(CO40/AMAZON!R50,0) -> 0 | CQ40: =TEMU!R132 -> 0 | CR40: =IFERROR(CQ40/TEMU!R25,0) -> 0 | CS40: =SHEIN!R101 -> 0 | CT40: =IFERROR(CS40/SHEIN!R20,0) -> 0 | CU40: =TK!R132 -> 0 | CV40: =IFERROR(CU40/TK!R25,0) -> 0 | DA40: =CO40+CQ40+CS40+CU40+CW40+CY40 -> 0 | DB40: =IFERROR(DA40/(CO11+CQ11+CS11+CU11),0) -> 0 | DC40: =IFERROR((DA40-CL40)/CL40,0) -> 0 | DD40: =AMAZON!T287 -> 0 | DE40: =IFERROR(DD40/AMAZON!T50,0) -> 0 | DF40: =TEMU!T132 -> 0 | DG40: =IFERROR(DF40/TEMU!T25,0) -> 0 | DH40: =SHEIN!T101 -> 0 | DI40: =IFERROR(DH40/SHEIN!T20,0) -> 0 | DJ40: =TK!T132 -> 0 | DK40: =IFERROR(DJ40/TK!T25,0) -> 0 | DP40: =DD40+DF40+DH40+DJ40+DL40+DN40 -> 0 | DQ40: =IFERROR(DP40/(DD11+DF11+DH11+DJ11),0) -> 0 | DR40: =IFERROR((DP40-DA40)/DA40,0) -> 0 | DS40: =AMAZON!V287 -> 0 | DT40: =IFERROR(DS40/AMAZON!V50,0) -> 0 | DU40: =TEMU!V132 -> 0 | DV40: =IFERROR(DU40/TEMU!V25,0) -> 0 | DW40: =SHEIN!V101 -> 0 | DX40: =IFERROR(DW40/SHEIN!V20,0) -> 0 | DY40: =TK!V132 -> 0 | DZ40: =IFERROR(DY40/TK!V25,0) -> 0 | EE40: =DS40+DU40+DW40+DY40+EA40+EC40 -> 0 | EF40: =IFERROR(EE40/(DS11+DU11+DW11+DY11),0) -> 0 | EG40: =IFERROR((EE40-DP40)/DP40,0) -> 0 | EH40: =AMAZON!X287 -> 0 | EI40: =IFERROR(EH40/AMAZON!X50,0) -> 0 | EJ40: =TEMU!X132 -> 0 | EK40: =IFERROR(EJ40/TEMU!X25,0) -> 0 | EL40: =SHEIN!X101 -> 0 | EM40: =IFERROR(EL40/SHEIN!X20,0) -> 0 | EN40: =TK!X132 -> 0 | EO40: =IFERROR(EN40/TK!X25,0) -> 0 | ET40: =EH40+EJ40+EL40+EN40+EP40+ER40 -> 0 | EU40: =IFERROR(ET40/(EH11+EJ11+EL11+EN11),0) -> 0 | EV40: =IFERROR((ET40-EE40)/EE40,0) -> 0 | EW40: =AMAZON!Z287 -> 0 | EX40: =IFERROR(EW40/AMAZON!Z50,0) -> 0 | EY40: =TEMU!Z132 -> 0 | EZ40: =IFERROR(EY40/TEMU!Z25,0) -> 0 | FA40: =SHEIN!Z101 -> 0 | FB40: =IFERROR(FA40/SHEIN!Z20,0) -> 0 | FC40: =TK!Z132 -> 0 | FD40: =IFERROR(FC40/TK!Z25,0) -> 0 | FI40: =EW40+EY40+FA40+FC40+FE40+FG40 -> 0 | FJ40: =IFERROR(FI40/(EW11+EY11+FA11+FC11),0) -> 0 | FK40: =IFERROR((FI40-ET40)/ET40,0) -> 0 | FL40: =AMAZON!AB287 -> 0 | FM40: =IFERROR(FL40/AMAZON!AB50,0) -> 0 | FN40: =TEMU!AB132 -> 0 | FO40: =IFERROR(FN40/TEMU!AB25,0) -> 0 | FP40: =SHEIN!AB101 -> 0 | FQ40: =IFERROR(FP40/SHEIN!AB20,0) -> 0 | FR40: =TK!AB132 -> 0 | FS40: =IFERROR(FR40/TK!AB25,0) -> 0 | FX40: =FL40+FN40+FP40+FR40+FT40+FV40 -> 0 | FY40: =IFERROR(FX40/(FL11+FN11+FP11+FR11),0) -> 0 | FZ40: =IFERROR((FX40-FI40)/FI40,0) -> 0 | GA40: =AMAZON!AD287 -> 0 | GB40: =IFERROR(GA40/AMAZON!AD50,0) -> 0 | GC40: =TEMU!AD132 -> 0 | GD40: =IFERROR(GC40/TEMU!AD25,0) -> 0 | GE40: =SHEIN!AD101 -> 0 | GF40: =IFERROR(GE40/SHEIN!AD20,0) -> 0 | GG40: =TK!AD132 -> 0 | GH40: =IFERROR(GG40/TK!AD25,0) -> 0 | GM40: =GA40+GC40+GE40+GG40+GI40+GK40 -> 0 | GN40: =IFERROR(GM40/(GA11+GC11+GE11+GG11),0) -> 0 | GO40: =IFERROR((GM40-FX40)/FX40,0) -> 0
A41: 边界利润率 | D41: =IFERROR(AMAZON!F296,"") -> 0 | F41: =IFERROR(TEMU!F136,"") -> 0 | H41: =IFERROR(SHEIN!F104,"") -> 0 | J41: =IFERROR(TK!F136,"") -> 0 | P41: =D41+F41+H41+J41+L41+N41 -> 0 | Q41: =IFERROR(P41/(D11+F11+H11+J11),0) -> 0 | R41: =IFERROR(AMAZON!H296,"") -> 0 | T41: =IFERROR(TEMU!H136,"") -> 0 | V41: =IFERROR(SHEIN!H104,"") -> 0 | X41: =IFERROR(TK!H136,"") -> 0 | AD41: =R41+T41+V41+X41+Z41+AB41 -> 0 | AE41: =IFERROR(AD41/(R11+T11+V11+X11),0) -> 0 | AG41: =IFERROR(AMAZON!J296,"") -> 0 | AI41: =IFERROR(TEMU!J136,"") -> 0 | AK41: =IFERROR(SHEIN!J104,"") -> 0 | AM41: =IFERROR(TK!J136,"") -> 0 | AS41: =AG41+AI41+AK41+AM41+AO41+AQ41 -> 0 | AT41: =IFERROR(AS41/(AG11+AI11+AK11+AM11),0) -> 0 | AU41: =IFERROR((AS41-AD41)/AD41,0) -> 0 | AV41: =IFERROR(AMAZON!L296,"") -> 0 | AX41: =IFERROR(TEMU!L136,"") -> 0 | AZ41: =IFERROR(SHEIN!L104,"") -> 0 | BB41: =IFERROR(TK!L136,"") -> 0 | BH41: =AV41+AX41+AZ41+BB41+BD41+BF41 -> 0 | BI41: =IFERROR(BH41/(AV11+AX11+AZ11+BB11),0) -> 0 | BJ41: =IFERROR((BH41-AS41)/AS41,0) -> 0 | BK41: =IFERROR(AMAZON!N296,"") -> 0 | BM41: =IFERROR(TEMU!N136,"") -> 0 | BO41: =IFERROR(SHEIN!N104,"") -> 0 | BQ41: =IFERROR(TK!N136,"") -> 0 | BW41: =BK41+BM41+BO41+BQ41+BS41+BU41 -> 0 | BX41: =IFERROR(BW41/(BK11+BM11+BO11+BQ11),0) -> 0 | BY41: =IFERROR((BW41-BH41)/BH41,0) -> 0 | BZ41: =IFERROR(AMAZON!P296,"") -> 0 | CB41: =IFERROR(TEMU!P136,"") -> 0 | CD41: =IFERROR(SHEIN!P104,"") -> 0 | CF41: =IFERROR(TK!P136,"") -> 0 | CL41: =BZ41+CB41+CD41+CF41+CH41+CJ41 -> 0 | CM41: =IFERROR(CL41/(BZ11+CB11+CD11+CF11),0) -> 0 | CN41: =IFERROR((CL41-BW41)/BW41,0) -> 0 | CO41: =IFERROR(AMAZON!R296,"") -> 0 | CQ41: =IFERROR(TEMU!R136,"") -> 0 | CS41: =IFERROR(SHEIN!R104,"") -> 0 | CU41: =IFERROR(TK!R136,"") -> 0 | DA41: =CO41+CQ41+CS41+CU41+CW41+CY41 -> 0 | DB41: =IFERROR(DA41/(CO11+CQ11+CS11+CU11),0) -> 0 | DC41: =IFERROR((DA41-CL41)/CL41,0) -> 0 | DD41: =IFERROR(AMAZON!T296,"") -> 0 | DF41: =IFERROR(TEMU!T136,"") -> 0 | DH41: =IFERROR(SHEIN!T104,"") -> 0 | DJ41: =IFERROR(TK!T136,"") -> 0 | DP41: =DD41+DF41+DH41+DJ41+DL41+DN41 -> 0 | DQ41: =IFERROR(DP41/(DD11+DF11+DH11+DJ11),0) -> 0 | DR41: =IFERROR((DP41-DA41)/DA41,0) -> 0 | DS41: =IFERROR(AMAZON!V296,"") -> 0 | DU41: =IFERROR(TEMU!V136,"") -> 0 | DW41: =IFERROR(SHEIN!V104,"") -> 0 | DY41: =IFERROR(TK!V136,"") -> 0 | EE41: =DS41+DU41+DW41+DY41+EA41+EC41 -> 0 | EF41: =IFERROR(EE41/(DS11+DU11+DW11+DY11),0) -> 0 | EG41: =IFERROR((EE41-DP41)/DP41,0) -> 0 | EH41: =IFERROR(AMAZON!X296,"") -> 0 | EJ41: =IFERROR(TEMU!X136,"") -> 0 | EL41: =IFERROR(SHEIN!X104,"") -> 0 | EN41: =IFERROR(TK!X136,"") -> 0 | ET41: =EH41+EJ41+EL41+EN41+EP41+ER41 -> 0 | EU41: =IFERROR(ET41/(EH11+EJ11+EL11+EN11),0) -> 0 | EV41: =IFERROR((ET41-EE41)/EE41,0) -> 0 | EW41: =IFERROR(AMAZON!Z296,"") -> 0 | EY41: =IFERROR(TEMU!Z136,"") -> 0 | FA41: =IFERROR(SHEIN!Z104,"") -> 0 | FC41: =IFERROR(TK!Z136,"") -> 0 | FI41: =EW41+EY41+FA41+FC41+FE41+FG41 -> 0 | FJ41: =IFERROR(FI41/(EW11+EY11+FA11+FC11),0) -> 0 | FK41: =IFERROR((FI41-ET41)/ET41,0) -> 0 | FL41: =IFERROR(AMAZON!AB296,"") -> 0 | FN41: =IFERROR(TEMU!AB136,"") -> 0 | FP41: =IFERROR(SHEIN!AB104,"") -> 0 | FR41: =IFERROR(TK!AB136,"") -> 0 | FX41: =FL41+FN41+FP41+FR41+FT41+FV41 -> 0 | FY41: =IFERROR(FX41/(FL11+FN11+FP11+FR11),0) -> 0 | FZ41: =IFERROR((FX41-FI41)/FI41,0) -> 0 | GA41: =IFERROR(AMAZON!AD296,"") -> 0 | GC41: =IFERROR(TEMU!AD136,"") -> 0 | GE41: =IFERROR(SHEIN!AD104,"") -> 0 | GG41: =IFERROR(TK!AD136,"") -> 0 | GM41: =GA41+GC41+GE41+GG41+GI41+GK41 -> 0 | GN41: =IFERROR(GM41/(GA11+GC11+GE11+GG11),0) -> 0 | GO41: =IFERROR((GM41-FX41)/FX41,0) -> 0

Sheet AMAZON
A1: 2026年AMAZON平台边界利润分析
F2: 全年 | H2: 1月 | J2: 2月 | L2: 3月 | N2: 4月 | P2: 5月 | R2: 6月 | T2: 7月 | V2: 8月 | X2: 9月 | Z2: 10月 | AB2: 11月 | AD2: 12月 | AF2: 环比变化
A3: 科目 | B3: 细分科目 | C3: 店铺 | D3: 站点 | E3: 单位 | F3: 金额 | G3: 占比 | H3: 金额 | I3: 占比 | J3: 金额 | K3: 占比 | L3: 金额 | M3: 占比 | N3: 金额 | O3: 占比 | P3: 金额 | Q3: 占比 | R3: 金额 | S3: 占比 | T3: 金额 | U3: 占比 | V3: 金额 | W3: 占比 | X3: 金额 | Y3: 占比 | Z3: 金额 | AA3: 占比 | AB3: 金额 | AC3: 占比 | AD3: 金额 | AE3: 占比 | AF3: 2月环比% | AG3: 3月环比% | AH3: 4月环比% | AI3: 5月环比% | AJ3: 6月环比% | AK3: 7月环比% | AL3: 8月环比% | AM3: 9月环比% | AN3: 10月环比% | AO3: 11月环比% | AP3: 12月环比%
A4: 净销售量 | C4: 合计 | E4: 件 | F4: =H4+J4+L4+N4+P4+R4+T4+V4+X4+Z4+AB4+AD4 -> 0 | G4: =IFERROR(F4/#REF!,"") | H4: =H13+H22 -> 0 | I4: =IFERROR(H4/#REF!,"") | J4: =J13+J22 -> 0 | K4: =IFERROR(J4/#REF!,"") | L4: =L13+L22 -> 0 | M4: =IFERROR(L4/#REF!,"") | N4: =N13+N22 -> 0 | O4: =IFERROR(N4/#REF!,"") | P4: =P13+P22 -> 0 | Q4: =IFERROR(P4/#REF!,"") | R4: =R13+R22 -> 0 | S4: =IFERROR(R4/#REF!,"") | T4: =T13+T22 -> 0 | U4: =IFERROR(T4/#REF!,"") | V4: =V13+V22 -> 0 | W4: =IFERROR(V4/#REF!,"") | X4: =X13+X22 -> 0 | Y4: =IFERROR(X4/#REF!,"") | Z4: =Z13+Z22 -> 0 | AA4: =IFERROR(Z4/#REF!,"") | AB4: =AB13+AB22 -> 0 | AC4: =IFERROR(AB4/#REF!,"") | AD4: =AD13+AD22 -> 0 | AE4: =IFERROR(AD4/#REF!,"") | AF4: =IFERROR((J4-H4)/H4,"") | AG4: =IFERROR((L4-J4)/J4,"") | AH4: =IFERROR((N4-L4)/L4,"") | AI4: =IFERROR((P4-N4)/N4,"") | AJ4: =IFERROR((R4-P4)/P4,"") | AK4: =IFERROR((T4-R4)/R4,"") | AL4: =IFERROR((V4-T4)/T4,"") | AM4: =IFERROR((X4-V4)/V4,"") | AN4: =IFERROR((Z4-X4)/X4,"") | AO4: =IFERROR((AB4-Z4)/Z4,"") | AP4: =IFERROR((AD4-AB4)/AB4,"")
A5: 净销售量 | C5: 特米 | D5: UK | E5: 件 | F5: =H5+J5+L5+N5+P5+R5+T5+V5+X5+Z5+AB5+AD5 -> 0 | G5: =IFERROR(F5/F$4,0) -> 0 | H5: =H14+H23 -> 0 | I5: =IFERROR(H5/H$4,"")
A6: 净销售量 | C6: 英茂 | D6: DE | E6: 件 | F6: =H6+J6+L6+N6+P6+R6+T6+V6+X6+Z6+AB6+AD6 -> 0 | G6: =IFERROR(F6/F$4,0) -> 0 | H6: =H15+H24 -> 0 | I6: =IFERROR(H6/H$4,"")
A7: 净销售量 | C7: 英茂 | D7: UK | E7: 件 | F7: =H7+J7+L7+N7+P7+R7+T7+V7+X7+Z7+AB7+AD7 -> 0 | G7: =IFERROR(F7/F$4,0) -> 0 | H7: =H16+H25 -> 0 | I7: =IFERROR(H7/H$4,"")
A8: 净销售量 | C8: 字同 | D8: UK | E8: 件 | F8: =H8+J8+L8+N8+P8+R8+T8+V8+X8+Z8+AB8+AD8 -> 0 | G8: =IFERROR(F8/F$4,0) -> 0 | H8: =H17+H26 -> 0 | I8: =IFERROR(H8/H$4,"")
A9: 净销售量 | C9: 起的快 | D9: UK | E9: 件 | F9: =H9+J9+L9+N9+P9+R9+T9+V9+X9+Z9+AB9+AD9 -> 0 | G9: =IFERROR(F9/F$4,0) -> 0 | H9: =H18+H27 -> 0 | I9: =IFERROR(H9/H$4,"")
A10: 净销售量 | C10: 昇新 | D10: UK | E10: 件 | F10: =H10+J10+L10+N10+P10+R10+T10+V10+X10+Z10+AB10+AD10 -> 0 | G10: =IFERROR(F10/F$4,0) -> 0 | H10: =H19+H28 -> 0 | I10: =IFERROR(H10/H$4,"")
A11: 净销售量 | C11: NOTTAC | D11: UK | E11: 件 | F11: =H11+J11+L11+N11+P11+R11+T11+V11+X11+Z11+AB11+AD11 -> 0 | G11: =IFERROR(F11/F$4,0) -> 0 | H11: =H20+H29 -> 0 | I11: =IFERROR(H11/H$4,"")
A12: 净销售量 | C12: Ledvia | D12: UK | E12: 件 | F12: =H12+J12+L12+N12+P12+R12+T12+V12+X12+Z12+AB12+AD12 -> 0 | G12: =IFERROR(F12/F$4,0) -> 0 | H12: =H21+H30 -> 0 | I12: =IFERROR(H12/H$4,"")
A13: 净销售量 | B13: 销售量 | D13: 合计 | E13: 件 | F13: =H13+J13+L13+N13+P13+R13+T13+V13+X13+Z13+AB13+AD13 -> 0 | G13: =IFERROR(F13/#REF!,"") | I13: =IFERROR(H13/#REF!,"") | K13: =IFERROR(J13/#REF!,"") | M13: =IFERROR(L13/#REF!,"") | O13: =IFERROR(N13/#REF!,"") | Q13: =IFERROR(P13/#REF!,"") | S13: =IFERROR(R13/#REF!,"") | U13: =IFERROR(T13/#REF!,"") | W13: =IFERROR(V13/#REF!,"") | Y13: =IFERROR(X13/#REF!,"") | AA13: =IFERROR(Z13/#REF!,"") | AC13: =IFERROR(AB13/#REF!,"") | AE13: =IFERROR(AD13/#REF!,"") | AF13: =IFERROR((J13-H13)/H13,"") | AG13: =IFERROR((L13-J13)/J13,"") | AH13: =IFERROR((N13-L13)/L13,"") | AI13: =IFERROR((P13-N13)/N13,"") | AJ13: =IFERROR((R13-P13)/P13,"") | AK13: =IFERROR((T13-R13)/R13,"") | AL13: =IFERROR((V13-T13)/T13,"") | AM13: =IFERROR((X13-V13)/V13,"") | AN13: =IFERROR((Z13-X13)/X13,"") | AO13: =IFERROR((AB13-Z13)/Z13,"")
B14: 销售量 | C14: 特米 | D14: UK | E14: 件 | F14: =H14+J14+L14+N14+P14+R14+T14+V14+X14+Z14+AB14+AD14 -> 0 | G14: =IFERROR(F14/F$13,0) -> 0 | I14: =IFERROR(H14/#REF!,"") | K14: =IFERROR(J14/#REF!,"") | M14: =IFERROR(L14/#REF!,"") | O14: =IFERROR(N14/#REF!,"") | Q14: =IFERROR(P14/#REF!,"") | S14: =IFERROR(R14/#REF!,"") | U14: =IFERROR(T14/#REF!,"") | W14: =IFERROR(V14/#REF!,"") | Y14: =IFERROR(X14/#REF!,"") | AA14: =IFERROR(Z14/#REF!,"") | AC14: =IFERROR(AB14/#REF!,"") | AE14: =IFERROR(AD14/#REF!,"") | AF14: =IFERROR((J14-H14)/H14,"") | AG14: =IFERROR((L14-J14)/J14,"") | AH14: =IFERROR((N14-L14)/L14,"") | AI14: =IFERROR((P14-N14)/N14,"") | AJ14: =IFERROR((R14-P14)/P14,"") | AK14: =IFERROR((T14-R14)/R14,"") | AL14: =IFERROR((V14-T14)/T14,"") | AM14: =IFERROR((X14-V14)/V14,"") | AN14: =IFERROR((Z14-X14)/X14,"") | AO14: =IFERROR((AB14-Z14)/Z14,"")
B15: 销售量 | C15: 英茂 | D15: DE | E15: 件 | F15: =H15+J15+L15+N15+P15+R15+T15+V15+X15+Z15+AB15+AD15 -> 0 | G15: =IFERROR(F15/F$13,0) -> 0 | I15: =IFERROR(H15/#REF!,"") | K15: =IFERROR(J15/#REF!,"") | M15: =IFERROR(L15/#REF!,"") | O15: =IFERROR(N15/#REF!,"") | Q15: =IFERROR(P15/#REF!,"") | S15: =IFERROR(R15/#REF!,"") | U15: =IFERROR(T15/#REF!,"") | W15: =IFERROR(V15/#REF!,"") | Y15: =IFERROR(X15/#REF!,"") | AA15: =IFERROR(Z15/#REF!,"") | AC15: =IFERROR(AB15/#REF!,"") | AE15: =IFERROR(AD15/#REF!,"") | AF15: =IFERROR((J15-H15)/H15,"") | AG15: =IFERROR((L15-J15)/J15,"") | AH15: =IFERROR((N15-L15)/L15,"") | AI15: =IFERROR((P15-N15)/N15,"") | AJ15: =IFERROR((R15-P15)/P15,"") | AK15: =IFERROR((T15-R15)/R15,"") | AL15: =IFERROR((V15-T15)/T15,"") | AM15: =IFERROR((X15-V15)/V15,"") | AN15: =IFERROR((Z15-X15)/X15,"") | AO15: =IFERROR((AB15-Z15)/Z15,"")
B16: 销售量 | C16: 英茂 | D16: UK | E16: 件 | F16: =H16+J16+L16+N16+P16+R16+T16+V16+X16+Z16+AB16+AD16 -> 0 | G16: =IFERROR(F16/F$13,0) -> 0 | I16: =IFERROR(H16/#REF!,"") | K16: =IFERROR(J16/#REF!,"") | M16: =IFERROR(L16/#REF!,"") | O16: =IFERROR(N16/#REF!,"") | Q16: =IFERROR(P16/#REF!,"") | S16: =IFERROR(R16/#REF!,"") | U16: =IFERROR(T16/#REF!,"") | W16: =IFERROR(V16/#REF!,"") | Y16: =IFERROR(X16/#REF!,"") | AA16: =IFERROR(Z16/#REF!,"") | AC16: =IFERROR(AB16/#REF!,"") | AE16: =IFERROR(AD16/#REF!,"") | AF16: =IFERROR((J16-H16)/H16,"") | AG16: =IFERROR((L16-J16)/J16,"") | AH16: =IFERROR((N16-L16)/L16,"") | AI16: =IFERROR((P16-N16)/N16,"") | AJ16: =IFERROR((R16-P16)/P16,"") | AK16: =IFERROR((T16-R16)/R16,"") | AL16: =IFERROR((V16-T16)/T16,"") | AM16: =IFERROR((X16-V16)/V16,"") | AN16: =IFERROR((Z16-X16)/X16,"") | AO16: =IFERROR((AB16-Z16)/Z16,"")
B17: 销售量 | C17: 字同 | D17: UK | E17: 件 | F17: =H17+J17+L17+N17+P17+R17+T17+V17+X17+Z17+AB17+AD17 -> 0 | G17: =IFERROR(F17/F$13,0) -> 0 | I17: =IFERROR(H17/#REF!,"") | K17: =IFERROR(J17/#REF!,"") | M17: =IFERROR(L17/#REF!,"") | O17: =IFERROR(N17/#REF!,"") | Q17: =IFERROR(P17/#REF!,"") | S17: =IFERROR(R17/#REF!,"") | U17: =IFERROR(T17/#REF!,"") | W17: =IFERROR(V17/#REF!,"") | Y17: =IFERROR(X17/#REF!,"") | AA17: =IFERROR(Z17/#REF!,"") | AC17: =IFERROR(AB17/#REF!,"") | AE17: =IFERROR(AD17/#REF!,"") | AF17: =IFERROR((J17-H17)/H17,"") | AG17: =IFERROR((L17-J17)/J17,"") | AH17: =IFERROR((N17-L17)/L17,"") | AI17: =IFERROR((P17-N17)/N17,"") | AJ17: =IFERROR((R17-P17)/P17,"") | AK17: =IFERROR((T17-R17)/R17,"") | AL17: =IFERROR((V17-T17)/T17,"") | AM17: =IFERROR((X17-V17)/V17,"") | AN17: =IFERROR((Z17-X17)/X17,"") | AO17: =IFERROR((AB17-Z17)/Z17,"")
B18: 销售量 | C18: 起的快 | D18: UK | E18: 件 | F18: =H18+J18+L18+N18+P18+R18+T18+V18+X18+Z18+AB18+AD18 -> 0 | G18: =IFERROR(F18/F$13,0) -> 0 | I18: =IFERROR(H18/#REF!,"") | K18: =IFERROR(J18/#REF!,"") | M18: =IFERROR(L18/#REF!,"") | O18: =IFERROR(N18/#REF!,"") | Q18: =IFERROR(P18/#REF!,"") | S18: =IFERROR(R18/#REF!,"") | U18: =IFERROR(T18/#REF!,"") | W18: =IFERROR(V18/#REF!,"") | Y18: =IFERROR(X18/#REF!,"") | AA18: =IFERROR(Z18/#REF!,"") | AC18: =IFERROR(AB18/#REF!,"") | AE18: =IFERROR(AD18/#REF!,"") | AF18: =IFERROR((J18-H18)/H18,"") | AG18: =IFERROR((L18-J18)/J18,"") | AH18: =IFERROR((N18-L18)/L18,"") | AI18: =IFERROR((P18-N18)/N18,"") | AJ18: =IFERROR((R18-P18)/P18,"") | AK18: =IFERROR((T18-R18)/R18,"") | AL18: =IFERROR((V18-T18)/T18,"") | AM18: =IFERROR((X18-V18)/V18,"") | AN18: =IFERROR((Z18-X18)/X18,"") | AO18: =IFERROR((AB18-Z18)/Z18,"")
B19: 销售量 | C19: 昇新 | D19: UK | E19: 件 | F19: =H19+J19+L19+N19+P19+R19+T19+V19+X19+Z19+AB19+AD19 -> 0 | G19: =IFERROR(F19/F$13,0) -> 0 | I19: =IFERROR(H19/#REF!,"") | K19: =IFERROR(J19/#REF!,"") | M19: =IFERROR(L19/#REF!,"") | O19: =IFERROR(N19/#REF!,"") | Q19: =IFERROR(P19/#REF!,"") | S19: =IFERROR(R19/#REF!,"") | U19: =IFERROR(T19/#REF!,"") | W19: =IFERROR(V19/#REF!,"") | Y19: =IFERROR(X19/#REF!,"") | AA19: =IFERROR(Z19/#REF!,"") | AC19: =IFERROR(AB19/#REF!,"") | AE19: =IFERROR(AD19/#REF!,"") | AF19: =IFERROR((J19-H19)/H19,"") | AG19: =IFERROR((L19-J19)/J19,"") | AH19: =IFERROR((N19-L19)/L19,"") | AI19: =IFERROR((P19-N19)/N19,"") | AJ19: =IFERROR((R19-P19)/P19,"") | AK19: =IFERROR((T19-R19)/R19,"") | AL19: =IFERROR((V19-T19)/T19,"") | AM19: =IFERROR((X19-V19)/V19,"") | AN19: =IFERROR((Z19-X19)/X19,"") | AO19: =IFERROR((AB19-Z19)/Z19,"")
B20: 销售量 | C20: NOTTAC | D20: UK | E20: 件 | F20: =H20+J20+L20+N20+P20+R20+T20+V20+X20+Z20+AB20+AD20 -> 0 | G20: =IFERROR(F20/F$13,0) -> 0 | I20: =IFERROR(H20/#REF!,"") | K20: =IFERROR(J20/#REF!,"") | M20: =IFERROR(L20/#REF!,"") | O20: =IFERROR(N20/#REF!,"") | Q20: =IFERROR(P20/#REF!,"") | S20: =IFERROR(R20/#REF!,"") | U20: =IFERROR(T20/#REF!,"") | W20: =IFERROR(V20/#REF!,"") | Y20: =IFERROR(X20/#REF!,"") | AA20: =IFERROR(Z20/#REF!,"") | AC20: =IFERROR(AB20/#REF!,"") | AE20: =IFERROR(AD20/#REF!,"") | AF20: =IFERROR((J20-H20)/H20,"") | AG20: =IFERROR((L20-J20)/J20,"") | AH20: =IFERROR((N20-L20)/L20,"") | AI20: =IFERROR((P20-N20)/N20,"") | AJ20: =IFERROR((R20-P20)/P20,"") | AK20: =IFERROR((T20-R20)/R20,"") | AL20: =IFERROR((V20-T20)/T20,"") | AM20: =IFERROR((X20-V20)/V20,"") | AN20: =IFERROR((Z20-X20)/X20,"") | AO20: =IFERROR((AB20-Z20)/Z20,"")
B21: 销售量 | C21: Ledvia | D21: UK | E21: 件 | F21: =H21+J21+L21+N21+P21+R21+T21+V21+X21+Z21+AB21+AD21 -> 0 | G21: =IFERROR(F21/F$13,0) -> 0 | I21: =IFERROR(H21/#REF!,"") | K21: =IFERROR(J21/#REF!,"") | M21: =IFERROR(L21/#REF!,"") | O21: =IFERROR(N21/#REF!,"") | Q21: =IFERROR(P21/#REF!,"") | S21: =IFERROR(R21/#REF!,"") | U21: =IFERROR(T21/#REF!,"") | W21: =IFERROR(V21/#REF!,"") | Y21: =IFERROR(X21/#REF!,"") | AA21: =IFERROR(Z21/#REF!,"") | AC21: =IFERROR(AB21/#REF!,"") | AE21: =IFERROR(AD21/#REF!,"")
A22: 净销售量 | B22: 退款量 | D22: 合计 | E22: 件 | F22: =H22+J22+L22+N22+P22+R22+T22+V22+X22+Z22+AB22+AD22 -> 0 | G22: =IFERROR(F22/F$13,0) -> 0 | I22: =IFERROR(H22/#REF!,"") | K22: =IFERROR(J22/#REF!,"") | M22: =IFERROR(L22/#REF!,"") | O22: =IFERROR(N22/#REF!,"") | Q22: =IFERROR(P22/#REF!,"") | S22: =IFERROR(R22/#REF!,"") | U22: =IFERROR(T22/#REF!,"") | W22: =IFERROR(V22/#REF!,"") | Y22: =IFERROR(X22/#REF!,"") | AA22: =IFERROR(Z22/#REF!,"") | AC22: =IFERROR(AB22/#REF!,"") | AE22: =IFERROR(AD22/#REF!,"") | AF22: =IFERROR((J22-H22)/H22,"") | AG22: =IFERROR((L22-J22)/J22,"") | AH22: =IFERROR((N22-L22)/L22,"") | AI22: =IFERROR((P22-N22)/N22,"") | AJ22: =IFERROR((R22-P22)/P22,"") | AK22: =IFERROR((T22-R22)/R22,"") | AL22: =IFERROR((V22-T22)/T22,"") | AM22: =IFERROR((X22-V22)/V22,"") | AN22: =IFERROR((Z22-X22)/X22,"") | AO22: =IFERROR((AB22-Z22)/Z22,"")
B23: 退款量 | C23: 特米 | D23: UK | E23: 件 | F23: =H23+J23+L23+N23+P23+R23+T23+V23+X23+Z23+AB23+AD23 -> 0 | G23: =IFERROR(F23/F$13,0) -> 0 | I23: =IFERROR(H23/#REF!,"") | K23: =IFERROR(J23/#REF!,"") | M23: =IFERROR(L23/#REF!,"") | O23: =IFERROR(N23/#REF!,"") | Q23: =IFERROR(P23/#REF!,"") | S23: =IFERROR(R23/#REF!,"") | U23: =IFERROR(T23/#REF!,"") | W23: =IFERROR(V23/#REF!,"") | Y23: =IFERROR(X23/#REF!,"") | AA23: =IFERROR(Z23/#REF!,"") | AC23: =IFERROR(AB23/#REF!,"") | AE23: =IFERROR(AD23/#REF!,"") | AF23: =IFERROR((J23-H23)/H23,"") | AG23: =IFERROR((L23-J23)/J23,"") | AH23: =IFERROR((N23-L23)/L23,"") | AI23: =IFERROR((P23-N23)/N23,"") | AJ23: =IFERROR((R23-P23)/P23,"") | AK23: =IFERROR((T23-R23)/R23,"") | AL23: =IFERROR((V23-T23)/T23,"") | AM23: =IFERROR((X23-V23)/V23,"") | AN23: =IFERROR((Z23-X23)/X23,"") | AO23: =IFERROR((AB23-Z23)/Z23,"")
B24: 退款量 | C24: 英茂 | D24: DE | E24: 件 | F24: =H24+J24+L24+N24+P24+R24+T24+V24+X24+Z24+AB24+AD24 -> 0 | G24: =IFERROR(F24/F$13,0) -> 0 | I24: =IFERROR(H24/#REF!,"") | K24: =IFERROR(J24/#REF!,"") | M24: =IFERROR(L24/#REF!,"") | O24: =IFERROR(N24/#REF!,"") | Q24: =IFERROR(P24/#REF!,"") | S24: =IFERROR(R24/#REF!,"") | U24: =IFERROR(T24/#REF!,"") | W24: =IFERROR(V24/#REF!,"") | Y24: =IFERROR(X24/#REF!,"") | AA24: =IFERROR(Z24/#REF!,"") | AC24: =IFERROR(AB24/#REF!,"") | AE24: =IFERROR(AD24/#REF!,"") | AF24: =IFERROR((J24-H24)/H24,"") | AG24: =IFERROR((L24-J24)/J24,"") | AH24: =IFERROR((N24-L24)/L24,"") | AI24: =IFERROR((P24-N24)/N24,"") | AJ24: =IFERROR((R24-P24)/P24,"") | AK24: =IFERROR((T24-R24)/R24,"") | AL24: =IFERROR((V24-T24)/T24,"") | AM24: =IFERROR((X24-V24)/V24,"") | AN24: =IFERROR((Z24-X24)/X24,"") | AO24: =IFERROR((AB24-Z24)/Z24,"")
B25: 退款量 | C25: 英茂 | D25: UK | E25: 件 | F25: =H25+J25+L25+N25+P25+R25+T25+V25+X25+Z25+AB25+AD25 -> 0 | G25: =IFERROR(F25/F$13,0) -> 0 | I25: =IFERROR(H25/#REF!,"") | K25: =IFERROR(J25/#REF!,"") | M25: =IFERROR(L25/#REF!,"") | O25: =IFERROR(N25/#REF!,"") | Q25: =IFERROR(P25/#REF!,"") | S25: =IFERROR(R25/#REF!,"") | U25: =IFERROR(T25/#REF!,"") | W25: =IFERROR(V25/#REF!,"") | Y25: =IFERROR(X25/#REF!,"") | AA25: =IFERROR(Z25/#REF!,"") | AC25: =IFERROR(AB25/#REF!,"") | AE25: =IFERROR(AD25/#REF!,"") | AF25: =IFERROR((J25-H25)/H25,"") | AG25: =IFERROR((L25-J25)/J25,"") | AH25: =IFERROR((N25-L25)/L25,"") | AI25: =IFERROR((P25-N25)/N25,"") | AJ25: =IFERROR((R25-P25)/P25,"") | AK25: =IFERROR((T25-R25)/R25,"") | AL25: =IFERROR((V25-T25)/T25,"") | AM25: =IFERROR((X25-V25)/V25,"") | AN25: =IFERROR((Z25-X25)/X25,"") | AO25: =IFERROR((AB25-Z25)/Z25,"")
B26: 退款量 | C26: 字同 | D26: UK | E26: 件 | F26: =H26+J26+L26+N26+P26+R26+T26+V26+X26+Z26+AB26+AD26 -> 0 | G26: =IFERROR(F26/F$13,0) -> 0 | I26: =IFERROR(H26/#REF!,"") | K26: =IFERROR(J26/#REF!,"") | M26: =IFERROR(L26/#REF!,"") | O26: =IFERROR(N26/#REF!,"") | Q26: =IFERROR(P26/#REF!,"") | S26: =IFERROR(R26/#REF!,"") | U26: =IFERROR(T26/#REF!,"") | W26: =IFERROR(V26/#REF!,"") | Y26: =IFERROR(X26/#REF!,"") | AA26: =IFERROR(Z26/#REF!,"") | AC26: =IFERROR(AB26/#REF!,"") | AE26: =IFERROR(AD26/#REF!,"") | AF26: =IFERROR((J26-H26)/H26,"") | AG26: =IFERROR((L26-J26)/J26,"") | AH26: =IFERROR((N26-L26)/L26,"") | AI26: =IFERROR((P26-N26)/N26,"") | AJ26: =IFERROR((R26-P26)/P26,"") | AK26: =IFERROR((T26-R26)/R26,"") | AL26: =IFERROR((V26-T26)/T26,"") | AM26: =IFERROR((X26-V26)/V26,"") | AN26: =IFERROR((Z26-X26)/X26,"") | AO26: =IFERROR((AB26-Z26)/Z26,"")
B27: 退款量 | C27: 起的快 | D27: UK | E27: 件 | F27: =H27+J27+L27+N27+P27+R27+T27+V27+X27+Z27+AB27+AD27 -> 0 | G27: =IFERROR(F27/F$13,0) -> 0 | I27: =IFERROR(H27/#REF!,"") | K27: =IFERROR(J27/#REF!,"") | M27: =IFERROR(L27/#REF!,"") | O27: =IFERROR(N27/#REF!,"") | Q27: =IFERROR(P27/#REF!,"") | S27: =IFERROR(R27/#REF!,"") | U27: =IFERROR(T27/#REF!,"") | W27: =IFERROR(V27/#REF!,"") | Y27: =IFERROR(X27/#REF!,"") | AA27: =IFERROR(Z27/#REF!,"") | AC27: =IFERROR(AB27/#REF!,"") | AE27: =IFERROR(AD27/#REF!,"") | AF27: =IFERROR((J27-H27)/H27,"") | AG27: =IFERROR((L27-J27)/J27,"") | AH27: =IFERROR((N27-L27)/L27,"") | AI27: =IFERROR((P27-N27)/N27,"") | AJ27: =IFERROR((R27-P27)/P27,"") | AK27: =IFERROR((T27-R27)/R27,"") | AL27: =IFERROR((V27-T27)/T27,"") | AM27: =IFERROR((X27-V27)/V27,"") | AN27: =IFERROR((Z27-X27)/X27,"") | AO27: =IFERROR((AB27-Z27)/Z27,"")
B28: 退款量 | C28: 昇新 | D28: UK | E28: 件 | F28: =H28+J28+L28+N28+P28+R28+T28+V28+X28+Z28+AB28+AD28 -> 0 | G28: =IFERROR(F28/F$13,0) -> 0 | I28: =IFERROR(H28/#REF!,"") | K28: =IFERROR(J28/#REF!,"") | M28: =IFERROR(L28/#REF!,"") | O28: =IFERROR(N28/#REF!,"") | Q28: =IFERROR(P28/#REF!,"") | S28: =IFERROR(R28/#REF!,"") | U28: =IFERROR(T28/#REF!,"") | W28: =IFERROR(V28/#REF!,"") | Y28: =IFERROR(X28/#REF!,"") | AA28: =IFERROR(Z28/#REF!,"") | AC28: =IFERROR(AB28/#REF!,"") | AE28: =IFERROR(AD28/#REF!,"") | AF28: =IFERROR((J28-H28)/H28,"") | AG28: =IFERROR((L28-J28)/J28,"") | AH28: =IFERROR((N28-L28)/L28,"") | AI28: =IFERROR((P28-N28)/N28,"") | AJ28: =IFERROR((R28-P28)/P28,"") | AK28: =IFERROR((T28-R28)/R28,"") | AL28: =IFERROR((V28-T28)/T28,"") | AM28: =IFERROR((X28-V28)/V28,"") | AN28: =IFERROR((Z28-X28)/X28,"") | AO28: =IFERROR((AB28-Z28)/Z28,"")
B29: 退款量 | C29: NOTTAC | D29: UK | E29: 件 | F29: =H29+J29+L29+N29+P29+R29+T29+V29+X29+Z29+AB29+AD29 -> 0 | G29: =IFERROR(F29/F$13,0) -> 0 | I29: =IFERROR(H29/#REF!,"") | K29: =IFERROR(J29/#REF!,"") | M29: =IFERROR(L29/#REF!,"") | O29: =IFERROR(N29/#REF!,"") | Q29: =IFERROR(P29/#REF!,"") | S29: =IFERROR(R29/#REF!,"") | U29: =IFERROR(T29/#REF!,"") | W29: =IFERROR(V29/#REF!,"") | Y29: =IFERROR(X29/#REF!,"") | AA29: =IFERROR(Z29/#REF!,"") | AC29: =IFERROR(AB29/#REF!,"") | AE29: =IFERROR(AD29/#REF!,"") | AF29: =IFERROR((J29-H29)/H29,"") | AG29: =IFERROR((L29-J29)/J29,"") | AH29: =IFERROR((N29-L29)/L29,"") | AI29: =IFERROR((P29-N29)/N29,"") | AJ29: =IFERROR((R29-P29)/P29,"") | AK29: =IFERROR((T29-R29)/R29,"") | AL29: =IFERROR((V29-T29)/T29,"") | AM29: =IFERROR((X29-V29)/V29,"") | AN29: =IFERROR((Z29-X29)/X29,"") | AO29: =IFERROR((AB29-Z29)/Z29,"")
B30: 退款量 | C30: Ledvia | D30: UK | E30: 件 | F30: =H30+J30+L30+N30+P30+R30+T30+V30+X30+Z30+AB30+AD30 -> 0 | G30: =IFERROR(F30/F$13,0) -> 0 | I30: =IFERROR(H30/#REF!,"") | K30: =IFERROR(J30/#REF!,"") | M30: =IFERROR(L30/#REF!,"") | O30: =IFERROR(N30/#REF!,"") | Q30: =IFERROR(P30/#REF!,"") | S30: =IFERROR(R30/#REF!,"") | U30: =IFERROR(T30/#REF!,"") | W30: =IFERROR(V30/#REF!,"") | Y30: =IFERROR(X30/#REF!,"") | AA30: =IFERROR(Z30/#REF!,"") | AC30: =IFERROR(AB30/#REF!,"") | AE30: =IFERROR(AD30/#REF!,"")
A31: 毛利率 | E31: % | G31: =IFERROR(F31/#REF!,"") | H31: =IFERROR(1-#REF!/#REF!,"") | I31: =IFERROR(H31/#REF!,"") | J31: =IFERROR(1-#REF!/#REF!,"") | K31: =IFERROR(J31/#REF!,"") | L31: =IFERROR(1-#REF!/#REF!,"") | M31: =IFERROR(L31/#REF!,"") | N31: =IFERROR(1-#REF!/#REF!,"") | O31: =IFERROR(N31/#REF!,"") | P31: =IFERROR(1-#REF!/#REF!,"") | Q31: =IFERROR(P31/#REF!,"") | R31: =IFERROR(1-#REF!/#REF!,"") | S31: =IFERROR(R31/#REF!,"") | T31: =IFERROR(1-#REF!/#REF!,"") | U31: =IFERROR(T31/#REF!,"") | V31: =IFERROR(1-#REF!/#REF!,"") | W31: =IFERROR(V31/#REF!,"") | X31: =IFERROR(1-#REF!/#REF!,"") | Y31: =IFERROR(X31/#REF!,"") | Z31: =IFERROR(1-#REF!/#REF!,"") | AA31: =IFERROR(Z31/#REF!,"") | AB31: =IFERROR(1-#REF!/#REF!,"") | AC31: =IFERROR(AB31/#REF!,"") | AD31: =IFERROR(1-#REF!/#REF!,"") | AE31: =IFERROR(AD31/#REF!,"") | AF31: =IFERROR((J31-H31)/H31,"") | AG31: =IFERROR((L31-J31)/J31,"") | AH31: =IFERROR((N31-L31)/L31,"") | AI31: =IFERROR((P31-N31)/N31,"") | AJ31: =IFERROR((R31-P31)/P31,"") | AK31: =IFERROR((T31-R31)/R31,"") | AL31: =IFERROR((V31-T31)/T31,"") | AM31: =IFERROR((X31-V31)/V31,"") | AN31: =IFERROR((Z31-X31)/X31,"") | AO31: =IFERROR((AB31-Z31)/Z31,"") | AP31: =IFERROR((AD31-AB31)/AB31,"")
A32: 毛利率 | C32: 特米 | D32: UK | E32: % | F32: =H32+J32+L32+N32+P32+R32+T32+V32+X32+Z32+AB32+AD32 -> 0
A33: 毛利率 | C33: 英茂 | D33: DE | E33: % | F33: =H33+J33+L33+N33+P33+R33+T33+V33+X33+Z33+AB33+AD33 -> 0
A34: 毛利率 | C34: 英茂 | D34: UK | E34: % | F34: =H34+J34+L34+N34+P34+R34+T34+V34+X34+Z34+AB34+AD34 -> 0
A35: 毛利率 | C35: 字同 | D35: UK | E35: % | F35: =H35+J35+L35+N35+P35+R35+T35+V35+X35+Z35+AB35+AD35 -> 0
A36: 毛利率 | C36: 起的快 | D36: UK | E36: % | F36: =H36+J36+L36+N36+P36+R36+T36+V36+X36+Z36+AB36+AD36 -> 0
A37: 毛利率 | C37: 昇新 | D37: UK | E37: % | F37: =H37+J37+L37+N37+P37+R37+T37+V37+X37+Z37+AB37+AD37 -> 0
A38: 毛利率 | C38: NOTTAC | D38: UK | E38: % | F38: =H38+J38+L38+N38+P38+R38+T38+V38+X38+Z38+AB38+AD38 -> 0
A39: 毛利率 | C39: Ledvia | D39: UK | E39: % | F39: =H39+J39+L39+N39+P39+R39+T39+V39+X39+Z39+AB39+AD39 -> 0
A40: 经营收入 | C40: 合计 | E40: 元 | F40: =H40+J40+L40+N40+P40+R40+T40+V40+X40+Z40+AB40+AD40 -> 0 | G40: 、 | H40: =H41+H68 -> 0 | I40: =IFERROR(H40/#REF!,"") | J40: =J41+J68 -> 0 | K40: =IFERROR(J40/#REF!,"") | L40: =L41+L68 -> 0 | M40: =IFERROR(L40/#REF!,"") | N40: =N41+N68 -> 0 | O40: =IFERROR(N40/#REF!,"") | P40: =P41+P68 -> 0 | Q40: =IFERROR(P40/#REF!,"") | R40: =R41+R68 -> 0 | S40: =IFERROR(R40/#REF!,"") | T40: =T41+T68 -> 0 | U40: =IFERROR(T40/#REF!,"") | V40: =V41+V68 -> 0 | W40: =IFERROR(V40/#REF!,"") | X40: =X41+X68 -> 0 | Y40: =IFERROR(X40/#REF!,"") | Z40: =Z41+Z68 -> 0 | AA40: =IFERROR(Z40/#REF!,"") | AB40: =AB41+AB68 -> 0 | AC40: =IFERROR(AB40/#REF!,"") | AD40: =AD41+AD68 -> 0 | AE40: =IFERROR(AD40/#REF!,"") | AF40: =IFERROR((J40-H40)/H40,"") | AG40: =IFERROR((L40-J40)/J40,"") | AH40: =IFERROR((N40-L40)/L40,"") | AI40: =IFERROR((P40-N40)/N40,"") | AJ40: =IFERROR((R40-P40)/P40,"") | AK40: =IFERROR((T40-R40)/R40,"") | AL40: =IFERROR((V40-T40)/T40,"") | AM40: =IFERROR((X40-V40)/V40,"") | AN40: =IFERROR((Z40-X40)/X40,"") | AO40: =IFERROR((AB40-Z40)/Z40,"")
A41: 经营销售 | C41: 合计 | E41: 元 | F41: =H41+J41+L41+N41+P41+R41+T41+V41+X41+Z41+AB41+AD41 -> 0 | G41: =IFERROR(F41/#REF!,"") | H41: =H50+H59 -> 0 | I41: =IFERROR(H41/#REF!,"") | J41: =J50+J59 -> 0 | K41: =IFERROR(J41/#REF!,"") | L41: =L50+L59 -> 0 | M41: =IFERROR(L41/#REF!,"") | N41: =N50+N59 -> 0 | O41: =IFERROR(N41/#REF!,"") | P41: =P50+P59 -> 0 | Q41: =IFERROR(P41/#REF!,"") | R41: =R50+R59 -> 0 | S41: =IFERROR(R41/#REF!,"") | T41: =T50+T59 -> 0 | U41: =IFERROR(T41/#REF!,"") | V41: =V50+V59 -> 0 | W41: =IFERROR(V41/#REF!,"") | X41: =X50+X59 -> 0 | Y41: =IFERROR(X41/#REF!,"") | Z41: =Z50+Z59 -> 0 | AA41: =IFERROR(Z41/#REF!,"") | AB41: =AB50+AB59 -> 0 | AC41: =IFERROR(AB41/#REF!,"") | AD41: =AD50+AD59 -> 0 | AE41: =IFERROR(AD41/#REF!,"") | AF41: =IFERROR((J41-H41)/H41,"") | AG41: =IFERROR((L41-J41)/J41,"") | AH41: =IFERROR((N41-L41)/L41,"") | AI41: =IFERROR((P41-N41)/N41,"") | AJ41: =IFERROR((R41-P41)/P41,"") | AK41: =IFERROR((T41-R41)/R41,"") | AL41: =IFERROR((V41-T41)/T41,"") | AM41: =IFERROR((X41-V41)/V41,"") | AN41: =IFERROR((Z41-X41)/X41,"") | AO41: =IFERROR((AB41-Z41)/Z41,"")
A42: 经营销售 | C42: 特米 | D42: UK | E42: 元 | F42: =H42+J42+L42+N42+P42+R42+T42+V42+X42+Z42+AB42+AD42 -> 0 | G42: =IFERROR(F42/F$41,0) -> 0 | H42: =H51+H60 -> 0 | I42: =IFERROR(H42/H$41,0) -> 0 | J42: =J51+J60 -> 0 | L42: =L51+L60 -> 0 | N42: =N51+N60 -> 0 | P42: =P51+P60 -> 0 | R42: =R51+R60 -> 0 | T42: =T51+T60 -> 0 | V42: =V51+V60 -> 0 | X42: =X51+X60 -> 0 | Z42: =Z51+Z60 -> 0 | AB42: =AB51+AB60 -> 0 | AD42: =AD51+AD60 -> 0
A43: 经营销售 | C43: 英茂 | D43: DE | E43: 元 | F43: =H43+J43+L43+N43+P43+R43+T43+V43+X43+Z43+AB43+AD43 -> 0 | G43: =IFERROR(F43/F$41,0) -> 0 | H43: =H52+H61 -> 0 | I43: =IFERROR(H43/H$41,0) -> 0 | J43: =J52+J61 -> 0 | L43: =L52+L61 -> 0 | N43: =N52+N61 -> 0 | P43: =P52+P61 -> 0 | R43: =R52+R61 -> 0 | T43: =T52+T61 -> 0 | V43: =V52+V61 -> 0 | X43: =X52+X61 -> 0 | Z43: =Z52+Z61 -> 0 | AB43: =AB52+AB61 -> 0 | AD43: =AD52+AD61 -> 0
